Workbook

Sheet 宝
A1: |-编号---- | B1: |-英文---- | C1: |-日文---- | D1: |-翻译---- | E1: |-注释---- | F1: |-跳过---- | G1: |-拼音- | H1: |-拼音2- | I1: |-拼音3- | J1: |-拼音4- | K1: |-拼音5-
A2: N001 | B2: BULBASAUR | C2: フシギダネ | D2: 妙蛙种子 | G2: miao4 | H2: wa1 | I2: zhong3 | J2: zi
A3: N002 | B3: IVYSAUR | C3: フシギソウ | D3: 妙蛙草 | G3: miao4 | H3: wa1 | I3: cao3
A4: N003 | B4: VENUSAUR | C4: フシギバナ | D4: 妙蛙花 | G4: miao4 | H4: wa1 | I4: hua1
A5: N004 | B5: CHARMANDER | C5: ヒトカゲ | D5: 小火龙 | G5: xiao3 | H5: huo3 | I5: long2
A6: N005 | B6: CHARMELEON | C6: リザード | D6: 火恐龙 | G6: huo3 | H6: kong3 | I6: long2
A7: N006 | B7: CHARIZARD | C7: リザードン | D7: 喷火龙 | G7: pen1 | H7: huo3 | I7: long2
A8: N007 | B8: SQUIRTLE | C8: ゼニガメ | D8: 杰尼龟 | G8: jie2 | H8: ni2 | I8: gui1
A9: N008 | B9: WARTORTLE | C9: カメール | D9: 卡咪龟 | G9: ka3 | H9: mi1 | I9: gui1
A10: N009 | B10: BLASTOISE | C10: カメックス | D10: 水箭龟 | G10: shui3 | H10: jian4 | I10: gui1
A11: N010 | B11: CATERPIE | C11: キャタピー | D11: 绿毛虫 | G11: lv4 | H11: mao2 | I11: chong2
A12: N011 | B12: METAPOD | C12: トランセル | D12: 铁甲蛹 | G12: tie3 | H12: jia3 | I12: yong3
A13: N012 | B13: BUTTERFREE | C13: バタフリー | D13: 巴大蝶 | G13: ba1 | H13: da4 | I13: die2
A14: N013 | B14: WEEDLE | C14: ビードル | D14: 独角虫 | G14: du2 | H14: jiao3 | I14: chong2
... A16: N015 | B16: BEEDRILL | C16: スピアー | D16: 大针蜂 | G16: da4 | H16: zhen1 | I16: feng1
A17: N016 | B17: PIDGEY | C17: ポッポ | D17: 波波 | G17: bo1 | H17: bo1
A18: N017 | B18: PIDGEOTTO | C18: ピジョン | D18: 比比鸟 | G18: bi3 | H18: bi3 | I18: niao3
A19: N018 | B19: PIDGEOT | C19: ピジョット | D19: 大比鸟 | G19: da4 | H19: bi3 | I19: niao3
A20: N019 | B20: RATTATA | C20: コラッタ | D20: 小拉达 | G20: xiao3 | H20: la1 | I20: da2
A21: N020 | B21: RATICATE | C21: ラッタ | D21: 拉达 | G21: la1 | H21: da2
A22: N021 | B22: SPEAROW | C22: オニスズメ | D22: 烈雀 | G22: lie4 | H22: que4
A23: N022 | B23: FEAROW | C23: オニドリル | D23: 大嘴雀 | G23: da4 | H23: zui3 | I23: que4
A24: N023 | B24: EKANS | C24: アーボ | D24: 阿柏蛇 | G24: a1 | H24: bo2 | I24: she2
A25: N024 | B25: ARBOK | C25: アーボック | D25: 阿柏怪 | G25: a1 | H25: bo2 | I25: guai4
A26: N025 | B26: PIKACHU | C26: ピカチュウ | D26: 皮卡丘 | G26: pi2 | H26: ka3 | I26: qiu1
A27: N026 | B27: RAICHU | C27: ライチュウ | D27: 雷丘 | G27: lei2 | H27: qiu1
A28: N027 | B28: SANDSHREW | C28: サンド | D28: 穿山鼠 | G28: chuan1 | H28: shan1 | I28: shu3
A29: N028 | B29: SANDSLASH | C29: サンドパン | D29: 穿山王 | G29: chuan1 | H29: shan1 | I29: wang2
A30: N029 | B30: NIDORAN♀ | C30: ニドラン♀ | D30: 尼多兰 | G30: ni2 | H30: duo1 | I30: lan2
A31: N030 | B31: NIDORINA | C31: ニドリーナ | D31: 尼多娜 | G31: ni2 | H31: duo1 | I31: na4
A32: N031 | B32: NIDOQUEEN | C32: ニドクイン | D32: 尼多后 | G32: ni2 | H32: duo1 | I32: hou4
A33: N032 | B33: NIDORAN♂ | C33: ニドラン♂ | D33: 尼多朗 | G33: ni2 | H33: duo1 | I33: lang3
A34: N033 | B34: NIDORINO | C34: ニドリーノ | D34: 尼多力诺 | G34: ni2 | H34: duo1 | I34: li4 | J34: nuo4
A35: N034 | B35: NIDOKING | C35: ニドキング | D35: 尼多王 | G35: ni2 | H35: duo1 | I35: wang2
A36: N035 | B36: CLEFAIRY | C36: ピッピ | D36: 皮皮 | G36: pi2 | H36: pi2
A37: N036 | B37: CLEFABLE | C37: ピクシー | D37: 皮可西 | G37: pi2 | H37: ke3 | I37: xi1
A38: N037 | B38: VULPIX | C38: ロコン | D38: 六尾 | G38: liu4 | H38: wei3
A39: N038 | B39: NINETALES | C39: キュウコン | D39: 九尾 | G39: jiu3 | H39: wei3
A40: N039 | B40: JIGGLYPUFF | C40: プリン | D40: 胖丁 | G40: pang4 | H40: ding1
A41: N040 | B41: WIGGLYTUFF | C41: プクリン | D41: 胖可丁 | G41: pang4 | H41: ke3 | I41: ding1
A42: N041 | B42: ZUBAT | C42: ズバット | D42: 超音蝠 | G42: chao1 | H42: yin1 | I42: fu2
A43: N042 | B43: GOLBAT | C43: ゴルバット | D43: 大嘴蝠 | G43: da4 | H43: zui3 | I43: fu2
A44: N043 | B44: ODDISH | C44: ナゾノクサ | D44: 走路草 | G44: zou3 | H44: lu4 | I44: cao3
A45: N044 | B45: GLOOM | C45: クサイハナ | D45: 臭臭花 | G45: chou4 | H45: chou4 | I45: hua1
A46: N045 | B46: VILEPLUME | C46: ラフレシア | D46: 霸王花 | G46: ba4 | H46: wang2 | I46: hua1
A47: N046 | B47: PARAS | C47: パラス | D47: 派拉斯 | G47: pai4 | H47: la1 | I47: si1
A48: N047 | B48: PARASECT | C48: パラセクト | D48: 派拉斯特 | G48: pai4 | H48: la1 | I48: si1 | J48: te4
A49: N048 | B49: VENONAT | C49: コンパン | D49: 毛球 | G49: mao2 | H49: qiu2
A50: N049 | B50: VENOMOTH | C50: モルフォン | D50: 摩鲁蛾 | G50: mo2 | H50: lu3 | I50: e2
A51: N050 | B51: DIGLETT | C51: ディグダ | D51: 地鼠 | G51: di4 | H51: shu3
A52: N051 | B52: DUGTRIO | C52: ダグトリオ | D52: 三地鼠 | G52: san1 | H52: di4 | I52: shu3
A53: N052 | B53: MEOWTH | C53: ニャース | D53: 喵喵 | G53: miao1 | H53: miao1
A54: N053 | B54: PERSIAN | C54: ペルシアン | D54: 猫老大 | G54: mao1 | H54: lao3 | I54: da4
A55: N054 | B55: PSYDUCK | C55: コダック | D55: 可达鸭 | G55: ke3 | H55: da2 | I55: ya1
A56: N055 | B56: GOLDUCK | C56: ゴルダック | D56: 哥达鸭 | G56: ge1 | H56: da2 | I56: ya1
A57: N056 | B57: MANKEY | C57: マンキー | D57: 猴怪 | G57: hou2 | H57: guai4
A58: N057 | B58: PRIMEAPE | C58: オコリザル | D58: 火暴猴 | G58: huo3 | H58: bao4 | I58: hou2
A59: N058 | B59: GROWLITHE | C59: ガーディ | D59: 卡蒂狗 | G59: ka3 | H59: di4 | I59: gou3
A60: N059 | B60: ARCANINE | C60: ウインディ | D60: 风速狗 | G60: feng1 | H60: su4 | I60: gou3
A61: N060 | B61: POLIWAG | C61: ニョロモ | D61: 蚊香蝌蚪 | G61: wen2 | H61: xiang1 | I61: ke1 | J61: dou3
A62: N061 | B62: POLIWHIRL | C62: ニョロゾ | D62: 蚊香君 | G62: wen2 | H62: xiang1 | I62: jun1
A63: N062 | B63: POLIWRATH | C63: ニョロボン | D63: 蚊香泳士 | G63: wen2 | H63: xiang1 | I63: yong3 | J63: shi4
A64: N063 | B64: ABRA | C64: ケーシィ | D64: 凯西 | G64: kai3 | H64: xi1
A65: N064 | B65: KADABRA | C65: ユンゲラー | D65: 勇基拉 | G65: yong3 | H65: ji1 | I65: la1
A66: N065 | B66: ALAKAZAM | C66: フーディン | D66: 胡地 | G66: hu2 | H66: di4
A67: N066 | B67: MACHOP | C67: ワンリキー | D67: 腕力 | G67: wan4 | H67: li4
A68: N067 | B68: MACHOKE | C68: ゴーリキー | D68: 豪力 | G68: hao2 | H68: li4
A69: N068 | B69: MACHAMP | C69: カイリキー | D69: 怪力 | G69: guai4 | H69: li4
A70: N069 | B70: BELLSPROUT | C70: マダツボミ | D70: 喇叭芽 | G70: la3 | H70: ba1 | I70: ya2
A71: N070 | B71: WEEPINBELL | C71: ウツドン | D71: 口呆花 | G71: kou3 | H71: dai1 | I71: hua1
A72: N071 | B72: VICTREEBEL | C72: ウツボット | D72: 大食花 | G72: da4 | H72: shi2 | I72: hua1
A73: N072 | B73: TENTACOOL | C73: メノクラゲ | D73: 玛瑙水母 | G73: ma3 | H73: nao3 | I73: shui3 | J73: mu3
A74: N073 | B74: TENTACRUEL | C74: ドククラゲ | D74: 毒刺水母 | G74: du2 | H74: ci4 | I74: shui3 | J74: mu3
A75: N074 | B75: GEODUDE | C75: イシツブテ | D75: 小拳石 | G75: xiao3 | H75: quan2 | I75: shi2
A76: N075 | B76: GRAVELER | C76: ゴローン | D76: 隆隆石 | G76: long2 | H76: long2 | I76: shi2
A77: N076 | B77: GOLEM | C77: ゴローニャ | D77: 隆隆岩 | G77: long2 | H77: long2 | I77: yan2
A78: N077 | B78: PONYTA | C78: ポニータ | D78: 小火马 | G78: xiao3 | H78: huo3 | I78: ma3
A79: N078 | B79: RAPIDASH | C79: ギャロップ | D79: 烈焰马 | G79: lie4 | H79: yan4 | I79: ma3
A80: N079 | B80: SLOWPOKE | C80: ヤドン | D80: 呆呆兽 | G80: dai1 | H80: dai1 | I80: shou4
A81: N080 | B81: SLOWBRO | C81: ヤドラン | D81: 呆壳兽 | G81: dai1 | H81: ke2 | I81: shou4
A82: N081 | B82: MAGNEMITE | C82: コイル | D82: 小磁怪 | G82: xiao3 | H82: ci2 | I82: guai4
A83: N082 | B83: MAGNETON | C83: レアコイル | D83: 三合一磁怪 | G83: san1 | H83: he2 | I83: yi1 | J83: ci2 | K83: guai4
A84: N083 | B84: FARFETCH'D | C84: カモネギ | D84: 大葱鸭 | G84: da4 | H84: cong1 | I84: ya1
A85: N084 | B85: DODUO | C85: ドードー | D85: 嘟嘟 | G85: du1 | H85: du1
A86: N085 | B86: DODRIO | C86: ドードリオ | D86: 嘟嘟利 | G86: du1 | H86: du1 | I86: li4
A87: N086 | B87: SEEL | C87: パウワウ | D87: 小海狮 | G87: xiao3 | H87: hai3 | I87: shi1
A88: N087 | B88: DEWGONG | C88: ジュゴン | D88: 白海狮 | G88: bai2 | H88: hai3 | I88: shi1
A89: N088 | B89: GRIMER | C89: ベトベター | D89: 臭泥 | G89: chou4 | H89: ni2
A90: N089 | B90: MUK | C90: ベトベトン | D90: 臭臭泥 | G90: chou4 | H90: chou4 | I90: ni2
A91: N090 | B91: SHELLDER | C91: シェルダー | D91: 大舌贝 | G91: da4 | H91: she2 | I91: bei4
A92: N091 | B92: CLOYSTER | C92: パルシェン | D92: 刺甲贝 | G92: ci4 | H92: jia3 | I92: bei4
A93: N092 | B93: GASTLY | C93: ゴース | D93: 鬼斯 | G93: gui3 | H93: si1
A94: N093 | B94: HAUNTER | C94: ゴースト | D94: 鬼斯通 | G94: gui3 | H94: si1 | I94: tong1
A95: N094 | B95: GENGAR | C95: ゲンガー | D95: 耿鬼 | G95: geng3 | H95: gui3
A96: N095 | B96: ONIX | C96: イワーク | D96: 大岩蛇 | G96: da4 | H96: yan2 | I96: she2
A97: N096 | B97: DROWZEE | C97: スリープ | D97: 催眠貘 | G97: cui1 | H97: mian2 | I97: mo4
A98: N097 | B98: HYPNO | C98: スリーパー | D98: 引梦貘人 | G98: yin3 | H98: meng4 | I98: mo4 | J98: ren2
A99: N098 | B99: KRABBY | C99: クラブ | D99: 大钳蟹 | G99: da4 | H99: qian2 | I99: xie4
A100: N099 | B100: KINGLER | C100: キングラー | D100: 巨钳蟹 | G100: ju4 | H100: qian2 | I100: xie4
A101: N100 | B101: VOLTORB | C101: ビリリダマ | D101: 霹雳电球 | G101: pi1 | H101: li4 | I101: dian4 | J101: qiu2
...

Sheet 训
A1: |-编号---- | B1: |-英文---- | C1: |-日文---- | D1: |-翻译---- | E1: |-注释---- | F1: |-跳过---- | G1: 版本
A2: P2DL_001$ | B2: FALKNER | C2: ハヤト | D2: 阿速 | H2: FALKNER
A3: P2DL_002$ | B3: WHITNEY | C3: アカネ | D3: 小茜 | H3: WHITNEY
A4: P2DL_003$ | B4: BUGSY | C4: ツクシ | D4: 阿笔 | H4: BUGSY
A5: P2DL_004$ | B5: MORTY | C5: マツバ | D5: 松叶 | H5: MORTY
A6: P2DL_005$ | B6: PRYCE | C6: ヤナギ | D6: 柳伯 | H6: PRYCE
A7: P2DL_006$ | B7: JASMINE | C7: ミカン | D7: 阿蜜 | H7: JASMINE
A8: P2DL_007$ | B8: CHUCK | C8: シジマ | D8: 阿四 | H8: CHUCK
A9: P2DL_008$ | B9: CLAIR | C9: イブキ | D9: 小椿 | H9: CLAIR
A10: P2DL_009$ | B10: ? | C10: ? | D10: ? | E10: 没用的符号，忽略 | F10: Y | H10: ?
A11: P2DL_009_00$ | B11: =B10 -> ? | C11: =C10 -> ? | D11: =D10 -> ? | H11: ?
A12: P2DL_009_01$ | B12: =B10 -> ? | C12: =C10 -> ? | D12: =D10 -> ? | H12: ?
A13: P2DL_009_02$ | B13: =B10 -> ? | C13: =C10 -> ? | D13: =D10 -> ? | H13: ?
A14: P2DL_009_03$ | B14: =B10 -> ? | C14: =C10 -> ? | D14: =D10 -> ? | H14: ?
A15: P2DL_009_04$ | B15: =B10 -> ? | C15: =C10 -> ? | D15: =D10 -> ? | H15: ?
A16: P2DL_009_05$ | B16: =B10 -> ? | C16: =C10 -> ? | D16: =D10 -> ? | H16: ?
A17: P2DL_009_06$ | B17: =B10 -> ? | C17: =C10 -> ? | D17: =D10 -> ? | H17: ?
A18: P2DL_009_07$ | B18: =B10 -> ? | C18: =C10 -> ? | D18: =D10 -> ? | H18: ?
A19: P2DL_009_08$ | B19: =B10 -> ? | C19: =C10 -> ? | D19: =D10 -> ? | H19: ?
A20: P2DL_009_09$ | B20: =B10 -> ? | C20: =C10 -> ? | D20: =D10 -> ? | H20: ?
A21: P2DL_009_10$ | B21: =B10 -> ? | C21: =C10 -> ? | D21: =D10 -> ? | H21: ?
A22: P2DL_009_11$ | B22: =B10 -> ? | C22: =C10 -> ? | D22: =D10 -> ? | H22: ?
A23: P2DL_009_12$ | B23: =B10 -> ? | C23: =C10 -> ? | D23: =D10 -> ? | H23: ?
A24: P2DL_009_13$ | B24: =B10 -> ? | C24: =C10 -> ? | D24: =D10 -> ? | H24: ?
A25: P2DL_011$ | B25: WILL | C25: イツキ | D25: 一树 | H25: WILL
A26: P2DL_012$ | B26: CAL | C26: ヒカル | D26: 光亮 | E26: 主角克隆 | H26: CAL
A27: P2DL_012_00$ | B27: =B26 -> CAL | C27: =C26 -> ヒカル | D27: =D26 -> 光亮 | H27: CAL
A28: P2DL_012_01$ | B28: =B26 -> CAL | C28: =C26 -> ヒカル | D28: =D26 -> 光亮 | H28: CAL
A29: P2DL_013$ | B29: BRUNO | C29: シバ | D29: 希巴 | H29: BRUNO
A30: P2DL_014$ | B30: KAREN | C30: カリン | D30: 梨花 | H30: KAREN
A31: P2DL_015$ | B31: KOGA | C31: キョウ | D31: 阿桔 | H31: KOGA
A32: P2DL_016$ | B32: LANCE | C32: ワタル | D32: 阿渡 | H32: LANCE
A33: P2DL_017$ | B33: BROCK | C33: タケシ | D33: 小刚 | H33: BROCK
A34: P2DL_018$ | B34: MISTY | C34: カスミ | D34: 小霞 | H34: MISTY
A35: P2DL_019$ | B35: LT.SURGE | C35: マチス | D35: 马志士 | H35: LT.SURGE
A36: P2DL_020$ | B36: ROSS | C36: ヤスフミ | D36: 康文 | H36: ROSS
A37: P2DL_020_00$ | B37: MITCH | C37: ノブヒロ | D37: 信弘 | H37: MITCH
A38: P2DL_020_01$ | B38: JED | C38: フジオ | D38: 不二雄 | H38: JED
A39: P2DL_020_02$ | B39: MARC | C39: カネオ | D39: 兼生 | H39: MARC
A40: P2DL_020_03$ | B40: RICH | C40: シンタロウ | D40: 真太郎 | H40: RICH
... A47: P2DL_022_04$ | B47: IAN | C47: ショウヘイ | D47: 翔平 | H47: IAN
A48: P2DL_022_05$ | B48: =B42 -> JOEY | C48: =C42 -> ゴロウ | D48: =D42 -> 五郎 | H48: JOEY
A49: P2DL_022_06$ | B49: =B42 -> JOEY | C49: =C42 -> ゴロウ | D49: =D42 -> 五郎 | H49: JOEY
A50: P2DL_022_07$ | B50: WARREN | C50: ヒロノブ | D50: 广宣 | H50: WARREN
A51: P2DL_022_08$ | B51: JIMMY | C51: ケンタ | D51: 健太 | H51: JIMMY
A52: P2DL_022_09$ | B52: OWEN | C52: ヒロユキ | D52: 浩之 | H52: OWEN
A53: P2DL_022_10$ | B53: JASON | C53: トシヒコ | D53: 裕介 | H53: JASON
A54: P2DL_022_11$ | B54: =B42 -> JOEY | C54: =C42 -> ゴロウ | D54: =D42 -> 五郎 | G54: CR
A55: P2DL_022_12$ | B55: =B42 -> JOEY | C55: =C42 -> ゴロウ | D55: =D42 -> 五郎 | G55: CR
A56: P2DL_023$ | B56: JACK | C56: シュウイチ | D56: 修一 | H56: JACK
A57: P2DL_023_00$ | B57: KIPP | C57: トモユキ | D57: 智行 | H57: KIPP
A58: P2DL_023_01$ | B58: ALAN | C58: マナブ | D58: 学武 | H58: ALAN
A59: P2DL_023_02$ | B59: JOHNNY | C59: キミヤス | D59: 公康 | H59: JOHNNY
A60: P2DL_023_03$ | B60: DANNY | C60: ノリタカ | D60: 典孝 | H60: DANNY
A61: P2DL_023_04$ | B61: TOMMY | C61: カズヒデ | D61: 和秀 | H61: TOMMY
A62: P2DL_023_05$ | B62: DUDLEY | C62: ケンジ | D62: 研二 | H62: DUDLEY
A63: P2DL_023_06$ | B63: JOE | C63: シンスケ | D63: 伸介 | H63: JOE
A64: P2DL_023_07$ | B64: BILLY | C64: キイチ | D64: 旗一 | H64: BILLY
A65: P2DL_023_08$ | B65: CHAD | C65: クリオ | D65: 板栗 | H65: CHAD
A66: P2DL_023_09$ | B66: NATE | C66: マサユキ | D66: 真幸 | H66: NATE
A67: P2DL_023_10$ | B67: RICKY | C67: アツシ | D67: 敦史 | H67: RICKY
A68: P2DL_023_11$ | B68: =B56 -> JACK | C68: =C56 -> シュウイチ | D68: =D56 -> 修一 | H68: JACK
A69: P2DL_023_12$ | B69: =B56 -> JACK | C69: =C56 -> シュウイチ | D69: =D56 -> 修一 | H69: JACK
A70: P2DL_023_13$ | B70: =B58 -> ALAN | C70: =C58 -> マナブ | D70: =D58 -> 学武 | H70: ALAN
A71: P2DL_023_14$ | B71: =B58 -> ALAN | C71: =C58 -> マナブ | D71: =D58 -> 学武 | H71: ALAN
A72: P2DL_023_15$ | B72: =B65 -> CHAD | C72: =C65 -> クリオ | D72: =D65 -> 板栗 | H72: CHAD
A73: P2DL_023_16$ | B73: =B65 -> CHAD | C73: =C65 -> クリオ | D73: =D65 -> 板栗 | H73: CHAD
A74: P2DL_023_17$ | B74: =B56 -> JACK | C74: =C56 -> シュウイチ | D74: =D56 -> 修一 | G74: CR
A75: P2DL_023_18$ | B75: =B56 -> JACK | C75: =C56 -> シュウイチ | D75: =D56 -> 修一 | G75: CR
A76: P2DL_023_19$ | B76: =B58 -> ALAN | C76: =C58 -> マナブ | D76: =D58 -> 学武 | G76: CR
A77: P2DL_023_20$ | B77: =B58 -> ALAN | C77: =C58 -> マナブ | D77: =D58 -> 学武 | G77: CR
A78: P2DL_023_21$ | B78: =B65 -> CHAD | C78: =C65 -> クリオ | D78: =D65 -> 板栗 | G78: CR
A79: P2DL_023_22$ | B79: =B65 -> CHAD | C79: =C65 -> クリオ | D79: =D65 -> 板栗 | G79: CR
A80: P2DL_024$ | B80: ROD | C80: ツバサ | D80: 小翼 | H80: ROD
A81: P2DL_024_00$ | B81: ABE | C81: ショウタ | D81: 翔太 | H81: ABE
A82: P2DL_024_01$ | B82: BRYAN | C82: ヨシキ | D82: 吉木 | H82: BRYAN
A83: P2DL_024_02$ | B83: THEO | C83: クニヒコ | D83: 国彦 | H83: THEO
A84: P2DL_024_03$ | B84: TOBY | C84: ハルキ | D84: 春树 | H84: TOBY
A85: P2DL_024_04$ | B85: DENIS | C85: アキノリ | D85: 明宪 | H85: DENIS
A86: P2DL_024_05$ | B86: VANCE | C86: モトヒロ | D86: 本广 | H86: VANCE
A87: P2DL_024_06$ | B87: HANK | C87: ソラオ | D87: 空男 | H87: HANK
A88: P2DL_024_07$ | B88: ROY | C88: ハヤオ | D88: 速雄 | H88: ROY
A89: P2DL_024_08$ | B89: BORIS | C89: ショウイチ | D89: 矢来 | H89: BORIS
A90: P2DL_024_09$ | B90: BOB | C90: エイゴ | D90: 英吾 | H90: BOB
A91: P2DL_024_10$ | B91: JOSE | C91: エイジ | D91: 英志 | H91: JOSE
A92: P2DL_024_11$ | B92: PETER | C92: ノブマサ | D92: 渡利 | H92: PETER
A93: P2DL_024_12$ | B93: =B91 -> JOSE | C93: =C91 -> エイジ | D93: =D91 -> 英志 | H93: JOSE
A94: P2DL_024_13$ | B94: PERRY | C94: ノリアキ | D94: 典明 | H94: PERRY
A95: P2DL_024_14$ | B95: BRET | C95: ノボル | D95: 阿登 | H95: BRET
A96: P2DL_024_15$ | B96: =B91 -> JOSE | C96: =C91 -> エイジ | D96: =D91 -> 英志 | H96: JOSE
A97: P2DL_024_16$ | B97: =B86 -> VANCE | C97: =C86 -> モトヒロ | D97: =D86 -> 本广 | H97: VANCE
A98: P2DL_024_17$ | B98: =B86 -> VANCE | C98: =C86 -> モトヒロ | D98: =D86 -> 本广 | H98: VANCE
A99: P2DL_025$ | B99: CARRIE | C99: ミカ | D99: 美香 | H99: CARRIE
A100: P2DL_025_00$ | B100: BRIDGET | C100: アスカ | D100: 飞鸟 | H100: BRIDGET
A101: P2DL_025_01$ | B101: ALICE | C101: チカ | D101: 千佳 | H101: ALICE
A102: P2DL_025_02$ | B102: KRISE | C102: ユキ | D102: 由纪 | H102: KRISE
A103: P2DL_025_03$ | B103: CONNIE | C103: レミ | D103: 丽美 | H103: CONNIE
A104: P2DL_025_04$ | B104: LINDA | C104: アキ | D104: 瑞秋 | H104: LINDA
A105: P2DL_025_05$ | B105: LAURA | C105: ミーナ | D105: 美奈 | H105: LAURA
A106: P2DL_025_06$ | B106: SHANNON | C106: チエ | D106: 千惠 | H106: SHANNON
...

Sheet 类
A1: |-编号---- | B1: |-英文---- | C1: |-日文---- | D1: |-翻译---- | E1: |-注释---- | F1: |-跳过----
A2: Name_P2DL_001$ | B2: LEADER | C2: ジムリーダー | D2: 道馆馆主
A3: Name_P2DL_002$ | B3: =B2 -> LEADER | C3: =C2 -> ジムリーダー | D3: =D2 -> 道馆馆主
A4: Name_P2DL_003$ | B4: =B2 -> LEADER | C4: =C2 -> ジムリーダー | D4: =D2 -> 道馆馆主
A5: Name_P2DL_004$ | B5: =B2 -> LEADER | C5: =C2 -> ジムリーダー | D5: =D2 -> 道馆馆主
A6: Name_P2DL_005$ | B6: =B2 -> LEADER | C6: =C2 -> ジムリーダー | D6: =D2 -> 道馆馆主
A7: Name_P2DL_006$ | B7: =B2 -> LEADER | C7: =C2 -> ジムリーダー | D7: =D2 -> 道馆馆主
A8: Name_P2DL_007$ | B8: =B2 -> LEADER | C8: =C2 -> ジムリーダー | D8: =D2 -> 道馆馆主
A9: Name_P2DL_008$ | B9: =B2 -> LEADER | C9: =C2 -> ジムリーダー | D9: =D2 -> 道馆馆主
A10: Name_P2DL_009$ | B10: RIVAL | C10: ライバル | D10: 劲敌
A11: Name_P2DL_010$ | B11: #MON PROF. | C11: ポケモンはかせ | D11: 宝可梦博士
A12: Name_P2DL_011$ | B12: ELITE FOUR | C12: してんのう | D12: 四天王
A13: Name_P2DL_012$ | B13: <PKMN> TRAINER | C13: ポケモントレーナー | D13: 宝可梦训练家
A14: Name_P2DL_013$ | B14: =B12 -> ELITE FOUR | C14: =C12 -> してんのう | D14: =D12 -> 四天王
A15: Name_P2DL_014$ | B15: =B12 -> ELITE FOUR | C15: =C12 -> してんのう | D15: =D12 -> 四天王
A16: Name_P2DL_015$ | B16: =B12 -> ELITE FOUR | C16: =C12 -> してんのう | D16: =D12 -> 四天王
A17: Name_P2DL_016$ | B17: CHAMPION | C17: チャンピオン | D17: 冠军
A18: Name_P2DL_017$ | B18: =B2 -> LEADER | C18: =C2 -> ジムリーダー | D18: =D2 -> 道馆馆主
A19: Name_P2DL_018$ | B19: =B2 -> LEADER | C19: =C2 -> ジムリーダー | D19: =D2 -> 道馆馆主
A20: Name_P2DL_019$ | B20: =B2 -> LEADER | C20: =C2 -> ジムリーダー | D20: =D2 -> 道馆馆主
A21: Name_P2DL_020$ | B21: SCIENTIST | C21: はぐれけんきゅういん | D21: 流浪研究员
A22: Name_P2DL_021$ | B22: =B2 -> LEADER | C22: =C2 -> ジムリーダー | D22: =D2 -> 道馆馆主
A23: Name_P2DL_022$ | B23: YOUNGSTER | C23: たんパンこぞう | D23: 短裤小子
A24: Name_P2DL_023$ | B24: SCHOOLBOY | C24: じゅくがえり | D24: 补习班学生
A25: Name_P2DL_024$ | B25: BIRD KEEPER | C25: とりつかい | D25: 养鸟人
A26: Name_P2DL_025$ | B26: LASS | C26: ミニスカート | D26: 迷你裙
A27: Name_P2DL_026$ | B27: =B2 -> LEADER | C27: =C2 -> ジムリーダー | D27: =D2 -> 道馆馆主
A28: Name_P2DL_027$ | B28: COOLTRAINER | C28: エリートトレーナー | D28: 精英训练家
A29: Name_P2DL_028$ | B29: =B28 -> COOLTRAINER | C29: =C28 -> エリートトレーナー | D29: =D28 -> 精英训练家
A30: Name_P2DL_029$ | B30: BEAUTY | C30: おとなのおねえさん | D30: 大姐姐
A31: Name_P2DL_030$ | B31: #MANIAC | C31: かいじゅうマニア | D31: 怪兽狂
A32: Name_P2DL_031$ | B32: ROCKET | C32: ロケットだんいん | D32: 火箭队员
A33: Name_P2DL_032$ | B33: GENTLEMAN | C33: ジェントルマン | D33: 绅士
A34: Name_P2DL_033$ | B34: SKIER | C34: スキーヤー | D34: 滑雪者
A35: Name_P2DL_034$ | B35: TEACHER | C35: せんせい | D35: 老师
A36: Name_P2DL_035$ | B36: =B2 -> LEADER | C36: =C2 -> ジムリーダー | D36: =D2 -> 道馆馆主
A37: Name_P2DL_036$ | B37: BUG CATCHER | C37: むしとり | D37: 捕虫少年
A38: Name_P2DL_037$ | B38: FISHER | C38: つりびと | D38: 垂钓者
A39: Name_P2DL_038$ | B39: SWIMMER♂ | C39: かいパンやろう | D39: 泳裤小伙子
A40: Name_P2DL_039$ | B40: SWIMMER♀ | C40: ビキニのおねえさん | D40: 比基尼姐姐
A41: Name_P2DL_040$ | B41: SAILOR | C41: ふなのり | D41: 水手
A42: Name_P2DL_041$ | B42: SUPER NERD | C42: りかけいのおとこ | D42: 理科男
A43: Name_P2DL_042$ | B43: =B10 -> RIVAL | C43: =C10 -> ライバル | D43: =D10 -> 劲敌
A44: Name_P2DL_043$ | B44: GUITARIST | C44: ギタリスト | D44: 吉他手
A45: Name_P2DL_044$ | B45: HIKER | C45: やまおとこ | D45: 登山男
A46: Name_P2DL_045$ | B46: BIKER | C46: ぼうそうぞく | D46: 暴走族
A47: Name_P2DL_046$ | B47: =B2 -> LEADER | C47: =C2 -> ジムリーダー | D47: =D2 -> 道馆馆主
A48: Name_P2DL_047$ | B48: BURGLAR | C48: かじばドロボウ | D48: 趁火打劫者
A49: Name_P2DL_048$ | B49: FIREBREATHER | C49: ひふきやろう | D49: 吹火人
A50: Name_P2DL_049$ | B50: JUGGLER | C50: ジプシージャグラー | D50: 流浪杂耍艺人 | E50: 需要注意此类型NPC名字长度
A51: Name_P2DL_050$ | B51: BLACKBELT | C51: からておう | D51: 空手道王
A52: Name_P2DL_051$ | B52: =B32 -> ROCKET | C52: =C32 -> ロケットだんいん | D52: =D32 -> 火箭队员
A53: Name_P2DL_052$ | B53: PSYCHIC | C53: サイキッカー | D53: 超能力者
A54: Name_P2DL_053$ | B54: PICNICKER | C54: ピクニックガール | D54: 野餐少女
A55: Name_P2DL_054$ | B55: CAMPER | C55: キャンプボーイ | D55: 露营少年
A56: Name_P2DL_055$ | B56: =B32 -> ROCKET | C56: =C32 -> ロケットだんいん | D56: =D32 -> 火箭队员
A57: Name_P2DL_056$ | B57: SAGE | C57: ぼうず | D57: 和尚
A58: Name_P2DL_057$ | B58: MEDIUM | C58: イタコ | D58: 神婆
A59: Name_P2DL_058$ | B59: BOARDER | C59: ボーダー | D59: 滑板客
A60: Name_P2DL_059$ | B60: #FAN | C60: だいすきクラブ | D60: 发烧友俱乐部
A61: Name_P2DL_060$ | B61: KIMONO GIRL | C61: まいこはん | D61: 和服女孩
A62: Name_P2DL_061$ | B62: TWINS | C62: ふたごちゃん | D62: 双胞胎
A63: Name_P2DL_062$ | B63: =B60 -> #FAN | C63: =C60 -> だいすきクラブ | D63: =D60 -> 发烧友俱乐部
A64: Name_P2DL_063$ | B64: =B13 -> <PKMN> TRAINER | C64: =C13 -> ポケモントレーナー | D64: =D13 -> 宝可梦训练家
A65: Name_P2DL_064$ | B65: =B2 -> LEADER | C65: =C2 -> ジムリーダー | D65: =D2 -> 道馆馆主
A66: Name_P2DL_065$ | B66: OFFICER | C66: おまわりさん | D66: 警察先生
A67: Name_P2DL_066$ | B67: =B32 -> ROCKET | C67: =C32 -> ロケットだんいん | D67: =D32 -> 火箭队员
A68: Name_P2DL_067$ | B68: MYSTICALMAN | C68: なぞのせいねん | D68: 谜之青年

Sheet 城
A1: |-编号---- | B1: |-英文---- | C1: |-日文---- | D1: |-翻译---- | E1: |-注释---- | F1: |-跳过----
A2: name_wakaba | B2: NEW BARK TOWN | C2: ワカバタウン | D2: 若叶镇
A3: name_yosino | B3: CHERRYGROVE CITY | C3: ヨシノシティ | D3: 吉花市
A4: name_kikyou | B4: VIOLET CITY | C4: キキョウシティ | D4: 桔梗市
A5: name_hiwada | B5: AZALEA TOWN | C5: ヒワダタウン | D5: 桧皮镇
A6: name_kogane | B6: GOLDENROD CITY | C6: コガネシティ | D6: 满金市
A7: name_enjyu | B7: ECRUTEAK CITY | C7: エンジュシティ | D7: 缘朱市
A8: name_asagi | B8: OLIVINE CITY | C8: アサギシティ | D8: 浅葱市
A9: name_tanba | B9: CIANWOOD CITY | C9: タンバシティ | D9: 湛蓝市
A10: name_tyouji | B10: MAHOGANY TOWN | C10: チョウジタウン | D10: 卡吉镇
A11: name_fusube | B11: BLACKTHORN CITY | C11: フスベシティ | D11: 烟墨市
A12: name_ikari | B12: LAKE OF RAGE | C12: いかりのみずうみ | D12: 愤怒之湖
A13: name_sirogane | B13: SILVER CAVE | C13: シロガネやま | D13: 白银山
... A103: name_special | B103: SPECIAL | C103: スペシャル(???) | D103: 特别(???)

Sheet 城GS
A1: |-编号---- | B1: |-英文---- | C1: |-日文---- | D1: |-翻译---- | E1: |-注释---- | F1: |-跳过----
A2: name_wakaba | B2: NEW BARK TOWN | C2: ワカバタウン | D2: 若叶镇
A3: name_yosino | B3: CHERRYGROVE CITY | C3: ヨシノシティ | D3: 吉花市
A4: name_kikyou | B4: VIOLET CITY | C4: キキョウシティ | D4: 桔梗市
A5: name_hiwada | B5: AZALEA TOWN | C5: ヒワダタウン | D5: 桧皮镇
A6: name_kogane | B6: GOLDENROD CITY | C6: コガネシティ | D6: 满金市
A7: name_enjyu | B7: ECRUTEAK CITY | C7: エンジュシティ | D7: 缘朱市
A8: name_asagi | B8: OLIVINE CITY | C8: アサギシティ | D8: 浅葱市
A9: name_tanba | B9: CIANWOOD CITY | C9: タンバシティ | D9: 湛蓝市
A10: name_tyouji | B10: MAHOGANY TOWN | C10: チョウジタウン | D10: 卡吉镇
A11: name_fusube | B11: BLACKTHORN CITY | C11: フスベシティ | D11: 烟墨市
A12: name_ikari | B12: LAKE OF RAGE | C12: いかりのみずうみ | D12: 愤怒之湖
A13: name_sirogane | B13: SILVER CAVE | C13: シロガネやま | D13: 白银山
... A103: name_special | B103: SPECIAL | C103: スペシャル(???) | D103: 特别(???)

Sheet 道
A1: |-编号---- | B1: |-英文---- | C1: |-日文---- | D1: |-翻译---- | E1: |-注释---- | F1: |-跳过----
A2: ItemName001$ | B2: MASTER BALL | C2: マスターボール | D2: 大师球
A3: ItemName002$ | B3: ULTRA BALL | C3: ハイパーボール | D3: 高级球
A4: ItemName003$ | B4: BRIGHTPOWDER | C4: ひかりのこな | D4: 光粉
A5: ItemName004$ | B5: GREAT BALL | C5: スーパーボール | D5: 超级球
A6: ItemName005$ | B6: # BALL | C6: モンスターボール | D6: 精灵球
A7: ItemName006$ | B7: TERU-SAMA | C7: カビチュウ | D7: 卡比丘
A8: ItemName007$ | B8: BICYCLE | C8: じてんしゃ | D8: 自行车
A9: ItemName008$ | B9: MOON STONE | C9: つきのいし | D9: 月之石
A10: ItemName009$ | B10: ANTIDOTE | C10: どくけし | D10: 解毒药
A11: ItemName010$ | B11: BURN HEAL | C11: やけどなおし | D11: 灼伤药
A12: ItemName011$ | B12: ICE HEAL | C12: こおりなおし | D12: 解冻药
A13: ItemName012$ | B13: AWAKENING | C13: ねむけざまし | D13: 解眠药
... A21: ItemName020$ | B21: REPEL | C21: むしよけスプレー | D21: 除虫喷雾
A22: ItemName021$ | B22: MAX ELIXER | C22: ピーピーマックス | D22: PP多项全补剂 | E22: 太长的名字，游戏各处需要补丁。
A23: ItemName022$ | B23: FIRE STONE | C23: ほのおのいし | D23: 火之石
A24: ItemName023$ | B24: THUNDERSTONE | C24: かみなりのいし | D24: 雷之石
A25: ItemName024$ | B25: WATER STONE | C25: みずのいし | D25: 水之石
A26: ItemName025$ | B26: =B7 -> TERU-SAMA | C26: =C7 -> カビチュウ | D26: =D7 -> 卡比丘
A27: ItemName026$ | B27: HP UP | C27: マックスアップ | D27: HP增强剂
A28: ItemName027$ | B28: PROTEIN | C28: タウリン | D28: 攻击增强剂
A29: ItemName028$ | B29: IRON | C29: ブロムヘキシン | D29: 防御增强剂
A30: ItemName029$ | B30: CARBOS | C30: インドメタシン | D30: 速度增强剂
A31: ItemName030$ | B31: LUCKY PUNCH | C31: ラッキーパンチ | D31: 吉利拳
A32: ItemName031$ | B32: CALCIUM | C32: リゾチウム | D32: 特殊增强剂
A33: ItemName032$ | B33: RARE CANDY | C33: ふしぎなアメ | D33: 神奇糖果
A34: ItemName033$ | B34: X ACCURACY | C34: ヨクアタール | D34: 命中强化
A35: ItemName034$ | B35: LEAF STONE | C35: リーフのいし | D35: 叶之石
A36: ItemName035$ | B36: METAL POWDER | C36: メタルパウダー | D36: 金属粉
A37: ItemName036$ | B37: NUGGET | C37: きんのたま | D37: 金珠
A38: ItemName037$ | B38: # DOLL | C38: ピッピにんぎょう | D38: 皮皮玩偶
... A45: ItemName044$ | B45: DIRE HIT | C45: クリティカッター | D45: 要害攻击
A46: ItemName045$ | B46: =B7 -> TERU-SAMA | C46: =C7 -> カビチュウ | D46: =D7 -> 卡比丘
A47: ItemName046$ | B47: FRESH WATER | C47: おいしいみず | D47: 美味之水
A48: ItemName047$ | B48: SODA POP | C48: サイコソーダ | D48: 劲爽汽水
A49: ItemName048$ | B49: LEMONADE | C49: ミックスオレ | D49: 果汁牛奶
A50: ItemName049$ | B50: X ATTACK | C50: プラスパワー | D50: 力量强化
A51: ItemName050$ | B51: =B7 -> TERU-SAMA | C51: =C7 -> カビチュウ | D51: =D7 -> 卡比丘
A52: ItemName051$ | B52: X DEFEND | C52: ディフェンダー | D52: 防御强化
A53: ItemName052$ | B53: X SPEED | C53: スピーダー | D53: 速度强化
A54: ItemName053$ | B54: X SPECIAL | C54: スペシャルアップ | D54: 特攻强化
A55: ItemName054$ | B55: COIN CASE | C55: コインケース | D55: 代币盒
A56: ItemName055$ | B56: ITEMFINDER | C56: ダウジングマシン | D56: 探宝器
A57: ItemName056$ | B57: =B7 -> TERU-SAMA | C57: =C7 -> カビチュウ | D57: =D7 -> 卡比丘
A58: ItemName057$ | B58: EXP.SHARE | C58: がくしゅうそうち | D58: 学习装置
A59: ItemName058$ | B59: OLD ROD | C59: ボロのつりざお | D59: 破旧钓竿
A60: ItemName059$ | B60: GOOD ROD | C60: いいつりざお | D60: 好钓竿
A61: ItemName060$ | B61: SILVER LEAF | C61: ぎんのはっぱ | D61: 银色叶子
A62: ItemName061$ | B62: SUPER ROD | C62: すごいつりざお | D62: 厉害钓竿
A63: ItemName062$ | B63: PP UP | C63: ポイントアップ | D63: PP提升剂
A64: ItemName063$ | B64: ETHER | C64: ピーピーエイド | D64: PP单项小补剂 | E64: 太长的名字，游戏各处需要补丁。
A65: ItemName064$ | B65: MAX ETHER | C65: ピーピーリカバー | D65: PP单项全补剂 | E65: 太长的名字，游戏各处需要补丁。
A66: ItemName065$ | B66: ELIXER | C66: ピーピーエイダー | D66: PP多项小补剂 | E66: 太长的名字，游戏各处需要补丁。
A67: ItemName066$ | B67: RED SCALE | C67: あかいウロコ | D67: 红色鳞片
A68: ItemName067$ | B68: SECRETPOTION | C68: ひでんのくすり | D68: 秘传之药
A69: ItemName068$ | B69: S.S.TICKET | C69: ふねのチケット | D69: 船票
A70: ItemName069$ | B70: MYSTERY EGG | C70: ふしぎなタマゴ | D70: 神奇蛋
A71: ItemName070$ | B71: CLEAR BELL | C71: とうめいなスズ | D71: 透明铃铛
A72: ItemName071$ | B72: SILVER WING | C72: ぎんいろのはね | D72: 银色之羽
A73: ItemName072$ | B73: MOOMOO MILK | C73: モーモーミルク | D73: 哞哞鲜奶
A74: ItemName073$ | B74: QUICK CLAW | C74: せんせいのツメ | D74: 先制之爪
A75: ItemName074$ | B75: PSNCUREBERRY | C75: どくけしのみ | D75: 解毒果
A76: ItemName075$ | B76: GOLD LEAF | C76: きんのはっぱ | D76: 金色叶子
A77: ItemName076$ | B77: SOFT SAND | C77: やわらかいすな | D77: 柔软沙子
A78: ItemName077$ | B78: SHARP BEAK | C78: するどいくちばし | D78: 锐利鸟嘴
... A90: ItemName089$ | B90: BLU APRICORN | C90: あおぼんぐり | D90: 蓝球果
A91: ItemName090$ | B91: =B7 -> TERU-SAMA | C91: =C7 -> カビチュウ | D91: =D7 -> 卡比丘
A92: ItemName091$ | B92: AMULET COIN | C92: おまもりこばん | D92: 护符金币
A93: ItemName092$ | B93: YLW APRICORN | C93: きぼんぐり | D93: 黄球果
A94: ItemName093$ | B94: GRN APRICORN | C94: みどぼんぐり | D94: 绿球果
A95: ItemName094$ | B95: CLEANSE TAG | C95: きよめのおふだ | D95: 洁净之符
A96: ItemName095$ | B96: MYSTIC WATER | C96: しんぴのしずく | D96: 神秘水滴
A97: ItemName096$ | B97: TWISTEDSPOON | C97: まがったスプーン | D97: 弯曲的汤匙
A98: ItemName097$ | B98: WHT APRICORN | C98: しろぼんぐり | D98: 白球果
A99: ItemName098$ | B99: BLACKBELT | C99: くろおび | D99: 黑带
A100: ItemName099$ | B100: BLK APRICORN | C100: くろぼんぐり | D100: 黑球果
A101: ItemName100$ | B101: =B7 -> TERU-SAMA | C101: =C7 -> カビチュウ | D101: =D7 -> 卡比丘
A102: ItemName101$ | B102: PNK APRICORN | C102: ももぼんぐり | D102: 粉球果
A103: ItemName102$ | B103: BLACKGLASSES | C103: くろいメガネ | D103: 黑色眼镜
A104: ItemName103$ | B104: SLOWPOKETAIL | C104: おいしいシッポ | D104: 美味尾巴
A105: ItemName104$ | B105: PINK BOW | C105: ピンクのリボン | D105: 粉红丝带
A106: ItemName105$ | B106: STICK | C106: ながねぎ | D106: 大葱
A107: ItemName106$ | B107: SMOKE BALL | C107: けむりだま | D107: 烟雾球
A108: ItemName107$ | B108: NEVERMELTICE | C108: とけないこおり | D108: 不融冰
A109: ItemName108$ | B109: MAGNET | C109: じしゃく | D109: 磁铁
A110: ItemName109$ | B110: MIRACLEBERRY | C110: きせきのみ | D110: 奇迹果
A111: ItemName110$ | B111: PEARL | C111: しんじゅ | D111: 珍珠
A112: ItemName111$ | B112: BIG PEARL | C112: おおきなしんじゅ | D112: 大珍珠
A113: ItemName112$ | B113: EVERSTONE | C113: かわらずのいし | D113: 不变之石
... A120: ItemName119$ | B120: FOCUS BAND | C120: きあいのハチマキ | D120: 气势头带
A121: ItemName120$ | B121: =B7 -> TERU-SAMA | C121: =C7 -> カビチュウ | D121: =D7 -> 卡比丘
A122: ItemName121$ | B122: ENERGYPOWDER | C122: ちからのこな | D122: 元气粉
A123: ItemName122$ | B123: ENERGY ROOT | C123: ちからのねっこ | D123: 元气根
A124: ItemName123$ | B124: HEAL POWDER | C124: ばんのうごな | D124: 万能粉
A125: ItemName124$ | B125: REVIVAL HERB | C125: ふっかつそう | D125: 复活草
A126: ItemName125$ | B126: HARD STONE | C126: かたいいし | D126: 硬石头
A127: ItemName126$ | B127: LUCKY EGG | C127: しあわせタマゴ | D127: 幸运蛋
A128: ItemName127$ | B128: CARD KEY | C128: カードキー | D128: 钥匙卡
A129: ItemName128$ | B129: MACHINE PART | C129: きかいのぶひん | D129: 机械零件
A130: ItemName129$ | B130: EGG TICKET | C130: タマゴけん | D130: 蛋兑换券
...

Sheet 道GS
A1: |-编号---- | B1: |-英文---- | C1: |-日文---- | D1: |-翻译---- | E1: |-注释---- | F1: |-跳过----
A2: ItemName001$ | B2: MASTER BALL | C2: マスターボール | D2: 大师球
A3: ItemName002$ | B3: ULTRA BALL | C3: ハイパーボール | D3: 高级球
A4: ItemName003$ | B4: BRIGHTPOWDER | C4: ひかりのこな | D4: 光粉
A5: ItemName004$ | B5: GREAT BALL | C5: スーパーボール | D5: 超级球
A6: ItemName005$ | B6: # BALL | C6: モンスターボール | D6: 精灵球
A7: ItemName006$ | B7: TERU-SAMA | C7: カビチュウ | D7: 卡比丘
A8: ItemName007$ | B8: BICYCLE | C8: じてんしゃ | D8: 自行车
A9: ItemName008$ | B9: MOON STONE | C9: つきのいし | D9: 月之石
A10: ItemName009$ | B10: ANTIDOTE | C10: どくけし | D10: 解毒药
A11: ItemName010$ | B11: BURN HEAL | C11: やけどなおし | D11: 灼伤药
A12: ItemName011$ | B12: ICE HEAL | C12: こおりなおし | D12: 解冻药
A13: ItemName012$ | B13: AWAKENING | C13: ねむけざまし | D13: 解眠药
... A21: ItemName020$ | B21: REPEL | C21: むしよけスプレー | D21: 除虫喷雾
A22: ItemName021$ | B22: MAX ELIXER | C22: ピーピーマックス | D22: PP多项全补剂 | E22: 太长的名字，游戏各处需要补丁。
A23: ItemName022$ | B23: FIRE STONE | C23: ほのおのいし | D23: 火之石
A24: ItemName023$ | B24: THUNDERSTONE | C24: かみなりのいし | D24: 雷之石
A25: ItemName024$ | B25: WATER STONE | C25: みずのいし | D25: 水之石
A26: ItemName025$ | B26: =B7 -> TERU-SAMA | C26: =C7 -> カビチュウ | D26: =D7 -> 卡比丘
A27: ItemName026$ | B27: HP UP | C27: マックスアップ | D27: HP增强剂
A28: ItemName027$ | B28: PROTEIN | C28: タウリン | D28: 攻击增强剂
A29: ItemName028$ | B29: IRON | C29: ブロムヘキシン | D29: 防御增强剂
A30: ItemName029$ | B30: CARBOS | C30: インドメタシン | D30: 速度增强剂
A31: ItemName030$ | B31: LUCKY PUNCH | C31: ラッキーパンチ | D31: 吉利拳
A32: ItemName031$ | B32: CALCIUM | C32: リゾチウム | D32: 特殊增强剂
A33: ItemName032$ | B33: RARE CANDY | C33: ふしぎなアメ | D33: 神奇糖果
A34: ItemName033$ | B34: X ACCURACY | C34: ヨクアタール | D34: 命中强化
A35: ItemName034$ | B35: LEAF STONE | C35: リーフのいし | D35: 叶之石
A36: ItemName035$ | B36: METAL POWDER | C36: メタルパウダー | D36: 金属粉
A37: ItemName036$ | B37: NUGGET | C37: きんのたま | D37: 金珠
A38: ItemName037$ | B38: # DOLL | C38: ピッピにんぎょう | D38: 皮皮玩偶
... A45: ItemName044$ | B45: DIRE HIT | C45: クリティカッター | D45: 要害攻击
A46: ItemName045$ | B46: =B7 -> TERU-SAMA | C46: =C7 -> カビチュウ | D46: =D7 -> 卡比丘
A47: ItemName046$ | B47: FRESH WATER | C47: おいしいみず | D47: 美味之水
A48: ItemName047$ | B48: SODA POP | C48: サイコソーダ | D48: 劲爽汽水
A49: ItemName048$ | B49: LEMONADE | C49: ミックスオレ | D49: 果汁牛奶
A50: ItemName049$ | B50: X ATTACK | C50: プラスパワー | D50: 力量强化
A51: ItemName050$ | B51: =B7 -> TERU-SAMA | C51: =C7 -> カビチュウ | D51: =D7 -> 卡比丘
A52: ItemName051$ | B52: X DEFEND | C52: ディフェンダー | D52: 防御强化
A53: ItemName052$ | B53: X SPEED | C53: スピーダー | D53: 速度强化
A54: ItemName053$ | B54: X SPECIAL | C54: スペシャルアップ | D54: 特攻强化
A55: ItemName054$ | B55: COIN CASE | C55: コインケース | D55: 代币盒
A56: ItemName055$ | B56: ITEMFINDER | C56: ダウジングマシン | D56: 探宝器
A57: ItemName056$ | B57: =B7 -> TERU-SAMA | C57: =C7 -> カビチュウ | D57: =D7 -> 卡比丘
A58: ItemName057$ | B58: EXP.SHARE | C58: がくしゅうそうち | D58: 学习装置
A59: ItemName058$ | B59: OLD ROD | C59: ボロのつりざお | D59: 破旧钓竿
A60: ItemName059$ | B60: GOOD ROD | C60: いいつりざお | D60: 好钓竿
A61: ItemName060$ | B61: SILVER LEAF | C61: ぎんのはっぱ | D61: 银色叶子
A62: ItemName061$ | B62: SUPER ROD | C62: すごいつりざお | D62: 厉害钓竿
A63: ItemName062$ | B63: PP UP | C63: ポイントアップ | D63: PP提升剂
A64: ItemName063$ | B64: ETHER | C64: ピーピーエイド | D64: PP单项小补剂 | E64: 太长的名字，游戏各处需要补丁。
A65: ItemName064$ | B65: MAX ETHER | C65: ピーピーリカバー | D65: PP单项全补剂 | E65: 太长的名字，游戏各处需要补丁。
A66: ItemName065$ | B66: ELIXER | C66: ピーピーエイダー | D66: PP多项小补剂 | E66: 太长的名字，游戏各处需要补丁。
A67: ItemName066$ | B67: RED SCALE | C67: あかいウロコ | D67: 红色鳞片
A68: ItemName067$ | B68: SECRETPOTION | C68: ひでんのくすり | D68: 秘传之药
A69: ItemName068$ | B69: S.S.TICKET | C69: ふねのチケット | D69: 船票
A70: ItemName069$ | B70: MYSTERY EGG | C70: ふしぎなタマゴ | D70: 神奇蛋
A71: ItemName070$ | B71: CLEAR BELL | C71: とうめいなスズ | D71: 透明铃铛
A72: ItemName071$ | B72: SILVER WING | C72: ぎんいろのはね | D72: 银色之羽
A73: ItemName072$ | B73: MOOMOO MILK | C73: モーモーミルク | D73: 哞哞鲜奶
A74: ItemName073$ | B74: QUICK CLAW | C74: せんせいのツメ | D74: 先制之爪
A75: ItemName074$ | B75: PSNCUREBERRY | C75: どくけしのみ | D75: 解毒果
A76: ItemName075$ | B76: GOLD LEAF | C76: きんのはっぱ | D76: 金色叶子
A77: ItemName076$ | B77: SOFT SAND | C77: やわらかいすな | D77: 柔软沙子
A78: ItemName077$ | B78: SHARP BEAK | C78: するどいくちばし | D78: 锐利鸟嘴
... A90: ItemName089$ | B90: BLU APRICORN | C90: あおぼんぐり | D90: 蓝球果
A91: ItemName090$ | B91: =B7 -> TERU-SAMA | C91: =C7 -> カビチュウ | D91: =D7 -> 卡比丘
A92: ItemName091$ | B92: AMULET COIN | C92: おまもりこばん | D92: 护符金币
A93: ItemName092$ | B93: YLW APRICORN | C93: きぼんぐり | D93: 黄球果
A94: ItemName093$ | B94: GRN APRICORN | C94: みどぼんぐり | D94: 绿球果
A95: ItemName094$ | B95: CLEANSE TAG | C95: きよめのおふだ | D95: 洁净之符
A96: ItemName095$ | B96: MYSTIC WATER | C96: しんぴのしずく | D96: 神秘水滴
A97: ItemName096$ | B97: TWISTEDSPOON | C97: まがったスプーン | D97: 弯曲的汤匙
A98: ItemName097$ | B98: WHT APRICORN | C98: しろぼんぐり | D98: 白球果
A99: ItemName098$ | B99: BLACKBELT | C99: くろおび | D99: 黑带
A100: ItemName099$ | B100: BLK APRICORN | C100: くろぼんぐり | D100: 黑球果
A101: ItemName100$ | B101: =B7 -> TERU-SAMA | C101: =C7 -> カビチュウ | D101: =D7 -> 卡比丘
A102: ItemName101$ | B102: PNK APRICORN | C102: ももぼんぐり | D102: 粉球果
A103: ItemName102$ | B103: BLACKGLASSES | C103: くろいメガネ | D103: 黑色眼镜
A104: ItemName103$ | B104: SLOWPOKETAIL | C104: おいしいシッポ | D104: 美味尾巴
A105: ItemName104$ | B105: PINK BOW | C105: ピンクのリボン | D105: 粉红丝带
A106: ItemName105$ | B106: STICK | C106: ながねぎ | D106: 大葱
A107: ItemName106$ | B107: SMOKE BALL | C107: けむりだま | D107: 烟雾球
A108: ItemName107$ | B108: NEVERMELTICE | C108: とけないこおり | D108: 不融冰
A109: ItemName108$ | B109: MAGNET | C109: じしゃく | D109: 磁铁
A110: ItemName109$ | B110: MIRACLEBERRY | C110: きせきのみ | D110: 奇迹果
A111: ItemName110$ | B111: PEARL | C111: しんじゅ | D111: 珍珠
A112: ItemName111$ | B112: BIG PEARL | C112: おおきなしんじゅ | D112: 大珍珠
A113: ItemName112$ | B113: EVERSTONE | C113: かわらずのいし | D113: 不变之石
... A120: ItemName119$ | B120: FOCUS BAND | C120: きあいのハチマキ | D120: 气势头带
A121: ItemName120$ | B121: =B7 -> TERU-SAMA | C121: =C7 -> カビチュウ | D121: =D7 -> 卡比丘
A122: ItemName121$ | B122: ENERGYPOWDER | C122: ちからのこな | D122: 元气粉
A123: ItemName122$ | B123: ENERGY ROOT | C123: ちからのねっこ | D123: 元气根
A124: ItemName123$ | B124: HEAL POWDER | C124: ばんのうごな | D124: 万能粉
A125: ItemName124$ | B125: REVIVAL HERB | C125: ふっかつそう | D125: 复活草
A126: ItemName125$ | B126: HARD STONE | C126: かたいいし | D126: 硬石头
A127: ItemName126$ | B127: LUCKY EGG | C127: しあわせタマゴ | D127: 幸运蛋
A128: ItemName127$ | B128: CARD KEY | C128: カードキー | D128: 钥匙卡
A129: ItemName128$ | B129: MACHINE PART | C129: きかいのぶひん | D129: 机械零件
A130: ItemName129$ | B130: EGG TICKET | C130: タマゴけん | D130: 蛋兑换券
...

Sheet 招
A1: |-编号---- | B1: |-英文---- | C1: |-日文---- | D1: |-翻译---- | E1: |-注释---- | F1: |-跳过----
A2: M001 | B2: POUND | C2: はたく | D2: 拍击
A3: M002 | B3: KARATE CHOP | C3: からてチョップ | D3: 空手劈
A4: M003 | B4: DOUBLESLAP | C4: おうふくビンタ | D4: 连环巴掌
A5: M004 | B5: COMET PUNCH | C5: れんぞくパンチ | D5: 连续拳
A6: M005 | B6: MEGA PUNCH | C6: メガトンパンチ | D6: 百万吨重拳
A7: M006 | B7: PAY DAY | C7: ネコにこばん | D7: 聚宝功
A8: M007 | B8: FIRE PUNCH | C8: ほのおのパンチ | D8: 火焰拳
A9: M008 | B9: ICE PUNCH | C9: れいとうパンチ | D9: 冰冻拳
A10: M009 | B10: THUNDERPUNCH | C10: かみなりパンチ | D10: 雷电拳
A11: M010 | B11: SCRATCH | C11: ひっかく | D11: 抓
A12: M011 | B12: VICEGRIP | C12: はさむ | D12: 夹住
A13: M012 | B13: GUILLOTINE | C13: ハサミギロチン | D13: 断头钳
... A252: M251 | B252: BEAT UP | C252: ふくろだたき | D252: 围攻

Sheet 图
A1: --开始------------ | C1: PokeGuide001 | D1: bulbasaur | E1: bulbasaur | F1: =IF(D1<>E1,"已更改","")
A2: SEED | C2: たね | D2: 种子 | E2: 种子 | F2: =IF(D2<>E2,"已更改","")
A3: 2'04 | C3: 0.7 m | D3: 0.7 m | E3: 0.7 m | F3: =IF(D3<>E3,"已更改","")
A4: 15.0 lb | C4: 6.9 kg | D4: 6.9 kg | E4: 6.9 kg | F4: =IF(D4<>E4,"已更改","")
A5: --图鉴------------ | B5: --２页------------ | C5: --图鉴------------------------------ | D5: --图鉴------------------ | E5: --图鉴------------------ | F5: =IF(D5<>E5,"已更改","")
A6: While it is young, | B6: stored in the | C6: うまれて しばらくの あいだ | D6: 刚出生后的一段时间里， | E6: 在出生后的一段时间内， | F6: =IF(D6<>E6,"已更改","") -> 已更改
A7: it uses the | B7: seeds on its back | C7: せなかの タネに つまった | D7: 靠吸收储存在背上种子里的 | E7: 靠吸收储存在背上种子里的 | F7: =IF(D7<>E7,"已更改","")
A8: nutrients that are | B8: in order to grow. | C8: えいようを とって そだつ。 | D8: 营养使自己成长。 | E8: 营养使自己成长。 | F8: =IF(D8<>E8,"已更改","")
F9: =IF(D9<>E9,"已更改","")
A10: --开始------------ | C10: PokeGuide002 | D10: ivysaur | E10: ivysaur | F10: =IF(D10<>E10,"已更改","")
A11: SEED | C11: たね | D11: 种子 | E11: 种子 | F11: =IF(D11<>E11,"已更改","")
A12: 3'03 | C12: 1.0 m | D12: 1.0 m | E12: 1.0 m | F12: =IF(D12<>E12,"已更改","")
A13: 29.0 lb | C13: 13.0 Kg | D13: 13.0 Kg | E13: 13.0 Kg | F13: =IF(D13<>E13,"已更改","")
A14: --图鉴------------ | B14: --２页------------ | C14: --图鉴------------------------------ | D14: --图鉴------------------ | E14: --图鉴------------------ | F14: =IF(D14<>E14,"已更改","")
A15: The bulb on its | B15: The bulb gives off | C15: せなかの つぼみは ようぶんを | D15: 背上的花蕾会在吸取 | E15: 背上的花蕾会在吸取 | F15: =IF(D15<>E15,"已更改","")
A16: back grows as it | B16: a pleasant aroma | C16: きゅうしゅう して ふくらむ。 | D16: 养分后膨胀。开花期间 | E16: 养分后膨胀。开花期间 | F16: =IF(D16<>E16,"已更改","")
A17: absorbs nutrients. | B17: when it blooms. | C17: はなのさくころ いいにおいが する。 | D17: 会发出怡人的香气。 | E17: 会发出怡人的香气。 | F17: =IF(D17<>E17,"已更改","")
F18: =IF(D18<>E18,"已更改","")
A19: --开始------------ | C19: PokeGuide003 | D19: venusaur | E19: venusaur | F19: =IF(D19<>E19,"已更改","")
A20: SEED | C20: たね | D20: 种子 | E20: 种子 | F20: =IF(D20<>E20,"已更改","")
A21: 6'07 | C21: 2.0 m | D21: 2.0 m | E21: 2.0 m | F21: =IF(D21<>E21,"已更改","")
A22: 221.0 lb | C22: 100.0 Kg | D22: 100.0 Kg | E22: 100.0 Kg | F22: =IF(D22<>E22,"已更改","")
A23: --图鉴------------ | B23: --２页------------ | C23: --图鉴------------------------------ | D23: --图鉴------------------ | E23: --图鉴------------------ | F23: =IF(D23<>E23,"已更改","")
A24: As it warms it- | B24: flower petals | C24: たいようの ひかりをあびて からだが | D24: 沐浴阳光让身体变暖的话， | E24: 沐浴阳光让身体变暖的话， | F24: =IF(D24<>E24,"已更改","")
A25: self and absorbs | B25: release a pleasant | C25: あたたまってくると はなびら から | D25: 就会从花瓣散发出 | E25: 就会从花瓣散发出 | F25: =IF(D25<>E25,"已更改","")
A26: the sunlight, its | B26: fragrance. | C26: ここちよくなる かおりが ただよう。 | D26: 令人神清气爽的香味。 | E26: 令人神清气爽的香味。 | F26: =IF(D26<>E26,"已更改","")
F27: =IF(D27<>E27,"已更改","")
A28: --开始------------ | C28: PokeGuide004 | D28: charmander | E28: charmander | F28: =IF(D28<>E28,"已更改","")
A29: LIZARD | C29: とかげ | D29: 蜥蜴 | E29: 蜥蜴 | F29: =IF(D29<>E29,"已更改","")
A30: 2'00 | C30: 0.6 m | D30: 0.6 m | E30: 0.6 m | F30: =IF(D30<>E30,"已更改","")
A31: 19.0 lb | C31: 8.5 Kg | D31: 8.5 Kg | E31: 8.5 Kg | F31: =IF(D31<>E31,"已更改","")
A32: --图鉴------------ | B32: --２页------------ | C32: --图鉴------------------------------ | D32: --图鉴------------------ | E32: --图鉴------------------ | F32: =IF(D32<>E32,"已更改","")
A33: If it's healthy, | B33: will burn vigor- | C33: しっぽの さきの ほのおは | D33: 在精力充沛时，在尾巴尖端 | E33: 在精力充沛时， | F33: =IF(D33<>E33,"已更改","") -> 已更改
A34: the flame on the | B34: ously, even if it | C34: げんきなら すこしくらい ぬれても | D34: 旺盛燃烧的火苗即使沾了 | E34: 尾巴尖端旺盛燃烧的火苗 | F34: =IF(D34<>E34,"已更改","") -> 已更改
A35: tip of its tail | B35: gets a bit wet. | C35: きえることなく もえさかる。 | D35: 少量的水也不会熄灭。 | E35: 即使沾了点水也不会熄灭。 | F35: =IF(D35<>E35,"已更改","") -> 已更改
F36: =IF(D36<>E36,"已更改","")
A37: --开始------------ | C37: PokeGuide005 | D37: charmeleon | E37: charmeleon | F37: =IF(D37<>E37,"已更改","")
A38: FLAME | C38: かえん | D38: 火焰 | E38: 火焰 | F38: =IF(D38<>E38,"已更改","")
A39: 3'07 | C39: 1.1 m | D39: 1.1 m | E39: 1.1 m | F39: =IF(D39<>E39,"已更改","")
A40: 42.0 lb | C40: 19.0 Kg | D40: 19.0 Kg | E40: 19.0 Kg | F40: =IF(D40<>E40,"已更改","")
A41: --图鉴------------ | B41: --２页------------ | C41: --图鉴------------------------------ | D41: --图鉴------------------ | E41: --图鉴------------------ | F41: =IF(D41<>E41,"已更改","")
A42: If it becomes | B42: intense flames, | C42: たたかいで きもちが たかぶると | D42: 在对战中情绪高涨的话， | E42: 在对战中感到兴奋的话， | F42: =IF(D42<>E42,"已更改","") -> 已更改
A43: agitated during | B43: incinerating its | C43: しゃくねつの ほのおを ふきながら | D43: 就会喷出灼热的火焰 | E43: 就会喷出灼热的火焰 | F43: =IF(D43<>E43,"已更改","")
A44: battle, it spouts | B44: surroundings. | C44: あたりを もやしてまわる。 | D44: 烧遍周围的一切。 | E44: 烧遍周围的一切。 | F44: =IF(D44<>E44,"已更改","")
F45: =IF(D45<>E45,"已更改","")
A46: --开始------------ | C46: PokeGuide006 | D46: charizard | E46: charizard | F46: =IF(D46<>E46,"已更改","")
A47: FLAME | C47: かえん | D47: 火焰 | E47: 火焰 | F47: =IF(D47<>E47,"已更改","")
A48: 5'07 | C48: 1.7 m | D48: 1.7 m | E48: 1.7 m | F48: =IF(D48<>E48,"已更改","")
A49: 200.0 lb | C49: 90.5 Kg | D49: 90.5 Kg | E49: 90.5 Kg | F49: =IF(D49<>E49,"已更改","")
A50: --图鉴------------ | B50: --２页------------ | C50: --图鉴------------------------------ | D50: --图鉴------------------ | E50: --图鉴------------------ | F50: =IF(D50<>E50,"已更改","")
A51: It uses its wings | B51: fire increases as | C51: つばさで おおぞらたかく まう。 | D51: 挥舞翅膀在高空中飞舞。 | E51: 挥舞翅膀在高空中飞舞。 | F51: =IF(D51<>E51,"已更改","")
A52: to fly high. The | B52: it gains exper- | C52: たたかいの けいけんを つむほど | D52: 积累的对战经验越多， | E52: 积累的对战经验越多， | F52: =IF(D52<>E52,"已更改","")
A53: temperature of its | B53: ience in battle. | C53: ほのおの おんどは あがっていく。 | D53: 火焰的温度就越高。 | E53: 火焰的温度就越高。 | F53: =IF(D53<>E53,"已更改","")
F54: =IF(D54<>E54,"已更改","")
A55: --开始------------ | C55: PokeGuide007 | D55: squirtle | E55: squirtle | F55: =IF(D55<>E55,"已更改","")
A56: TINYTURTLE | C56: かめのこ | D56: 小龟 | E56: 小龟 | F56: =IF(D56<>E56,"已更改","")
A57: 1'08 | C57: 0.5 m | D57: 0.5 m | E57: 0.5 m | F57: =IF(D57<>E57,"已更改","")
A58: 20.0 lb | C58: 9.0 Kg | D58: 9.0 Kg | E58: 9.0 Kg | F58: =IF(D58<>E58,"已更改","")
A59: --图鉴------------ | B59: --２页------------ | C59: --图鉴------------------------------ | D59: --图鉴------------------ | E59: --图鉴------------------ | F59: =IF(D59<>E59,"已更改","")
A60: When it feels | B60: inside its shell | C60: あぶなくなると こうらに てあしを | D60: 一旦遇到危险就会把手脚 | E60: 一旦遇到危险就会把手脚 | F60: =IF(D60<>E60,"已更改","")
A61: threatened, it | B61: and sprays water | C61: ひっこめて みを まもりながら | D61: 缩到壳里，保护自己的同时 | E61: 缩到壳里以保护自己， | F61: =IF(D61<>E61,"已更改","") -> 已更改
A62: draws its legs | B62: from its mouth. | C62: くちから みずを ふきだしてくる。 | D62: 从口中喷水。 | E62: 同时还会用嘴喷水。 | F62: =IF(D62<>E62,"已更改","") -> 已更改
F63: =IF(D63<>E63,"已更改","")
A64: --开始------------ | C64: PokeGuide008 | D64: wartortle | E64: wartortle | F64: =IF(D64<>E64,"已更改","")
A65: TURTLE | C65: かめ | D65: 龟 | E65: 龟 | F65: =IF(D65<>E65,"已更改","")
A66: 3'03 | C66: 1.0 m | D66: 1.0 m | E66: 1.0 m | F66: =IF(D66<>E66,"已更改","")
A67: 50.0 lb | C67: 22.5 Kg | D67: 22.5 Kg | E67: 22.5 Kg | F67: =IF(D67<>E67,"已更改","")
A68: --图鉴------------ | B68: --２页------------ | C68: --图鉴------------------------------ | D68: --图鉴------------------ | E68: --图鉴------------------ | F68: =IF(D68<>E68,"已更改","")
A69: Its long, furry | B69: making it quite | C69: ながくて ふさふさの しっぽは | D69: 毛茸茸的长尾巴被当作 | E69: 蓬松的长尾巴被当作 | F69: =IF(D69<>E69,"已更改","") -> 已更改
A70: tail is a symbol | B70: popular among | C70: ながいきの シンボル。 | D70: 长寿的象征，因此在 | E70: 长寿的象征，因此在 | F70: =IF(D70<>E70,"已更改","")
A71: of longevity, | B71: older people. | C71: とくに おとしよりに にんきがある。 | D71: 老年人中特别受欢迎。 | E71: 老年人中特别受欢迎。 | F71: =IF(D71<>E71,"已更改","")
F72: =IF(D72<>E72,"已更改","")
A73: --开始------------ | C73: PokeGuide009 | D73: blastoise | E73: blastoise | F73: =IF(D73<>E73,"已更改","")
A74: SHELLFISH | C74: こうら | D74: 甲壳 | E74: 甲壳 | F74: =IF(D74<>E74,"已更改","")
A75: 5'03 | C75: 1.6 m | D75: 1.6 m | E75: 1.6 m | F75: =IF(D75<>E75,"已更改","")
A76: 189.0 lb | C76: 85.5 Kg | D76: 85.5 Kg | E76: 85.5 Kg | F76: =IF(D76<>E76,"已更改","")
A77: --图鉴------------ | B77: --２页------------ | C77: --图鉴------------------------------ | D77: --图鉴------------------ | E77: --图鉴------------------ | F77: =IF(D77<>E77,"已更改","")
A78: It firmly plants | B78: shooting water | C78: せなかの ふんしゃこう から | D78: 从后背的喷射口中喷出 | E78: 从后背的喷口中 | F78: =IF(D78<>E78,"已更改","") -> 已更改
A79: its feet on the | B79: from the jets on | C79: いきおいよく みずを だすとき | D79: 强力水柱的时候，会先把 | E79: 喷出强力水柱的时候， | F79: =IF(D79<>E79,"已更改","") -> 已更改
A80: ground before | B80: its back. | C80: ちからづよく だいちを ふみしめる。 | D80: 脚稳稳地踩在地面上。 | E80: 双脚会重重地踏在地面上。 | F80: =IF(D80<>E80,"已更改","") -> 已更改
F81: =IF(D81<>E81,"已更改","")
A82: --开始------------ | C82: PokeGuide010 | D82: caterpie | E82: caterpie | F82: =IF(D82<>E82,"已更改","")
A83: WORM | C83: いもむし | D83: 虫宝宝 | E83: 虫宝宝 | F83: =IF(D83<>E83,"已更改","")
A84: 1'00 | C84: 0.3 m | D84: 0.3 m | E84: 0.3 m | F84: =IF(D84<>E84,"已更改","")
A85: 6.0 lb | C85: 2.9 Kg | D85: 2.9 Kg | E85: 2.9 Kg | F85: =IF(D85<>E85,"已更改","")
A86: --图鉴------------ | B86: --２页------------ | C86: --图鉴------------------------------ | D86: --图鉴------------------ | E86: --图鉴------------------ | F86: =IF(D86<>E86,"已更改","")
A87: It crawls into | B87: among leaves that | C87: はっぱの なかに もぐりこむのは | D87: 为了将自己隐藏在与 | E87: 为了将自己隐藏在与 | F87: =IF(D87<>E87,"已更改","")
A88: foliage where it | B88: are the same color | C88: からだと おなじいろの なかで | D88: 身体颜色相同的环境中， | E88: 身体颜色相同的环境中， | F88: =IF(D88<>E88,"已更改","")
A89: camouflages itself | B89: as its body. | C89: じぶんを カモフラージュするため。 | D89: 会钻到树叶里面去。 | E89: 会钻到树叶里面去。 | F89: =IF(D89<>E89,"已更改","")
F90: =IF(D90<>E90,"已更改","")
A91: --开始------------ | C91: PokeGuide011 | D91: metapod | E91: metapod | F91: =IF(D91<>E91,"已更改","")
A92: COCOON | C92: さなぎ | D92: 蛹 | E92: 蛹 | F92: =IF(D92<>E92,"已更改","")
A93: 2'04 | C93: 0.7 m | D93: 0.7 m | E93: 0.7 m | F93: =IF(D93<>E93,"已更改","")
A94: 22.0 lb | C94: 9.9 Kg | D94: 9.9 Kg | E94: 9.9 Kg | F94: =IF(D94<>E94,"已更改","")
A95: --图鉴------------ | B95: --２页------------ | C95: --图鉴------------------------------ | D95: --图鉴------------------ | E95: --图鉴------------------ | F95: =IF(D95<>E95,"已更改","")
A96: This is its pre- | B96: only harden, so it | C96: しんかを まっている じょうたい。 | D96: 等待进化的状态。 | E96: 一直都在等待进化。 | F96: =IF(D96<>E96,"已更改","") -> 已更改
A97: evolved form. At | B97: remains motionless | C97: かたくなる ことしか できないので | D97: 除了变硬什么都做不了， | E97: 除了变硬什么都做不了， | F97: =IF(D97<>E97,"已更改","")
A98: this stage, it can | B98: to avoid attack. | C98: おそわれないよう じっとしている。 | D98: 只能一动不动地避免袭击。 | E98: 为避免袭击只好保持不动。 | F98: =IF(D98<>E98,"已更改","") -> 已更改
F99: =IF(D99<>E99,"已更改","")
A100: --开始------------ | C100: PokeGuide012 | D100: butterfree | E100: butterfree | F100: =IF(D100<>E100,"已更改","")
...

Sheet 其
A1: |-编号---- | B1: |-英文---- | C1: |-日文---- | D1: |-翻译---- | E1: |-注释---- | F1: |-跳过----
A2: O001 | B2: ELM | C2: ウツギ | D2: 空木
A3: O002 | B3: EARL | C3: ジョバンニ | D3: 初始
A4: O003 | B4: KURT | C4: ガンテツ | D4: 钢铁
A5: O004 | B5: MOM | C5: ママ | D5: 妈妈
A6: O005 | B6: BUENA | C6: アオイ | D6: 葵妍
A7: O006 | B7: MR.#MON | C7: ポケモンじいさん | D7: 宝可梦爷爷
A8: O007 | B8: MARY | C8: クルミ | D8: 胡桃 | E8: 大木讲座
A9: O008 | B9: LILY | C9: リリス | D9: 莉莉丝 | E9: 那城这人 对红；朱顶红
A10: O009 | B10: REED | C10: ツゲ | D10: 阿植 | E10: 幸运频道
A11: O010 | B11: BEN | C11: セージ | D11: 靖史 | E11: 城都音乐 鼠尾草
A12: O011 | B12: FERN | C12: コージ | D12: 浩史 | E12: 关都音乐 鼠麴草
A13: O013 | B13: SILKTREE | C13: ネムノキ | D13: 合欢
A14: O014 | B14: MONICA | C14: ツキコ | D14: 星琪一
A15: O015 | B15: TUSCANY | C15: ヒコ | D15: 星琪二
A16: O016 | B16: WESLEY | C16: ミズオ | D16: 星祺三
A17: O017 | B17: ARTHUR | C17: モクオ | D17: 星祺四
A18: O018 | B18: FRIEDA | C18: カネコ | D18: 星琪五
A19: O019 | B19: SANTOS | C19: ツチオ | D19: 星祺六
A20: O020 | B20: SUNNY | C20: ニチオ | D20: 星祺天
A21: O021 | B21: MOVE DELETER | C21: わすれオヤジ | D21: 遗忘大叔 | E21: 忘记大叔 / 招式遗忘大叔
A22: O022 | B22: DUDE | C22: おにいさん | D22: 小哥
A23: O023 | B23: Master of the Dragon Tamer clan | C23: ドラゴンつかいいちぞくの長老さま | D23: 龙之长老 | E23: 根本无法对照，随便填写一下
A24: O024 | B24: MASTER | C24: ちょうろう | D24: 长老 | E24: MASTER全大写基本能对上长老（除了大师球对不上）
A25: O025 | B25: OAK | C25: オーキド | D25: 大木
A26: O026 | B26: DAISY | C26: ナナミ | D26: 奈奈美
A27: O027 | B27: GIOVANNI | C27: サカキ | D27: 坂木
A28: O028 | B28: LORELEI | C28: カンナ | D28: 科拿 | E28: 未出现
A29: O030 | B29: AGATHA | C29: キクコ | D29: 菊子
A30: O032 | B30: BILL | C30: マサキ | D30: 正辉
A31: O033 | B31: MR.FUJI | C31: フジろうじん | D31: 富士老人
A32: O034 | B32: FUJI | C32: フジ | D32: 富士
A33: O035 | B33: BAOBA | C33: バオバ | D33: 巴奥巴 | E33: 未出现
A34: O036 | B34: COPYCAT | C34: モノマネむすめ | D34: 模仿少女 | E34: Mimic Girl的写法不知道哪里来的
A35: O037 | B35: NAME RATER | C35: せいめいはんだんし | D35: 姓名鉴定师
A36: O038 | B36: type | C36: タイプ | D36: 属性
A37: O039 | B37: normal | C37: ノーマルタイプ | D37: 一般 | E37: 英文版小写，或者是normal-type
A38: O040 | B38: fire | C38: ほのおタイプ | D38: 火
A39: O041 | B39: water | C39: みずタイプ | D39: 水
A40: O042 | B40: electric | C40: でんきタイプ | D40: 电
A41: O043 | B41: grass | C41: くさタイプ | D41: 草
A42: O044 | B42: ice | C42: こおりタイプ | D42: 冰
A43: O045 | B43: fighting | C43: かくとうタイプ | D43: 格斗
A44: O046 | B44: poison | C44: どくタイプ | D44: 毒
A45: O047 | B45: ground | C45: じめんタイプ | D45: 地面
A46: O048 | B46: flying | C46: ひこうタイプ | D46: 飞行 | E46: 英文版小写，或者是flying-type
A47: O049 | B47: psychic | C47: エスパータイプ | D47: 超能力
A48: O050 | B48: bug | C48: むしタイプ | D48: 虫
A49: O051 | B49: rock | C49: いわタイプ | D49: 岩石
A50: O052 | B50: ghost | C50: ゴーストタイプ | D50: 幽灵
A51: O053 | B51: dragon | C51: ドラゴンタイプ | D51: 龙
A52: O054 | B52: dark | C52: あくタイプ | D52: 恶
A53: O055 | B53: steel | C53: はがねタイプ | D53: 钢
A54: O056 | B54: KANTO | C54: カントー | D54: 关都
A55: O057 | B55: JOHTO | C55: ジョウト | D55: 城都
A56: O058 | B56: BRASS TOWER | C56: かねのとう | D56: 金钟塔
A57: O059 | B57: #MON MUSIC | C57: ポケモン ミュージック | D57: 宝可梦音乐台
A58: O060 | B58: MUSIC | C58: ミュージック | D58: 音乐台
... A60: O062 | B60: TRAINER TIPS | C60: おとくな けいじばん！ | D60: 有用的公告牌！

Sheet 文1
A1: |---英文---------+ | C1: |---日文-------------------------+ | E1: |---翻译--------------+----------+ | H1: |---提词---------+ | I1: |---注释---------+ | J1: msg_heal_11_common
A2: Good morning! | C2: おはよう ございます！ | E2: 早上好！
A3: Welcome to our | C3: ポケモン センター です！ | E3: 这里是宝可梦中心！
A4: #MON CENTER.
A7: |---英文---------+ | C7: |---日文-------------------------+ | E7: |---翻译--------------+----------+ | H7: |---提词---------+ | I7: |---注释---------+ | J7: msg_heal_12_common
A8: Hello! | C8: こんにちは！ | E8: 你好！
A9: Welcome to our | C9: ポケモン センター です！ | E9: 这里是宝可梦中心！
A10: #MON CENTER.
A13: |---英文---------+ | C13: |---日文-------------------------+ | E13: |---翻译--------------+----------+ | H13: |---提词---------+ | I13: |---注释---------+ | J13: msg_heal_13_common
A14: Good evening! | C14: おそくまで おつかれさまです！ | E14: 坚持到这么晚，辛苦了！
A15: You're out late. | C15: ポケモン センター です！ | E15: 这里是宝可梦中心！
A17: Welcome to our
A18: #MON CENTER.
A21: |---英文---------+ | C21: |---日文-------------------------+ | E21: |---翻译--------------+----------+ | H21: |---提词---------+ | I21: |---注释---------+ | J21: msg_heal_11_01_common
A22: Good morning! | C22: おはよう ございます！ | E22: 早上好！
A24: This is the #- | C24: ポケモンコミュニケーションセンター | E24: 欢迎光临
A25: MON COMMUNICATION | C25: へ ようこそ！ | E25: 宝可梦对话中心！
A27: CENTER--or the
A28: #COM CENTER.
A31: |---英文---------+ | C31: |---日文-------------------------+ | E31: |---翻译--------------+----------+ | H31: |---提词---------+ | I31: |---注释---------+ | J31: msg_heal_12_01_common
A32: Hello! | C32: こんにちは！ | E32: 你好！
A34: This is the #- | C34: ポケモンコミュニケーションセンター | E34: 欢迎光临
A35: MON COMMUNICATION | C35: へ ようこそ！ | E35: 宝可梦对话中心！
A37: CENTER--or the
A38: #COM CENTER.
A41: |---英文---------+ | C41: |---日文-------------------------+ | E41: |---翻译--------------+----------+ | H41: |---提词---------+ | I41: |---注释---------+ | J41: msg_heal_13_01_common
A42: Good to see you | C42: おそくまで おつかれさまです！ | E42: 坚持到这么晚，辛苦了！
A43: working so late.
C44: ポケモンコミュニケーションセンター | E44: 欢迎来到
A45: This is the #- | C45: へ ようこそ！ | E45: 宝可梦对话中心！
A46: MON COMMUNICATION
A48: CENTER--or the
A49: #COM CENTER.
A52: |---英文---------+ | C52: |---日文-------------------------+ | E52: |---翻译--------------+----------+ | H52: |---提词---------+ | I52: |---注释---------+ | J52: msg_heal_01_common
A53: We can heal your | C53: ここでは ポケモンの | E53: 这里将会为您
A54: #MON to perfect | C54: たいりょく かいふくを します！ | E54: 回复宝可梦的体力！
A55: health.
C56: あなたの ポケモンを | E56: 要让你的宝可梦，
A57: Shall we heal your | C57: やすませて あげますか？ | E57: 休息一下吗？
A58: #MON?
A61: |---英文---------+ | C61: |---日文-------------------------+ | E61: |---翻译--------------+----------+ | H61: |---提词---------+ | I61: |---注释---------+ | J61: msg_heal_02_common
A62: OK, may I see your | C62: それでは | E62: 那么，
A63: #MON? | C63: あずからせて いただきます！ | E63: 就交给我吧！
A66: |---英文---------+ | C66: |---日文-------------------------+ | E66: |---翻译--------------+----------+ | H66: |---提词---------+ | I66: |---注释---------+ | J66: msg_heal_03_common
A67: Thank you for | C67: おまちどおさま！ | E67: 久等了！
A68: waiting.
C69: おあずかり した ポケモンは | E69: 交给我的宝可梦
A70: Your #MON are | C70: みんな げんきに なりましたよ！ | E70: 全都变得精力充沛了哦！
A71: fully healed.
A74: |---英文---------+ | C74: |---日文-------------------------+ | E74: |---翻译--------------+----------+ | H74: |---提词---------+ | I74: |---注释---------+ | J74: msg_heal_04_common
A75: We hope to see you | C75: またの | E75: 欢迎
A76: again. | C76: ごりようを おまち してます！ | E76: 下次再来！
A79: |---英文---------+ | C79: |---日文-------------------------+ | E79: |---翻译--------------+----------+ | H79: |---提词---------+ | I79: |---注释---------+ | J79: msg_heal_05_common
A80: We hope to see you | C80: またの | E80: 欢迎 | I80: 未找到文本关联
A81: again. | C81: ごりようを おまち してます！ | E81: 下次再来！
A84: |---英文---------+ | C84: |---日文-------------------------+ | E84: |---翻译--------------+----------+ | H84: |---提词---------+ | I84: |---注释---------+ | J84: msg_heal_10_common
A85: Your #MON | C85: おあずかり した ポケモンに | E85: 您交给我们的宝可梦
A86: appear to be | C86: なんだか ちいさな せいめいたいが | E86: 身上似乎附着着
C87: くっついて いるようです | E87: 微小生命体。
A88: infected by tiny
A89: life forms. | C89: ポケモンは げんき ですし | E89: 宝可梦很健康。
C90: もんだい なさそうですけど | E90: 虽说没有什么大碍，
A91: Your #MON are | C91: ポケモン センターでは | E91: 但是在宝可梦中心
A92: healthy and seem | C92: これいじょうの ことは わかりません | E92: 无法得知更多的情况。
A93: to be fine.
A95: But we can't tell
A96: you anything more
A98: at a #MON
A99: CENTER.
A102: |---英文---------+ | C102: |---日文-------------------------+ | E102: |---翻译--------------+----------+ | H102: |---提词---------+ | I102: |---注释---------+ | J102: msg_heal_10_01_common
A103: Your #MON | C103: おあずかり した ポケモンに | E103: 您交给我们的宝可梦
A104: appear to be | C104: なんだか ちいさな せいめいたいが | E104: 身上似乎附着着
C105: くっついて いるようです | E105: 微小生命体。
A106: infected by tiny
A107: life forms. | C107: ポケモンは げんき ですし | E107: 宝可梦很健康。
C108: もんだい なさそうですけど | E108: 虽说没有什么大碍，
A109: Your #MON are | C109: こちらでは | E109: 但是我们
A110: healthy and seem | C110: これいじょうの ことは わかりません | E110: 无法得知更多的情况。
A111: to be fine.
A113: But we can't tell
A114: you anything more.
A117: |---英文---------+ | C117: |---日文-------------------------+ | E117: |---翻译--------------+----------+ | H117: |---提词---------+ | I117: |---注释---------+ | J117: msg_shelves01_common
A118: It's full of | C118: むずかしい ほんで いっぱいだ！ | E118: 摆满了很复杂的书！ | I118: 摆满了很复杂的书！
A119: difficult books.
A122: |---英文---------+ | C122: |---日文-------------------------+ | E122: |---翻译--------------+----------+ | H122: |---提词---------+ | I122: |---注释---------+ | J122: msg_shelves02_common
A123: A whole collection | C123: ポケモンえほんが そろってる！ | E123: 放着一整套宝可梦绘本！ | I123: 放着一整套宝可梦绘本！
A124: of #MON picture
A125: books!
A128: |---英文---------+ | C128: |---日文-------------------------+ | E128: |---翻译--------------+----------+ | H128: |---提词---------+ | I128: |---注释---------+ | J128: msg_shelves03_common
A129: #MON magazines… | C129: ポケモンざっしが ならんでる！ | E129: 陈列着宝可梦的杂志！ | I129: 陈列着宝可梦的杂志！
A130: #MON PAL,
C131: ……ポケモンのとも | E131: ……宝可梦之友 | I131: ……宝可梦之友
A132: #MON HANDBOOK, | C132: ……ポケモン てちょう | E132: ……宝可梦手册 | I132: ……宝可梦手册
A133: #MON GRAPH… | C133: ……ポケモン グラフ | E133: ……宝可梦画报 | I133: ……宝可梦画报
A136: |---英文---------+ | C136: |---日文-------------------------+ | E136: |---翻译--------------+----------+ | H136: |---提词---------+ | I136: |---注释---------+ | J136: msg_shelves04_common
A137: TEAM ROCKET OATH | C137: ロケットだんの こころえ | E137: 火箭队心得：
A139: Steal #MON for | C139: ポケモンを うばって かねもうけ！ | E139: 抢夺宝可梦，发财不是梦！
A140: profit! | C140: ポケモンを つかって かねもうけ！ | E140: 使唤宝可梦，实现发财梦！
A142: Exploit #MON | C142: すべての ポケモンは | E142: 所有宝可梦都是
A143: for profit! | C143: ロケットだんの ために！ | E143: 为了火箭队而生！
...

Sheet 文2
A1: |---英文---------+ | C1: |---日文-------------------------+ | E1: |---翻译--------------+----------+ | H1: |---提词---------+ | I1: |---注释---------+ | J1: msg_bird04_01_d27r0103
A2: Why are you here? | C2: きみは なんなんだ？ | E2: 你是来干嘛的？
A3: Are you just going | C3: おみまいか？ ひやかしか？ | E3: 探望？闲逛？
C4: ひやかしなら かえってもらうよ！ | E4: 闲逛的话还是回去吧！
A5: to gawk? I suggest
A6: that you leave!
A9: |---英文---------+ | C9: |---日文-------------------------+ | E9: |---翻译--------------+----------+ | H9: |---提词---------+ | I9: |---注释---------+ | J9: msg_bird04_02_d27r0103
A10: You really are | C10: ほんき だね | E10: 不是来玩啊……
A11: concerned… | C11: おみまい するんだね | E11: 真的是来探望呢。
A14: |---英文---------+ | C14: |---日文-------------------------+ | E14: |---翻译--------------+----------+ | H14: |---提词---------+ | I14: |---注释---------+ | J14: msg_bird04_03_d27r0103
A15: How the heck do | C15: どうやって うえに のぼるんだ？ | E15: 顶层要怎么走啊？
A16: you go up? | C16: おみまいに いきたいのに | E16: 本来想去探望一下的，
C17: いけなくて こまってるんだよ | E17: 却找不到路，头疼。
A18: I want to visit
A19: the sick #MON,
A21: but I can't get up
A22: there…
A25: |---英文---------+ | C25: |---日文-------------------------+ | E25: |---翻译--------------+----------+ | H25: |---提词---------+ | I25: |---注释---------+ | J25: msg_sailor03_01_d27r0103
A26: Sailors are both | C26: うみのおとこは つよさと やさしさ | E26: 海上男儿既强大
A27: kind and strong. | C27: その ２つを かねそなえている | E27: 又不失温柔。
A28: How about you? | C28: きみは どうなんだ？ | E28: 你又是哪种人呢？
A31: |---英文---------+ | C31: |---日文-------------------------+ | E31: |---翻译--------------+----------+ | H31: |---提词---------+ | I31: |---注释---------+ | J31: msg_sailor03_02_d27r0103
A32: You are both kind | C32: きみの たたかいかた | E32: 你的战斗方式
A33: and strong… | C33: つよさと やさしさが かんじられる | E33: 温柔而强大呢。
A36: |---英文---------+ | C36: |---日文-------------------------+ | E36: |---翻译--------------+----------+ | H36: |---提词---------+ | I36: |---注释---------+ | J36: msg_sailor03_03_d27r0103
A37: Every time I come | C37: アサギに もどるたび | E37: 只要我回到浅葱市，
A38: back to OLIVINE, I | C38: ポケモンジムに よってたのだが…… | E38: 必定会去一趟道馆。
A39: visit the GYM.
C40: ジムリーダーの つかう ポケモンの | E40: 馆主使用的宝可梦属性 | H40: =_xlfn.TEXTJOIN(":",TRUE,类!C2,类!D2) -> ジムリーダー:道馆馆主
A41: The GYM LEADER's | C41: タイプが いつのまにか かわってたよ | E41: 似乎和以前不太一样…… | H41: =_xlfn.TEXTJOIN(":",TRUE,其!C36,其!D36) -> タイプ:属性
A42: #MON type has
A44: changed without me
A45: noticing.
A48: |---英文---------+ | C48: |---日文-------------------------+ | E48: |---翻译--------------+----------+ | H48: |---提词---------+ | I48: |---注释---------+ | J48: msg_gentle01_01_d27r0103
A49: I travel the world | C49: わたしは せかいを たびして | E49: 我周游世界，
A50: to train my #- | C50: ポケモンを きたえている | E50: 以此来锻炼宝可梦。
A51: MON. I wish to | C51: ちょっと しょうぶ してもらいますぞ | E51: 来和我对战吧！
A52: battle with you.
A55: |---英文---------+ | C55: |---日文-------------------------+ | E55: |---翻译--------------+----------+ | H55: |---提词---------+ | I55: |---注释---------+ | J55: msg_gentle01_02_d27r0103
A56: …sigh… I must | C56: はあ…… | E56: 哎……
A57: train some more… | C57: まだまだ しゅぎょうが たりないな | E57: 修行还不够啊……
A60: |---英文---------+ | C60: |---日文-------------------------+ | E60: |---翻译--------------+----------+ | H60: |---提词---------+ | I60: |---注释---------+ | J60: msg_gentle01_03_d27r0103
A61: JASMINE used to | C61: ミカンさんは もともと | E61: 以前的阿蜜用的都是 | H61: =_xlfn.TEXTJOIN(":",TRUE,训!C7,训!D7) -> ミカン:阿蜜
A62: use rock #MON | C62: イワークなど いわタイプの | E62: 大岩蛇一类的宝可梦， | H62: =_xlfn.TEXTJOIN(" ",TRUE,_xlfn.TEXTJOIN(":",TRUE,宝!C96,宝!D96),_xlfn.TEXTJOIN(":",TRUE,其!C49,其!D49)) -> イワーク:大岩蛇 いわタイプ:岩石
A63: like ONIX. | C63: ポケモンを つかう | E63: 那时还是擅长岩石属性的 | I63: 是擅长岩石属性的
C64: ポケモントレーナー だったのだ | E64: 宝可梦训练家。 | H64: =_xlfn.TEXTJOIN(":",TRUE,类!C13,类!D13) -> ポケモントレーナー:宝可梦训练家
A67: |---英文---------+ | C67: |---日文-------------------------+ | E67: |---翻译--------------+----------+ | H67: |---提词---------+ | I67: |---注释---------+ | J67: msg_sailor04_01_d27r0104
A68: JASMINE must be | C68: ミカンちゃん…… | E68: 阿蜜…… | H68: =_xlfn.TEXTJOIN(":",TRUE,训!C7,训!D7) -> ミカン:阿蜜
A69: worried sick about | C69: ポケモンが しんぱい なんだろな | E69: 很担心宝可梦呢……
A70: the #MON here. | C70: クスリ とも わらわないんだ | E70: 仿佛要永远地失去笑容了。
A72: She won't even
A73: smile these days.
A76: |---英文---------+ | C76: |---日文-------------------------+ | E76: |---翻译--------------+----------+ | H76: |---提词---------+ | I76: |---注释---------+ | J76: msg_sailor04_02_d27r0104
A77: I can't manage a | C77: おれも わらえない…… | E77: 我也要忘记怎么笑了……
A78: smile either…
A81: |---英文---------+ | C81: |---日文-------------------------+ | E81: |---翻译--------------+----------+ | H81: |---提词---------+ | I81: |---注释---------+ | J81: msg_sailor04_03_d27r0104
A82: Speaking of sick, | C82: くすり…… | E82: 要……药！
A83: I've heard there's | C83: そうだ！ タンバには うでのいい | E83: 我记得听别人说过，
C84: くすりやが いるって はなしだ！ | E84: 湛蓝市有家妙手药店！
A85: a good PHARMACY in
A86: CIANWOOD.
A89: |---英文---------+ | C89: |---日文-------------------------+ | E89: |---翻译--------------+----------+ | H89: |---提词---------+ | I89: |---注释---------+ | J89: msg_mini05_01_d27r0104
A90: JASMINE is this | C90: ミカンちゃん | E90: 阿蜜毕竟还是 | H90: =_xlfn.TEXTJOIN(":",TRUE,训!C7,训!D7) -> ミカン:阿蜜
A91: city's GYM LEADER. | C91: このまちの ジムリーダーなのに…… | E91: 这个城市的道馆馆主…… | H91: =_xlfn.TEXTJOIN(":",TRUE,类!C2,类!D2) -> ジムリーダー:道馆馆主
A93: I mean to bring | C93: あたし つれもどす つもりなの | E93: 我一定要把她带回去！
A94: her back with me. | C94: だれにも じゃまは させないわよ！ | E94: 谁也别想妨碍我！
A96: Nobody had better
A97: get in my way!
A100: |---英文---------+ | C100: |---日文-------------------------+ | E100: |---翻译--------------+----------+ | H100: |---提词---------+ | I100: |---注释---------+ | J100: msg_mini05_02_d27r0104
A101: Aaack! My #MON! | C101: ああ わたしの ポケモン！ | E101: 啊啊，我的宝可梦！
A104: |---英文---------+ | C104: |---日文-------------------------+ | E104: |---翻译--------------+----------+ | H104: |---提词---------+ | I104: |---注释---------+ | J104: msg_mini05_03_d27r0104
A105: Right. Anybody | C105: そうね だれだって ポケモン | E105: 宝可梦受伤了的话，
A106: would be worried | C106: きずついたら しんぱい するわよね | E106: 确实很让人担心呢。
A107: if his or her own
A108: #MON were hurt. | C108: ミカンちゃんが ジムに もどれるよう | E108: 我会在这里祈祷， | H108: =_xlfn.TEXTJOIN(":",TRUE,训!C7,训!D7) -> ミカン:阿蜜
C109: わたし おいのり するわ | E109: 希望阿蜜尽快重返道馆。
A110: I'll pray for the
A111: #MON here, so
A113: JASMINE can come
A114: back to the GYM.
A117: |---英文---------+ | C117: |---日文-------------------------+ | E117: |---翻译--------------+----------+ | H117: |---提词---------+ | I117: |---注释---------+ | J117: msg_sailor05_01_d27r0105
A118: I wanted to battle | C118: ミカンさんと しょうぶ したかったが | E118: 本来是想和阿蜜对战的， | H118: =_xlfn.TEXTJOIN(":",TRUE,训!C7,训!D7) -> ミカン:阿蜜
A119: JASMINE, but she's | C119: それどころじゃ ないようだ | E119: 但现在好像不是时候。
C120: かわりに あいて してくれんかね | E120: 那就让你来代替她吧！
A121: not up to it now.
A122: So, how about you?
A125: |---英文---------+ | C125: |---日文-------------------------+ | E125: |---翻译--------------+----------+ | H125: |---提词---------+ | I125: |---注释---------+ | J125: msg_sailor05_02_d27r0105
A126: Whoa, whoa. You're | C126: おお おお！ | E126: 哦、哦！
A127: overwhelming! | C127: なんという つよさだ！ | E127: 强到离谱！
A130: |---英文---------+ | C130: |---日文-------------------------+ | E130: |---翻译--------------+----------+ | H130: |---提词---------+ | I130: |---注释---------+ | J130: msg_sailor05_03_d27r0105
A131: A GYM LEADER isn't | C131: つよいだけが ジムリーダー じゃない | E131: 馆主不仅要有强大的实力， | H131: =_xlfn.TEXTJOIN(":",TRUE,类!C2,类!D2) -> ジムリーダー:道馆馆主
A132: just about being | C132: やさしさも ひつよう ってことだな | E132: 还需要一颗温柔的心。
A134: strong. A LEADER
A135: also needs to be
A136: compassionate.
A139: |---英文---------+ | C139: |---日文-------------------------+ | E139: |---翻译--------------+----------+ | H139: |---提词---------+ | I139: |---注释---------+ | J139: msg_bird06_01_d27r0105
A140: We're pretty high | C140: そらが ちかいからな | E140: 天空近在咫尺，
A141: up here. My bird | C141: ぼくの とりポケ ぜっこうちょう！ | E141: 我的鸟宝可梦状态绝佳！
A143: #MON are in
A144: prime form.
...

Sheet 文3
A1: |---英文---------+ | C1: |---日文-------------------------+ | E1: |---翻译--------------+----------+ | H1: |---提词---------+ | I1: |---注释---------+ | J1: NoEggMSG_000_Itemmain
A2: An EGG can't hold | C2: タマゴには | E2: 无法让蛋 | H2: =_xlfn.TEXTJOIN(":",TRUE,宝!C254,宝!D254) -> タマゴ:蛋
A3: an item. | C3: もたせることが できません！ | E3: 携带道具！
A6: |---英文---------+ | C6: |---日文-------------------------+ | E6: |---翻译--------------+----------+ | H6: |---提词---------+ | I6: |---注释---------+ | J6: NoItemMSG_001_Itemmain
A7: No items. | C7: もっていません | E7: 没有携带任何道具。
A10: |---英文---------+ | C10: |---日文-------------------------+ | E10: |---翻译--------------+----------+ | H10: |---提词---------+ | I10: |---注释---------+ | J10: TrashCountMSG_002_Itemmain
A11: Throw away how | C11: いくつ すてますか？ | E11: 要丢弃多少个？
A12: many?
A15: |---英文---------+ | C15: |---日文-------------------------+ | E15: |---翻译--------------+----------+ | H15: |---提词---------+ | I15: |---注释---------+ | J15: ReconfirmMSG_003_Itemmain
A16: Throw away 【1】 | C16: 【0】を 【1】こ | E16: 丢弃【1】个【0】， | J16: text_ram wStringBuffer2
A17: 【0】(S)? | C17: すててもよろしいですか？ | E17: 可以吗？ | J17: text_decimal wItemQuantityChange, 1, 2
A20: |---英文---------+ | C20: |---日文-------------------------+ | E20: |---翻译--------------+----------+ | H20: |---提词---------+ | I20: |---注释---------+ | J20: TrashedMSG_004_Itemmain
A21: Threw away | C21: 【0】を | E21: 【0】被 | J21: text_ram wStringBuffer2
A22: 【0】(S). | C22: すてました！ | E22: 丢弃了！
A25: |---英文---------+ | C25: |---日文-------------------------+ | E25: |---翻译--------------+----------+ | H25: |---提词---------+ | I25: |---注释---------+ | J25: InpossibleMSG_005_Itemmain
A26: OAK: <PLAYER>! | C26: オーキドの ことば…… | E26: 大木博士说过…… | H26: =_xlfn.TEXTJOIN(":",TRUE,其!C25,其!D25) -> オーキド:大木
A27: This isn't the | C27: <PLAYER>よ！ こういうものには | E27: <PLAYER>！这种东西
A28: time to use that! | C28: つかいどきが あるのじゃ！ | E28: 是要看场合来用的啊！
A31: |---英文---------+ | C31: |---日文-------------------------+ | E31: |---翻译--------------+----------+ | H31: |---提词---------+ | I31: |---注释---------+ | J31: NoMonsMSG_006_Itemmain
A32: You don't have a | C32: ポケモンを もっていません！ | E32: 没有同行宝可梦！
A33: #MON!
A36: |---英文---------+ | C36: |---日文-------------------------+ | E36: |---翻译--------------+----------+ | H36: |---提词---------+ | I36: |---注释---------+ | J36: EntryMSG_007_Itemmain
A37: Registered the | C37: 【0】を | E37: 将【0】 | J37: text_ram wStringBuffer2
A38: 【0】. | C38: べんりボタンに とうろくした！ | E38: 添加到了快捷键！ | I38: 添加到了便利键！
A41: |---英文---------+ | C41: |---日文-------------------------+ | E41: |---翻译--------------+----------+ | H41: |---提词---------+ | I41: |---注释---------+ | J41: CannotEntryMSG_008_Itemmain
A42: You can't register | C42: そのどうぐは | E42: 那个道具
A43: that item. | C43: とうろくできません！ | E43: 无法被添加！
A46: |---英文---------+ | C46: |---日文-------------------------+ | E46: |---翻译--------------+----------+ | H46: |---提词---------+ | I46: |---注释---------+ | J46: ExchangeMSG_009_Itemmain
A47: Where should this | C47: どこに | E47: 要移动
A48: be moved to? | C48: いどう しますか？ | E48: 到哪里吗？
A51: |---英文---------+ | C51: |---日文-------------------------+ | E51: |---翻译--------------+----------+ | H51: |---提词---------+ | I51: |---注释---------+ | J51: BattleCannotEntry_010_Itemmain
A55: |---英文---------+ | C55: |---日文-------------------------+ | E55: |---翻译--------------+----------+ | H55: |---提词---------+ | I55: |---注释---------+ | J55: BattleCannotUseMS_011_Itemmain
A56: You can't use it | C56: せんとう ちゅうは | E56: 战斗中
A57: in a battle. | C57: できません！ | E57: 不能使用！
A60: |---英文---------+ | C60: |---日文-------------------------+ | E60: |---翻译--------------+----------+ | H60: |---提词---------+ | I60: |---注释---------+ | J60: anata_msg_000_Kojindat
A61: Are you a boy? | C61: あなたは おとこのこ ですか？ | E61: 你是男孩吗？
A62: Or are you a girl? | C62: それとも おんなのこ ですか？ | E62: 还是女孩呢？
A65: |---英文---------+ | C65: |---日文-------------------------+ | E65: |---翻译--------------+----------+ | H65: |---提词---------+ | I65: |---注释---------+ | J65: seikou_msg_000_Kougeki
A66: <USER>'s | C66: <USER>の | E66: <USER>的 | J66: text_ram wStringBuffer2
A67: 【0】 | C67: 【0】が | E67: 【0】
A70: |---英文---------+ | C70: |---日文-------------------------+ | E70: |---翻译--------------+----------+ | H70: |---提词---------+ | I70: |---注释---------+ | J70: gunto_msg_001_Kougeki
A71: 【0】<SCROLL>went way up! | C71: 【0】<SCROLL>ぐーんと あがった！ | E71: 【0】<SCROLL>大幅提高了！ | I71: 算超过吗？ --- 不算 --- 删除特殊符号，需要注意文本效果 | J71: text_pause
I72: 【0】<SCROLL>大幅提高了！
A74: |---英文---------+ | C74: |---日文-------------------------+ | E74: |---翻译--------------+----------+ | H74: |---提词---------+ | I74: |---注释---------+ | J74: agatta_msg_001_Kougeki
A75: went up! | C75: あがった！ | E75: 提高了！
A78: |---英文---------+ | C78: |---日文-------------------------+ | E78: |---翻译--------------+----------+ | H78: |---提词---------+ | I78: |---注释---------+ | J78: seikou_msg_002_Kougeki
A79: <TARGET>'s | C79: <TARGET>の | E79: <TARGET>的 | J79: text_ram wStringBuffer2
A80: 【0】 | C80: 【0】が | E80: 【0】
A83: |---英文---------+ | C83: |---日文-------------------------+ | E83: |---翻译--------------+----------+ | H83: |---提词---------+ | I83: |---注释---------+ | J83: gakutto_msg_003_Kougeki
A84: 【0】<SCROLL>sharply fell! | C84: 【0】<SCROLL>がくっと さがった！ | E84: 【0】<SCROLL>大幅降低了！ | I84: 同上 -- 不算 --- 删除特殊符号，需要注意文本效果 | J84: text_pause
I85: 【0】<SCROLL>大幅降低了！
A87: |---英文---------+ | C87: |---日文-------------------------+ | E87: |---翻译--------------+----------+ | H87: |---提词---------+ | I87: |---注释---------+ | J87: sagatta_msg_003_Kougeki
A88: fell! | C88: さがった！ | E88: 降低了！
A91: |---英文---------+ | C91: |---日文-------------------------+ | E91: |---翻译--------------+----------+ | H91: |---提词---------+ | I91: |---注释---------+ | J91: message_004_Kougeki
A92: <USER> | C92: <USER> | E92: |
A95: |---英文---------+ | C95: |---日文-------------------------+ | E95: |---翻译--------------+----------+ | H95: |---提词---------+ | I95: |---注释---------+ | J95: kamaitachi_msg_005_Kougeki
C96: の まわりで | E96: <USER>
A97: made a whirlwind! | C97: くうきが うずを まく！ | E97: 周围的空气产生了旋涡！
A100: |---英文---------+ | C100: |---日文-------------------------+ | E100: |---翻译--------------+----------+ | H100: |---提词---------+ | I100: |---注释---------+ | J100: solarbeam_msg_006_Kougeki
C101: は | E101: <USER>
A102: took in sunlight! | C102: ひかりを きゅうしゅうした！ | E102: 吸收了光！
A105: |---英文---------+ | C105: |---日文-------------------------+ | E105: |---翻译--------------+----------+ | H105: |---提词---------+ | I105: |---注释---------+ | J105: rocketzutuki_msg_007_Kougeki
C106: は | E106: <USER>
A107: lowered its head! | C107: くびを ひっこめた！ | E107: 把头缩了进去！
A110: |---英文---------+ | C110: |---日文-------------------------+ | E110: |---翻译--------------+----------+ | H110: |---提词---------+ | I110: |---注释---------+ | J110: godbird_msg_008_Kougeki
C111: を | E111: 强光包围了 | I111: 对象名字需要换行
A112: is glowing! | C112: はげしい ひかりが つつむ！ | E112: <USER>！
A115: |---英文---------+ | C115: |---日文-------------------------+ | E115: |---翻译--------------+----------+ | H115: |---提词---------+ | I115: |---注释---------+ | J115: kyuukouka_msg_009_Kougeki
C116: は | E116: <USER>
A117: flew up high! | C117: そらたかく とびあがった！ | E117: 飞向了高空！
A120: |---英文---------+ | C120: |---日文-------------------------+ | E120: |---翻译--------------+----------+ | H120: |---提词---------+ | I120: |---注释---------+ | J120: anawohoru_msg_010_Kougeki
C121: は | E121: <USER>
A122: dug a hole! | C122: あなをほって ちちゅうに もぐった！ | E122: 挖洞钻入了地下！
A125: |---英文---------+ | C125: |---日文-------------------------+ | E125: |---翻译--------------+----------+ | H125: |---提词---------+ | I125: |---注释---------+ | J125: message_011_Kougeki
A126: <USER> | C126: <USER> | E126: <USER>
A129: |---英文---------+ | C129: |---日文-------------------------+ | E129: |---翻译--------------+----------+ | H129: |---提词---------+ | I129: |---注释---------+ | J129: no_012_Kougeki
C130: の | E130: |
A131: used
A134: |---英文---------+ | C134: |---日文-------------------------+ | E134: |---翻译--------------+----------+ | H134: |---提词---------+ | I134: |---注释---------+ | J134: ha_013_Kougeki
C135: は | E135: | | I135: 这啥
A136: used
A139: |---英文---------+ | C139: |---日文-------------------------+ | E139: |---翻译--------------+----------+ | H139: |---提词---------+ | I139: |---注释---------+ | J139: meireimushi_msg_014_Kougeki
A140: instead, | C140: めいれいをむしして | E140: 无视命令
A144: |---英文---------+ | C144: |---日文-------------------------+ | E144: |---翻译--------------+----------+ | H144: |---提词---------+ | I144: |---注释---------+ | J144: waza_msg_015_Kougeki
A145: 【0】 | J145: text_ram wStringBuffer2
C146: 【0】 | E146: 使出了【0】
A149: |---英文---------+ | C149: |---日文-------------------------+ | E149: |---翻译--------------+----------+ | H149: |---提词---------+ | I149: |---注释---------+ | J149: wo_tukatta_msg_016_Kougeki
A150: ! | C150: を つかった！ | E150: ！
A153: |---英文---------+ | C153: |---日文-------------------------+ | E153: |---翻译--------------+----------+ | H153: |---提词---------+ | I153: |---注释---------+ | J153: sita_msg_017_Kougeki
A154: ! | C154: した！ | E154: ！
A157: |---英文---------+ | C157: |---日文-------------------------+ | E157: |---翻译--------------+----------+ | H157: |---提词---------+ | I157: |---注释---------+ | J157: wo_sita_msg_018_Kougeki
A158: ! | C158: を した！ | E158: ！
A161: |---英文---------+ | C161: |---日文-------------------------+ | E161: |---翻译--------------+----------+ | H161: |---提词---------+ | I161: |---注释---------+ | J161: kougeki_msg_019_Kougeki
A162: ! | C162: こうげき！ | E162: ！
A165: |---英文---------+ | C165: |---日文-------------------------+ | E165: |---翻译--------------+----------+ | H165: |---提词---------+ | I165: |---注释---------+ | J165: direct_msg_020_Kougeki
A166: ! | C166: ！ | E166: ！
A169: |---英文---------+ | C169: |---日文-------------------------+ | E169: |---翻译--------------+----------+ | H169: |---提词---------+ | I169: |---注释---------+ | J169: umareta_msg_000_Kozukuri
A170: Huh? | C170: あれ…………？ | E170: 哦…………？
A172: | | C172: | | E172: |
A175: |---英文---------+ | C175: |---日文-------------------------+ | E175: |---翻译--------------+----------+ | H175: |---提词---------+ | I175: |---注释---------+ | J175: dummyMSG_001_Kozukuri
...

Sheet 文4
A1: |---英文---------+ | C1: |---日文-------------------------+ | E1: |---翻译--------------+----------+ | H1: |---提词---------+ | I1: |---注释---------+ | J1: msg_oldwoman_01_r05r0401
A2: Eeyaaaah! | C2: きえーーーいっ！ | E2: 消失——吧！
A4: I sense a sinister | C4: おぬしに ふきつな カゲが | E4: 有个不吉利的影子
A5: shadow hovering | C5: とりついて おるうっ！ | E5: 附在施主身上！
A6: over you. | C6: これを もっていくが よい！ | E6: 请你带上这个！
A8: Take this to ward
A9: it off!
A12: |---英文---------+ | C12: |---日文-------------------------+ | E12: |---翻译--------------+----------+ | H12: |---提词---------+ | I12: |---注释---------+ | J12: msg_oldwoman_02_r05r0401
A13: You were in mortal | C13: あぶないところ じゃった！ | E13: 真是好险啊！
A14: danger, but you | C14: これで あんしんじゃ！ | E14: 这下就能放心了！
A15: are protected now.
A18: |---英文---------+ | C18: |---日文-------------------------+ | E18: |---翻译--------------+----------+ | H18: |---提词---------+ | I18: |---注释---------+ | J18: msg_womana_00_r05r0401
A19: My grandma is into | C19: うちの おばあちゃん | E19: 我家的奶奶呀，
A20: warding off what | C20: おはらいに こってるのよ | E20: 一直很热衷于驱邪。
C21: ごめんね おどろかせちゃって | E21: 抱歉啊，让你受惊了。
A22: she believes to be
A23: evil spirits.
A25: I'm sorry that she
A26: startled you.
A29: |---英文---------+ | C29: |---日文-------------------------+ | E29: |---翻译--------------+----------+ | H29: |---提词---------+ | I29: |---注释---------+ | J29: msg_middlem_00_r06
A30: The road is closed | C30: はつでんしょの じこが | E30: 在发电厂的事故 | H30: =_xlfn.TEXTJOIN(":",TRUE,城!C19,城!D19) -> はつでんしょ:发电厂
A31: until the problem | C31: かいけつ するまで | E31: 得到解决之前，
C32: つうこうきんし なんだって！ | E32: 这里禁止通行！
A33: at the POWER PLANT
A34: is solved.
A37: |---英文---------+ | C37: |---日文-------------------------+ | E37: |---翻译--------------+----------+ | H37: |---提词---------+ | I37: |---注释---------+ | J37: msg_sign01_00_r06
A38: UNDERGROUND PATH | C38: ここから ちかつうろ | E38: 前方是地下通道 | H38: =_xlfn.TEXTJOIN(":",TRUE,城!C101,城!D101) -> ちかつうろ:地下通道
C39: ハナダシティ …… クチバシティ | E39: 华蓝市 <……> 枯叶市 | H39: =_xlfn.TEXTJOIN(" ",TRUE,_xlfn.TEXTJOIN(":",TRUE,城!C31,城!D31),_xlfn.TEXTJOIN(":",TRUE,城!C33,城!D33)) -> ハナダシティ:华蓝市 クチバシティ:枯叶市
A40: CERULEAN CITY -
A41: VERMILION CITY
A44: |---英文---------+ | C44: |---日文-------------------------+ | E44: |---翻译--------------+----------+ | H44: |---提词---------+ | I44: |---注释---------+ | J44: msg_lovem_13_01_r06
A45: My PHANPY is the | C45: だから わたしの ゴマゾウちゃんが | E45: 所以说我的小小象 | H45: =_xlfn.TEXTJOIN(":",TRUE,宝!C232,宝!D232) -> ゴマゾウ:小小象
A46: cutest in the | C46: せかいで １ばん かわいいん です！ | E46: 是世界第1可爱！
A47: world.
A50: |---英文---------+ | C50: |---日文-------------------------+ | E50: |---翻译--------------+----------+ | H50: |---提词---------+ | I50: |---注释---------+ | J50: msg_lovem_13_02_r06
A51: My PHANPY! | C51: わたしの ゴマゾウちゃんがー！ | E51: 我的小小象啊——！ | H51: =_xlfn.TEXTJOIN(":",TRUE,宝!C232,宝!D232) -> ゴマゾウ:小小象
A54: |---英文---------+ | C54: |---日文-------------------------+ | E54: |---翻译--------------+----------+ | H54: |---提词---------+ | I54: |---注释---------+ | J54: msg_lovem_13_03_r06
A55: Look how adorable | C55: みてくださいよ この | E55: 你一定要看一下！
A56: my PHANPY acts! | C56: ゴマゾウちゃんの あまえた しぐさ！ | E56: 我家小小象撒娇的样子！ | H56: =_xlfn.TEXTJOIN(":",TRUE,宝!C232,宝!D232) -> ゴマゾウ:小小象
A58: Isn't it cute | C58: もう かわいくて かわいくて | E58: 真是可爱得不得了！
A59: enough to make | C59: クゥーって かんじに なるでしょ？ | E59: 是不是觉得心都融化了？
A60: your heart melt?
A63: |---英文---------+ | C63: |---日文-------------------------+ | E63: |---翻译--------------+----------+ | H63: |---提词---------+ | I63: |---注释---------+ | J63: msg_lovem_14_01_r06
A64: My TEDDIURSA is | C64: だから わたしの ヒメグマちゃんが | E64: 所以说我的熊宝宝 | H64: =_xlfn.TEXTJOIN(":",TRUE,宝!C217,宝!D217) -> ヒメグマ:熊宝宝
A65: the cutest in the | C65: せかいで １ばん かわいいん です！ | E65: 是世界第1可爱！
A66: world.
A69: |---英文---------+ | C69: |---日文-------------------------+ | E69: |---翻译--------------+----------+ | H69: |---提词---------+ | I69: |---注释---------+ | J69: msg_lovem_14_02_r06
A70: My TEDDIURSA! | C70: わたしの ヒメグマちゃんがー！ | E70: 我的熊宝宝啊——！ | H70: =_xlfn.TEXTJOIN(":",TRUE,宝!C217,宝!D217) -> ヒメグマ:熊宝宝
A73: |---英文---------+ | C73: |---日文-------------------------+ | E73: |---翻译--------------+----------+ | H73: |---提词---------+ | I73: |---注释---------+ | J73: msg_lovem_14_03_r06
A74: Look how adorable | C74: みてくださいよ この | E74: 你一定要看一下！
A75: my TEDDIURSA acts! | C75: ヒメグマちゃんの あまえた しぐさ！ | E75: 我家熊宝宝撒娇的样子！ | H75: =_xlfn.TEXTJOIN(":",TRUE,宝!C217,宝!D217) -> ヒメグマ:熊宝宝
A77: Isn't it cute | C77: もう かわいくて かわいくて | E77: 真是可爱得不得了！
A78: enough to make | C78: クゥーって かんじに なるでしょ？ | E78: 是不是觉得心都融化了？
A79: your heart melt?
A82: |---英文---------+ | C82: |---日文-------------------------+ | E82: |---翻译--------------+----------+ | H82: |---提词---------+ | I82: |---注释---------+ | J82: msg_counterm_01_r06r0201
A83: Welcome to SAFFRON | C83: リニア モーターカーのまち | E83: 欢迎来到
A84: CITY, home of the | C84: ヤマブキ シティへ ようこそ！ | E84: 磁浮列车之城——金黄市！
A85: MAGNET TRAIN!
C86: ……と いいたいけど | E86: 我是很想这么说……
A87: …That's what I'd | C87: はつでんしょで じこが あったらしく | E87: 但是发电厂好像出事了， | H87: =_xlfn.TEXTJOIN(":",TRUE,城!C19,城!D19) -> はつでんしょ:发电厂
A88: normally say, but | C88: でんきが おくられて こないから | E88: 完全不能输出电力。
C89: リニアが うごいて いないんだ | E89: 磁浮列车也跟着停运了。
A90: the MAGNET TRAIN
A91: isn't running now.
A93: It's not getting
A94: any electricity
A96: because there's
A97: something wrong
A99: with the POWER
A100: PLANT.
A103: |---英文---------+ | C103: |---日文-------------------------+ | E103: |---翻译--------------+----------+ | H103: |---提词---------+ | I103: |---注释---------+ | J103: msg_counterm_02_r06r0201
A104: The MAGNET TRAIN | C104: ヤマブキで ゆうめいな ものは | E104: 要说金黄市的特色，
A105: is the most famous | C105: やっぱり リニア だね！ | E105: 那当然是磁浮列车啦！
A107: thing about SAF-
A108: FRON.
A111: |---英文---------+ | C111: |---日文-------------------------+ | E111: |---翻译--------------+----------+ | H111: |---提词---------+ | I111: |---注释---------+ | J111: msg_sign01_00_r07
A112: What's this flyer? | C112: …… おしらせの チラシだ！ | E112: ……这里贴着一张告示！
A114: … Uncouth trainers | C114: さいきん ちかつうろで | E114: 最近有些没规矩的训练家 | H114: =_xlfn.TEXTJOIN(":",TRUE,城!C101,城!D101) -> ちかつうろ:地下通道
A115: have been holding | C115: マナーの わるい トレーナーたちが | E115: 聚集在地下通道
C116: ポケモン しょうぶを しています | E116: 进行宝可梦对战。
A117: battles in the
A118: UNDERGROUND PATH. | C118: ふきん じゅうみん から | E118: 住在附近的居民
C119: くじょうが あったので | E119: 向我们发来了投诉，
A120: Because of rising | C120: ちかつうろを へいさ しました！ | E120: 因此决定关闭地下通道！ | H120: =_xlfn.TEXTJOIN(":",TRUE,城!C101,城!D101) -> ちかつうろ:地下通道
A121: complaints by lo-
A122: cal residents, the | C122: …… タマムシ けいさつ より | E122: ……玉虹市警署留
A123: UNDERGROUND PATH
A124: has been sealed
A125: indefinitely.
A127: CELADON POLICE
A130: |---英文---------+ | C130: |---日文-------------------------+ | E130: |---翻译--------------+----------+ | H130: |---提词---------+ | I130: |---注释---------+ | J130: msg_door_00_r07
A131: It's locked… | C131: カギが かかっている！ | E131: 锁得紧紧的！
C132: ……あけられない！ | E132: ……打不开！
A135: |---英文---------+ | C135: |---日文-------------------------+ | E135: |---翻译--------------+----------+ | H135: |---提词---------+ | I135: |---注释---------+ | J135: msg_counterm_01_r07r0101
A136: Did you hear about | C136: はつでんしょで じこが | E136: 发电厂好像 | H136: =_xlfn.TEXTJOIN(":",TRUE,城!C19,城!D19) -> はつでんしょ:发电厂
A137: the accident at | C137: あったみたいだね | E137: 发生了什么事故。
A138: the POWER PLANT?
C139: はつでんしょは はんたいがわ | E139: 发电厂啊，去对面那侧 | H139: =_xlfn.TEXTJOIN(":",TRUE,城!C19,城!D19) -> はつでんしょ:发电厂
A140: It's located in | C140: シオンの ほうに あるよ | E140: 往紫苑镇方向走就是了。
A141: the East, close to
...

Sheet 文5
A1: |---英文---------+ | C1: |---日文-------------------------+ | E1: |---翻译--------------+----------+ | H1: |---提词---------+ | I1: |---注释---------+ | J1: msg_tree_01_r36
A2: It's a weird tree. | C2: おかしな き だ！ | E2: 有棵奇怪的树！
A3: Use SQUIRTBOTTLE? | C3: ゼニガメじょうろを つかいますか？ | E3: 要使用杰尼龟喷壶吗？ | H3: =_xlfn.TEXTJOIN(":",TRUE,道!C176,道!D176) -> ゼニガメじょうろ:杰尼龟喷壶
A6: |---英文---------+ | C6: |---日文-------------------------+ | E6: |---翻译--------------+----------+ | H6: |---提词---------+ | I6: |---注释---------+ | J6: msg_tree_02_r36
A7: <PLAYER> used the | C7: <PLAYER>は | E7: <PLAYER>使用了
A8: SQUIRTBOTTLE. | C8: ゼニガメじょうろを つかった！ | E8: 杰尼龟喷壶！ | H8: =_xlfn.TEXTJOIN(":",TRUE,道!C176,道!D176) -> ゼニガメじょうろ:杰尼龟喷壶
A11: |---英文---------+ | C11: |---日文-------------------------+ | E11: |---翻译--------------+----------+ | H11: |---提词---------+ | I11: |---注释---------+ | J11: msg_tree_03_r36
A12: The weird tree | C12: おかしな きは | E12: 奇怪的树好像很反感
A13: doesn't like the | C13: ゼニガメじょうろを いやがってる！ | E13: 杰尼龟喷壶！ | H13: =_xlfn.TEXTJOIN(":",TRUE,道!C176,道!D176) -> ゼニガメじょうろ:杰尼龟喷壶
A14: SQUIRTBOTTLE!
C15: おかしな きが おそいかかってきた！ | E15: 奇怪的树扑过来了！
A16: The weird tree
A17: attacked!
A20: |---英文---------+ | C20: |---日文-------------------------+ | E20: |---翻译--------------+----------+ | H20: |---提词---------+ | I20: |---注释---------+ | J20: msg_saki_01_r36
A21: I'm the FLOWER | C21: あたし フラワーショップの サキ | E21: 我是花店的绽芳。
A22: SHOP's FLORIA!
C23: ねーねー きいて きいて！ | E23: 听我说，听我说！
A24: Listen, listen!
C25: うごく きに みずを かけて みたら | E25: 我试着给会动的树浇水，
A26: When I sprinkled | C26: おどろいて とびあがったの！ | E26: 它居然吓了一跳！
A27: water on that
C28: きっと しょうたいは ポケモンなのよ | E28: 我猜它肯定是宝可梦！
A29: wiggly tree, it
A30: jumped right up! | C30: もっと みずを かければ おどろいて | E30: 再多浇点水吓吓它，
C31: しょうたいを あらわす はずよ！ | E31: 它一定会原形毕露！
A32: It just has to be
A33: a #MON. | C33: そうだ！ | E33: 对了！
C34: おねえちゃんに このことを はなして | E34: 我要把这件事告诉姐姐，
A35: I bet it would be | C35: じょうろを かして もらおーっと！ | E35: 让她把喷壶借给我！
A36: shocked out of its
A38: disguise if you
A39: soaked it!
A41: I know! I'll tell
A42: my sis and borrow
A43: her water bottle!
A46: |---英文---------+ | C46: |---日文-------------------------+ | E46: |---翻译--------------+----------+ | H46: |---提词---------+ | I46: |---注释---------+ | J46: msg_saki_02_r36
A47: When I told my sis | C47: うちの おねえちゃんに | E47: 我跟我姐姐讲了
A48: about the jiggly | C48: うごく きの はなしを したら | E48: 那棵会动的树的事情，
C49: あぶないから やめなさい だって！ | E49: 她却说太危险了别管它！
A50: tree, she said
A51: it's dangerous. | C51: アカネちゃんに かてたら | E51: 如果我能打赢小茜， | H51: =_xlfn.TEXTJOIN(":",TRUE,训!C3,训!D3) -> アカネ:小茜
C52: じょうろ かして くれるかなぁ…… | E52: 她就给我喷壶吧……
A53: If I beat WHITNEY,
A54: I wonder if she'll
A56: lend me her water
A57: bottle…
A60: |---英文---------+ | C60: |---日文-------------------------+ | E60: |---翻译--------------+----------+ | H60: |---提词---------+ | I60: |---注释---------+ | J60: msg_bigman_01_r36
A61: Wa-hey! | C61: うっす！ | E61: 你好呀！
A63: I was going to | C63: わいの キョーレツな ぶちかまし で | E63: 我本来以为，
A64: snap that tree | C64: き の １ぽんや ２ほん ぽっきりと | E64: 靠我那厚重的掌力，
C65: へしおって やろうと おもったが…… | E65: 推倒一两棵树不在话下……
A66: with my straight-
A67: arm punch. | C67: ダメだったで ごわす！ | E67: 但是办不到呀！
C68: むねんで ごわす！ | E68: 真是太遗憾了呀！
A69: But I couldn't!
A70: I'm a failure!
A73: |---英文---------+ | C73: |---日文-------------------------+ | E73: |---翻译--------------+----------+ | H73: |---提词---------+ | I73: |---注释---------+ | J73: msg_bigman_02_r36
A74: Did you clear that | C74: おぬしが あの ジャマな きを | E74: 是你帮我搞定了
A75: wretched tree? | C75: かたづけて くれたで ごわすか？ | E75: 那棵碍事的树？
A77: I'm impressed! | C77: おそれ いったで ごわす！ | E77: 真是令人惭愧呀！
A78: I want you to | C78: これを あげるで ごわす！ | E78: 我要送给你这个呀！
A79: have this.
A82: |---英文---------+ | C82: |---日文-------------------------+ | E82: |---翻译--------------+----------+ | H82: |---提词---------+ | I82: |---注释---------+ | J82: msg_bigman_03_r36
A83: <PLAYER> received | C83: <PLAYER>は | E83: <PLAYER>得到了
A84: TM08. | C84: わざマシン０８を もらった！ | E84: 招式学习器08！ | H84: =_xlfn.TEXTJOIN(":",TRUE,道!C200,道!D200) -> わざマシン０８:招式学习器08
A87: |---英文---------+ | C87: |---日文-------------------------+ | E87: |---翻译--------------+----------+ | H87: |---提词---------+ | I87: |---注释---------+ | J87: msg_bigman_04_r36
A88: That happens to be | C88: なかみは ひっさつ いわくだき！ | E88: 里面是必杀碎岩！ | H88: =_xlfn.TEXTJOIN(":",TRUE,招!C250,招!D250) -> いわくだき:碎岩
A89: ROCK SMASH. | C89: それが あれば | E89: 只要有了这个招式，
C90: いしっコロ なぞ いっぱつで ごわす | E90: 随手一击就能打碎岩块！
A91: You can shatter
A92: rocks with just a | C92: ジャマな いしっコロは | E92: 请你尽情地
C93: こわすが よろしいで ごわす！ | E93: 去击碎岩块呀！
A94: single well-aimed
A95: smack.
A97: If any rocks are
A98: in your way, just
A99: smash 'em up!
A102: |---英文---------+ | C102: |---日文-------------------------+ | E102: |---翻译--------------+----------+ | H102: |---提词---------+ | I102: |---注释---------+ | J102: msg_girl_01_r36
A103: An odd tree is | C103: おかしな きが はえちゃって | E103: 路上长了棵奇怪的树，
A104: blocking the way | C104: コガネに いけないのよー！ | E104: 没法去满金市了！
A105: to GOLDENROD CITY.
C106: すっごく ひろい ポケモンセンターが | E106: 之前有人告诉我，
A107: I wanted to go see | C107: できたって いうから | E107: 那里建了超大宝可梦中心，
A108: the huge #MON | C108: みに いこうと おもったのに | E108: 我真的好想去看看啊……
A110: CENTER they just
A111: opened…
A114: |---英文---------+ | C114: |---日文-------------------------+ | E114: |---翻译--------------+----------+ | H114: |---提词---------+ | I114: |---注释---------+ | J114: msg_girl_02_r36
A115: That odd tree dis- | C115: まるで いなくなったみたいに | E115: 那棵奇怪的树
A116: appeared without a | C116: おかしな き きえちゃった…… | E116: 消失得无影无踪……
A117: trace.
C118: えっ！ ポケモンだったの？ | E118: 什么！它是宝可梦？
A119: Oh! That tree was
A120: really a #MON?
A123: |---英文---------+ | C123: |---日文-------------------------+ | E123: |---翻译--------------+----------+ | H123: |---提词---------+ | I123: |---注释---------+ | J123: msg_esp07_01_r36
A124: I'm going to read | C124: きみの かんがえ あててみせる！ | E124: 让我猜猜你的心思！
A125: your thoughts!
A128: |---英文---------+ | C128: |---日文-------------------------+ | E128: |---翻译--------------+----------+ | H128: |---提词---------+ | I128: |---注释---------+ | J128: msg_esp07_02_r36
A129: I misread you! | C129: あたらなかった | E129: 没猜中！
A132: |---英文---------+ | C132: |---日文-------------------------+ | E132: |---翻译--------------+----------+ | H132: |---提词---------+ | I132: |---注释---------+ | J132: msg_esp07_03_r36
A133: I'd be strong if | C133: あいての かんがえを よんで | E133: 如果进攻时能预测对手，
...

Sheet 文6
A1: |---英文---------+ | C1: |---日文-------------------------+ | E1: |---翻译--------------+----------+ | H1: |---提词---------+ | I1: |---注释---------+ | J1: msg_matisu_01_t06r0701
A2: SURGE: Hey, you | C2: マチス『ヘーイ！ | E2: 马志士：Hey！ | H2: =_xlfn.TEXTJOIN(":",TRUE,训!C35,训!D35) -> マチス:马志士
A3: little tyke! | C3: プア リトル キッド！ | E3: Poor little kid！
A5: I have to hand it | C5: ミーに たたかいを いどむなんて | E5: 居然想向me发起挑战，
A6: to you. It may not | C6: ユーは みのほどしらず！ | E6: You真是不知天高地厚！
C7: ミーの エレクトリック ポケモン | E7: Me的electric宝可梦，
A8: be very smart to | C8: ナンバー ワン ねー！ | E8: 简直number one！
A9: challenge me, but
A10: it takes guts! | C10: せんじょうじゃ まけたこと | E10: Me在战场上
C11: アリマセーン！！ | E11: 从来没输过！！
A12: When it comes to
A13: electric #MON, | C13: ユーも てきの ソルジャー みたく | E13: 我要让you浑身麻麻的，
A14: I'm number one! | C14: びりびり シビレさせてあげるよ！ | E14: 就像敌方soldier那样！
A16: I've never lost on
A17: the battlefield.
A19: I'll zap you just
A20: like I did my
A21: enemies in war!
A24: |---英文---------+ | C24: |---日文-------------------------+ | E24: |---翻译--------------+----------+ | H24: |---提词---------+ | I24: |---注释---------+ | J24: msg_matisu_02_t06r0701
A25: SURGE: Arrrgh! | C25: マチス『オー ノー！ | E25: 马志士：Oh no！ | H25: =_xlfn.TEXTJOIN(":",TRUE,训!C35,训!D35) -> マチス:马志士
A26: You are strong! | C26: ユー は ストロング！ | E26: You真是strong！
A28: OK, kid. You get | C28: オッケー！ | E28: Ok！
A29: THUNDERBADGE! | C29: オレンジバッジ やるヨ！ | E29: 橙色徽章就给you了！
A32: |---英文---------+ | C32: |---日文-------------------------+ | E32: |---翻译--------------+----------+ | H32: |---提词---------+ | I32: |---注释---------+ | J32: msg_matisu_03_t06r0701
A33: <PLAYER> received | C33: <PLAYER>は マチスから | E33: <PLAYER>从马志士那里 | H33: =_xlfn.TEXTJOIN(":",TRUE,训!C35,训!D35) -> マチス:马志士
A34: THUNDERBADGE. | C34: オレンジバッジを もらった！ | E34: 得到了橙色徽章！
A37: |---英文---------+ | C37: |---日文-------------------------+ | E37: |---翻译--------------+----------+ | H37: |---提词---------+ | I37: |---注释---------+ | J37: msg_matisu_04_t06r0701
A38: SURGE: THUNDER- | C38: マチス『オレンジバッジ もってると | E38: 马志士：有了橙色徽章， | H38: =_xlfn.TEXTJOIN(":",TRUE,训!C35,训!D35) -> マチス:马志士
A39: BADGE increases | C39: ユーの ポケモン スピード アップ！ | E39: You的宝可梦
A40: #MON's speed. | E40: 就会speed up！
C41: ミーに かった あかし ネー！
A42: Consider it proof | C42: たいせつ する グッド！ | E42: 这是战胜me的证明！
A43: that you defeated | E43: You要好好珍惜！
A45: me. You wear it
A46: proudly, hear?
A49: |---英文---------+ | C49: |---日文-------------------------+ | E49: |---翻译--------------+----------+ | H49: |---提词---------+ | I49: |---注释---------+ | J49: msg_matisu_05_t06r0701
A50: SURGE: Hey, kid! | C50: マチス『ヘイ！ ユー！ | E50: 马志士：Hey，you！ | H50: =_xlfn.TEXTJOIN(":",TRUE,训!C35,训!D35) -> マチス:马志士
A51: Still slugging and | C51: がんばって ますかー？ | E51: 还在继续努力吧？
A52: chugging away?
C53: ミーと ポケモンも | E53: Me和宝可梦们
A54: My #MON and I | C54: がんばって マース！ | E54: 也在继续努力！
A55: are still at it!
A58: |---英文---------+ | C58: |---日文-------------------------+ | E58: |---翻译--------------+----------+ | H58: |---提词---------+ | I58: |---注释---------+ | J58: msg_gentle03_01_t06r0701
A59: You're here to | C59: マチス しょうさを | E59: 你来这里是想要 | H59: =_xlfn.TEXTJOIN(":",TRUE,训!C35,训!D35) -> マチス:马志士
A60: defeat LT.SURGE? | C60: たおしに きたのか！ | E60: 打败马志士少校吗！
C61: そうは させないっ！ | E61: 别想得逞！
A62: Not if I can help
A63: it!
A66: |---英文---------+ | C66: |---日文-------------------------+ | E66: |---翻译--------------+----------+ | H66: |---提词---------+ | I66: |---注释---------+ | J66: msg_gentle03_02_t06r0701
A67: Sorry I failed | C67: もうしわけ ありません！ | E67: 非常抱歉！
A68: you, LT.SURGE, | C68: マチス しょうさ！ | E68: 马志士少校！ | H68: =_xlfn.TEXTJOIN(":",TRUE,训!C35,训!D35) -> マチス:马志士
A69: sir!
A72: |---英文---------+ | C72: |---日文-------------------------+ | E72: |---翻译--------------+----------+ | H72: |---提词---------+ | I72: |---注释---------+ | J72: msg_gentle03_03_t06r0701
A73: When I was still | C73: ぐんたいに いた ころだ…… | E73: 以前在部队的时候……
A74: in the army, LT. | C74: わたしは マチス しょうさに | E74: 我曾经被马志士少校 | H74: =_xlfn.TEXTJOIN(":",TRUE,训!C35,训!D35) -> マチス:马志士
C75: いのちを すくわれた……！ | E75: 救过一命……！
A76: SURGE saved my
A77: life.
A80: |---英文---------+ | C80: |---日文-------------------------+ | E80: |---翻译--------------+----------+ | H80: |---提词---------+ | I80: |---注释---------+ | J80: msg_guiter02_01_t06r0701
A81: LT.SURGE recog- | C81: でんき つかいの うでを | E81: 我使用电属性的技术
A82: nized my potential | C82: マチスさんに みとめられた！ | E82: 可是得到马志士认可的！ | H82: =_xlfn.TEXTJOIN(":",TRUE,训!C35,训!D35) -> マチス:马志士
C83: オレに かてるかな！？ | E83: 你赢得了我吗！？
A84: with electric
A85: #MON.
A87: Think you can beat
A88: me?
A91: |---英文---------+ | C91: |---日文-------------------------+ | E91: |---翻译--------------+----------+ | H91: |---提词---------+ | I91: |---注释---------+ | J91: msg_guiter02_02_t06r0701
A92: Ooh, how shocking! | C92: ひゅー！ しびれた！ | E92: 咻——！麻掉了！
A95: |---英文---------+ | C95: |---日文-------------------------+ | E95: |---翻译--------------+----------+ | H95: |---提词---------+ | I95: |---注释---------+ | J95: msg_guiter02_03_t06r0701
A96: If the GYM's traps | C96: ジムの しかけが うごいてれば | E96: 如果道馆的机关还在，
A97: were working, you | C97: おまえなんか たおせたのに……！ | E97: 我肯定能赢你……！
A99: would have been
A100: toast…
A103: |---英文---------+ | C103: |---日文-------------------------+ | E103: |---翻译--------------+----------+ | H103: |---提词---------+ | I103: |---注释---------+ | J103: msg_gypsy03_01_t06r0701
A104: I'm going to take | C104: おまえは オレが たおす！ | E104: 由我来打败你！
A105: you down! Prepare | C105: かくごしろっ！ | E105: 做好觉悟吧！
A106: to be shocked!
A109: |---英文---------+ | C109: |---日文-------------------------+ | E109: |---翻译--------------+----------+ | H109: |---提词---------+ | I109: |---注释---------+ | J109: msg_gypsy03_02_t06r0701
A110: Gwaaah! | C110: ぐはあっ！ | E110: 呜哇！
A111: I was overpowered… | C111: つよいっ！ | E111: 好强！
A114: |---英文---------+ | C114: |---日文-------------------------+ | E114: |---翻译--------------+----------+ | H114: |---提词---------+ | I114: |---注释---------+ | J114: msg_gypsy03_03_t06r0701
A115: Don't get too com- | C115: オレに かったからって | E115: 你只是赢了我而已，
A116: fortable about | C116: あんしん するなよ…… | E116: 别掉以轻心啊……
C117: マチス しょうさは つよいぜ…… | E117: 马志士少校很强的…… | H117: =_xlfn.TEXTJOIN(":",TRUE,训!C35,训!D35) -> マチス:马志士
A118: beating me…
A119: LT.SURGE is tough.
A122: |---英文---------+ | C122: |---日文-------------------------+ | E122: |---翻译--------------+----------+ | H122: |---提词---------+ | I122: |---注释---------+ | J122: msg_danpei_01_t06r0701
A123: Yo! CHAMP in | C123: おーす！ | E123: 嗨～！
A124: making! | C124: みらいの チャンピオン！ | E124: 未来的冠军！ | H124: =_xlfn.TEXTJOIN(":",TRUE,类!C17,类!D17) -> チャンピオン:冠军
C125: あんた ラッキーだよ！ | E125: 你很走运！ | H125: =_xlfn.TEXTJOIN(":",TRUE,宝!C114,宝!D114) -> ラッキー:吉利蛋
A126: You lucked out
A127: this time. | C127: いつも マチスは ようじんぶかく | E127: 平时马志士都会 | H127: =_xlfn.TEXTJOIN(":",TRUE,训!C35,训!D35) -> マチス:马志士
C128: トラップを しかけてるけど | E128: 小心翼翼地设置陷阱，
A129: LT.SURGE is very | C129: いまは さいわい こしょうちゅう！ | E129: 但现在正好坏掉了！
A130: cautious. He has
C131: こころ おきなく | E131: 尽管放心，
A132: traps set all over | C132: マチスと たたかってくれ！ | E132: 好好和马志士对战吧！ | H132: =_xlfn.TEXTJOIN(":",TRUE,训!C35,训!D35) -> マチス:马志士
A133: the GYM.
A135: But--he-heh--the
A136: traps aren't
...

Sheet 文7
A1: |---英文---------+ | C1: |---日文-------------------------+ | E1: |---翻译--------------+----------+ | H1: |---提词---------+ | I1: |---注释---------+ | J1: msg_manb_01_t24r0201
A2: I, I'm in shock! | C2: な なんてことだ…… | E2: 这、这算什么啊……
A4: A guy about your | C4: きみと おなじくらいの としごろで | E4: 有个和你年纪差不多、
A5: age with piercing | C5: めつきが するどくて | E5: 目光凶狠、
C6: かみのけ ながくて | E6: 长发飘飘、
A7: eyes and long hair | C7: なんだか こわそうな しょうねんに | E7: 样子有些可怕的少年
A8: came in. | C8: だいじな ポケモンを とられたよ！ | E8: 把我宝贵的宝可梦抢走了！
A10: He scared me into | C10: てもとに １ぴき のこっているけど | E10: 我身边只剩1只了，
A11: giving him my | C11: また おそわれたら どうしよう…… | E11: 要是再次遇袭的话……
A12: prized #MON!
C13: きみ つよそうだな | E13: 你看起来挺强的啊。
A14: I still have one | C14: しばらく ポケモン あずかってよ！ | E14: 暂时帮我保管宝可梦吧！
A15: left, but what if
A16: he comes back?
A18: You look strong.
A19: Could you look
A21: after my #MON
A22: for a while?
A25: |---英文---------+ | C25: |---日文-------------------------+ | E25: |---翻译--------------+----------+ | H25: |---提词---------+ | I25: |---注释---------+ | J25: msg_manb_02_t24r0201
A26: Oh, thank you! | C26: じゃ じゃあ たのむ！ | E26: 那就定了，拜托你了！
C27: だいじに してやってくれよ | E27: 一定要好好对它！
A28: Take good care of
A29: it, please!
A32: |---英文---------+ | C32: |---日文-------------------------+ | E32: |---翻译--------------+----------+ | H32: |---提词---------+ | I32: |---注释---------+ | J32: msg_manb_03_t24r0201
A33: <PLAYER> received a | C33: <PLAYER>は マニアから | E33: <PLAYER>从狂热迷
A34: #MON. | C34: ポケモンを あずかった！ | E34: 那里接管了宝可梦！
A37: |---英文---------+ | C37: |---日文-------------------------+ | E37: |---翻译--------------+----------+ | H37: |---提词---------+ | I37: |---注释---------+ | J37: msg_manb_05_t24r0201
A38: Your #MON party | C38: ポケモン いっぱいだよ | E38: 你的宝可梦太多了！
A39: is full.
A42: |---英文---------+ | C42: |---日文-------------------------+ | E42: |---翻译--------------+----------+ | H42: |---提词---------+ | I42: |---注释---------+ | J42: msg_manb_06_t24r0201
A43: Oh, no… What'll | C43: そ そんなあ | E43: 怎、怎么这样……
A44: I do if he comes | C44: また おそわれたら どうしよう | E44: 下次遇袭该怎么办啊？
A45: back?
A48: |---英文---------+ | C48: |---日文-------------------------+ | E48: |---翻译--------------+----------+ | H48: |---提词---------+ | I48: |---注释---------+ | J48: msg_manb_10_t24r0201
A49: Hi! How's my #- | C49: ぼくの ポケモン げんき？ | E49: 我的宝可梦还好吗？
A50: MON?
C51: もう おそわれそうに ないし | E51: 好像不会再遇袭了，
A52: I think I'm safe | C52: ポケモン かえしてほしいんだ | E52: 我希望你把宝可梦还给我。
A53: now, so may I have
A54: it back?
A57: |---英文---------+ | C57: |---日文-------------------------+ | E57: |---翻译--------------+----------+ | H57: |---提词---------+ | I57: |---注释---------+ | J57: msg_manb_11_t24r0201
A58: Thank you! | C58: ありがとう！ | E58: 感谢！
A61: |---英文---------+ | C61: |---日文-------------------------+ | E61: |---翻译--------------+----------+ | H61: |---提词---------+ | I61: |---注释---------+ | J61: msg_manb_12_t24r0201
A62: Hey, you don't | C62: ぼくの ポケモン いないじゃん | E62: 我的宝可梦不在这里啊。
A63: have my #MON
A64: with you.
A67: |---英文---------+ | C67: |---日文-------------------------+ | E67: |---翻译--------------+----------+ | H67: |---提词---------+ | I67: |---注释---------+ | J67: msg_manb_13_t24r0201
A68: My #MON has | C68: ぼくの ポケモン | E68: 我的宝可梦
A69: come to like you. | C69: きみに なついちゃってるな | E69: 和你非常亲近呢。
A71: All right, you | C71: わかった！ ポケモンは ゆずる！ | E71: 好吧！宝可梦就给你了！
A72: should keep it. | C72: そのかわり だいじに してくれよ | E72: 不过你一定要好好对它哦。
A74: But promise to
A75: be good to it!
A78: |---英文---------+ | C78: |---日文-------------------------+ | E78: |---翻译--------------+----------+ | H78: |---提词---------+ | I78: |---注释---------+ | J78: msg_manb_14_t24r0201
A79: Oh, no, no… That's | C79: そ そんなあ | E79: 怎、怎么这样……
A80: the same as being | C80: だったら おそわれたのと おなじだ | E80: 这和遇袭有什么区别？
A81: robbed.
A84: |---英文---------+ | C84: |---日文-------------------------+ | E84: |---翻译--------------+----------+ | H84: |---提词---------+ | I84: |---注释---------+ | J84: msg_manb_15_t24r0201
A85: For #MON, hap- | C85: ポケモンにとって しあわせ なのは | E85: 对宝可梦而言， | H85: =_xlfn.TEXTJOIN(":",TRUE,招!C146,招!D146) -> あわ:泡沫
A86: piness is being | C86: だいじに してくれる ひとと | E86: 和珍爱自己的训练家同行
C87: いっしょに いること じゃないかな | E87: 是一件非常幸福的事情吧？
A88: with a person who
A89: treats them well.
A92: |---英文---------+ | C92: |---日文-------------------------+ | E92: |---翻译--------------+----------+ | H92: |---提词---------+ | I92: |---注释---------+ | J92: msg_manb_16_t24r0201
A93: If I take my #- | C93: ボクが その ポケモンを うけとると | E93: 我要是把宝可梦拿回来，
A94: MON back, what are | C94: キミは たたかえなく なっちゃうね！ | E94: 你用什么战斗啊？
A96: you going to use
A97: in battle?
A100: |---英文---------+ | C100: |---日文-------------------------+ | E100: |---翻译--------------+----------+ | H100: |---提词---------+ | I100: |---注释---------+ | J100: msg_leader06_01_t24r0301
A101: WAHAHAH! | C101: おっしゃ！ | E101: 不错！
C102: ここまで きたかーっ！ | E102: 你居然能到这里！
A103: So you've come | C103: いっとくが わしは つよいぞ！ | E103: 先说一句，我非常强！
A104: this far!
C105: きたえた ポケモンは | E105: 我锻炼出的宝可梦
A106: Let me tell you, | C106: いわを くだき | E106: 既能粉碎岩石，
A107: I'm tough! | C107: ホネをも こなみじん にする！ | E107: 也能让对手粉身碎骨！
A109: My #MON will | C109: ちょっと みておれ | E109: 你瞧好了！
A110: crush stones and
A111: shatter bones!
A113: Watch this!
A116: |---英文---------+ | C116: |---日文-------------------------+ | E116: |---翻译--------------+----------+ | H116: |---提词---------+ | I116: |---注释---------+ | J116: msg_leader06_09_t24r0301
A117: CHUCK: Urggh! | C117: シジマ『ううー | E117: 阿四：呜—— | H117: =_xlfn.TEXTJOIN(":",TRUE,训!C8,训!D8) -> シジマ:阿四
A118: … | C118: …… …… …… | E118: <……> <……> <……>
A120: Oooarrgh! | C120: どりゃああ！！ | E120: 喝呀——！！
A123: |---英文---------+ | C123: |---日文-------------------------+ | E123: |---翻译--------------+----------+ | H123: |---提词---------+ | I123: |---注释---------+ | J123: msg_leader06_10_t24r0301
A124: There! Scared now, | C124: どうだ！ おじけづいたろ！ | E124: 怎么样！怕了吧！
A125: are you?
C126: なに ポケモンとは かんけい ない？ | E126: 什么？你问宝可梦在哪？
A127: What? | C127: それも そうだ！ | E127: 我给忘了！
A128: It has nothing to | C128: では しょうぶと いくかあ！ | E128: 那就开始对战吧！
A130: do with #MON?
A131: That's true!
A133: Come on. We shall
A134: do battle!
A137: |---英文---------+ | C137: |---日文-------------------------+ | E137: |---翻译--------------+----------+ | H137: |---提词---------+ | I137: |---注释---------+ | J137: msg_leader06_02_t24r0301
A138: Wha? Huh? | C138: おりょ？ | E138: 哎哟？
A139: I lost? | C139: わしが まけるとは…… | E139: 我怎么输了……
A141: How about that! | C141: こりゃ まいった！ | E141: 这可真难为情啊！
A142: You're worthy of | C142: よーしっ！ この ショックバッジは | E142: 很好！
A143: STORMBADGE! | C143: おまえに ふさわしい！ | E143: 你配得上打击徽章！
...

Sheet 文8
A1: |---英文---------+ | C1: |---日文-------------------------+ | E1: |---翻译--------------+----------+ | H1: |---提词---------+ | I1: |---注释---------+ | J1: msg_leader08_01_t30r0101
A2: I am CLAIR. | C2: わたしは イブキ！ | E2: 我叫小椿！ | H2: =_xlfn.TEXTJOIN(":",TRUE,训!C9,训!D9) -> イブキ:小椿
A4: The world's best | C4: せかいで いちばんの | E4: 是世界第一
A5: dragon master. | C5: ドラゴンつかい よ | E5: 龙使者。
A7: I can hold my own | C7: じつりょくも ポケモンリーグ | E7: 即使是面对
A8: against even the | C8: してんのうに だって | E8: 联盟里的四天王， | H8: =_xlfn.TEXTJOIN(":",TRUE,类!C12,类!D12) -> してんのう:四天王
C9: まけてなんか ないわよ！ | E9: 凭我的实力也不会输！
A10: #MON LEAGUE's | C10: どう それでも たたかうの？ | E10: 即便如此，你还要挑战吗？
A11: ELITE FOUR.
C12: …… そう わかったわ | E12: ……好吧，我明白了。
A13: Do you still want | C13: じゃ はじめましょう！ | E13: 那就开始吧！
A14: to take me on?
C15: わたしも ジムリーダーとして | E15: 作为道馆馆主， | H15: =_xlfn.TEXTJOIN(":",TRUE,类!C2,类!D2) -> ジムリーダー:道馆馆主
A16: …Fine. | C16: ぜんりょくで あいて してあげる！ | E16: 我会全力应战的！
A17: Let's do it!
A19: As a GYM LEADER,
A20: I will use my full
A22: power against any
A23: opponent!
A26: |---英文---------+ | C26: |---日文-------------------------+ | E26: |---翻译--------------+----------+ | H26: |---提词---------+ | I26: |---注释---------+ | J26: msg_leader08_02_t30r0101
A27: I lost? | C27: この わたしが まけるなんて…… | E27: 我居然输了……
A29: I don't believe | C29: しんじられない | E29: 不敢相信！
A30: it. There must be | C30: なにかの まちがいよ…… | E30: 一定是哪里弄错了……
A31: some mistake…
A34: |---英文---------+ | C34: |---日文-------------------------+ | E34: |---翻译--------------+----------+ | H34: |---提词---------+ | I34: |---注释---------+ | J34: msg_leader08_03_t30r0101
A35: I won't admit | C35: わたしは みとめないわ | E35: 我不承认。
A36: this.
C37: まけて いうのも なんだけど | E37: 虽然输家说这种话不合适，
A38: I may have lost, | C38: あなたの かんがえかた じゃ | E38: 可是以你现在的心态
A39: but you're still | C39: ポケモンリーグに ちょうせん なんて | E39: 根本就没有资格
C40: むり よ | E40: 挑战宝可梦联盟。
A41: not ready for the
A42: #MON LEAGUE. | C42: …… そうだわ！ | E42: ……对了！
A44: I know. You should | C44: この ポケモンジムの うらに | E44: 在这个宝可梦道馆后面
A45: take the dragon | C45: りゅうのあな とよばれる | E45: 有一个洞穴， | H45: =_xlfn.TEXTJOIN(":",TRUE,城!C25,城!D25) -> りゅうのあな:龙穴
A46: user challenge. | C46: ばしょが あるの | E46: 人们称之为龙穴。
A48: Behind this GYM is | C48: ちゅうおうに ほこらが あるから | E48: 龙穴中心处有个祠堂，
A49: a place called | C49: そこへ いきなさい | E49: 你去那里吧。
A50: DRAGON'S DEN.
C51: もし そこで あなたが | E51: 如果你能在那里
A52: There is a small | C52: あまい かんがえを かえられたなら | E52: 改掉现在天真的想法，
A53: shrine at its
C54: ジムバッジを わたすに ふさわしい | E54: 那我就承认你是
A55: center. | C55: トレーナーとして みとめてあげるわ！ | E55: 配得上道馆徽章的训练家！
A56: Go there.
A58: If you can prove
A59: that you've lost
A61: your lazy ideals,
A62: I will recognize
A64: you as a trainer
A65: worthy of a GYM
A66: BADGE!
A69: |---英文---------+ | C69: |---日文-------------------------+ | E69: |---翻译--------------+----------+ | H69: |---提词---------+ | I69: |---注释---------+ | J69: msg_leader08_04_t30r0101
A70: What's the matter? | C70: どうしたの？ | E70: 怎么？
A72: Is it too much to | C72: やっぱり あなたじゃ むり かしら？ | E72: 你果然办不到吧？
A73: expect of you?
A76: |---英文---------+ | C76: |---日文-------------------------+ | E76: |---翻译--------------+----------+ | H76: |---提词---------+ | I76: |---注释---------+ | J76: msg_leader08_08_t30r0101
A77: You've kept me | C77: おそいわよ！ | E77: 太慢了！
A78: waiting! | C78: さっさと うけとりなさい！ | E78: 赶紧拿完走人！
A80: Here! Take this!
A83: |---英文---------+ | C83: |---日文-------------------------+ | E83: |---翻译--------------+----------+ | H83: |---提词---------+ | I83: |---注释---------+ | J83: msg_leader08_09_t30r0101
A84: <PLAYER> received | C84: <PLAYER>は イブキから | E84: <PLAYER>从小椿那里 | H84: =_xlfn.TEXTJOIN(":",TRUE,训!C9,训!D9) -> イブキ:小椿
A85: TM24. | C85: わざマシン２４を もらった！ | E85: 得到了招式学习器24！ | H85: =_xlfn.TEXTJOIN(":",TRUE,道!C216,道!D216) -> わざマシン２４:招式学习器24
A88: |---英文---------+ | C88: |---日文-------------------------+ | E88: |---翻译--------------+----------+ | H88: |---提词---------+ | I88: |---注释---------+ | J88: msg_leader08_10_t30r0101
A89: That contains | C89: なかに はいっているのは | E89: 这里面是——
A90: DRAGONBREATH. | C90: りゅうのいぶき | E90: 龙息。 | H90: =_xlfn.TEXTJOIN(":",TRUE,招!C226,招!D226) -> りゅうのいぶき:龙息
A92: No, it doesn't | C92: …… べつに シャレじゃ ないわよ | E92: ……不是那个最辣辣椒！
A93: have anything to | C93: いらないなら むりして | E93: 如果你不需要，
A94: do with my breath. | C94: もっていかなくても いいのよ | E94: 我也不会强迫你的。
A96: If you don't want
A97: it, you don't have
A98: to take it.
A101: |---英文---------+ | C101: |---日文-------------------------+ | E101: |---翻译--------------+----------+ | H101: |---提词---------+ | I101: |---注释---------+ | J101: msg_leader08_11_t30r0101
A102: What is this? You | C102: なによ！ | E102: 真是的！
A103: don't have room? | C103: せいり されてないじゃないの！ | E103: 你应该好好整理才对啊！
A106: |---英文---------+ | C106: |---日文-------------------------+ | E106: |---翻译--------------+----------+ | H106: |---提词---------+ | I106: |---注释---------+ | J106: msg_leader08_12_t30r0101
A107: What's the matter? | C107: どうしたの？ | E107: 你愣着干什么？
C108: ポケモンリーグに むかうんでしょう？ | E108: 该去宝可梦联盟了吧？
A109: Aren't you headed
A110: to the #MON | C110: ばしょは しってるの？ | E110: 知道该往哪走吗？
A111: LEAGUE?
C112: ここからだと そうね… | E112: 如果从这里出发……
A113: Don't you know | C113: まずは ワカバタウンに いくといいわ | E113: 那就先去若叶镇吧！ | H113: =_xlfn.TEXTJOIN(":",TRUE,城!C2,城!D2) -> ワカバタウン:若叶镇
A114: where it is?
C115: そこから なみのりで | E115: 然后就用冲浪 | H115: =_xlfn.TEXTJOIN(":",TRUE,招!C58,招!D58) -> なみのり:冲浪
A116: From here, go to | C116: ずっと ひがしに すすんで いけば | E116: 一直朝着东方前进，
A117: NEW BARK TOWN. | C117: ポケモンリーグに とうちゃく するわ | E117: 就能到达宝可梦联盟了。
C118: でも きびしい みちのりに なるわよ | E118: 但是，这段路可不平坦。
A119: Then SURF east.
A120: The route there is | C120: それと… ポケモンリーグでも | E120: 还有啊……
A121: very tough. | C121: まけることは ゆるさないからね！ | E121: 我不许你输给宝可梦联盟！
A123: Don't you dare | C123: そうでないと まけた わたしが | E123: 要不然，
A124: lose at the #- | C124: みじめに なるでしょ！ | E124: 我这个手下败将情何以堪！
A125: MON LEAGUE!
C126: …がんばりなさい | E126: ……加油啊！
A127: If you do, I'll
A128: feel even worse
A130: about having lost
A131: to you!
A133: Give it every-
...

Sheet 文9
A1: |---英文---------+ | C1: |---日文-------------------------+ | E1: |---翻译--------------+----------+ | H1: |---提词---------+ | I1: |---注释---------+ | J1: msg_middlew01_01_t25r1201
A2: Oh my, your pack | C2: あらあら！ あなた リュックに | E2: 哎呀哎呀！你的背包里 | H2: =_xlfn.TEXTJOIN(":",TRUE,其!C59,其!D59) -> リュック:背包
A3: looks so heavy! | C3: たくさん つめこんで おもそうねえー | E3: 装了许多东西对吧？
A5: Oh! Do you happen | C5: そうだわ！ もしかして あなた | E5: 对了！你有没有
A6: to have something | C6: ブイブイメール っていうの | E6: 叫做伊布信件的道具？ | H6: =_xlfn.TEXTJOIN(":",TRUE,道!C186,道!D186) -> ブイブイメール:伊布信件
A7: named EON MAIL? | C7: もってないかしら？ | E7: 我的女儿说她很想要，
C8: むすめが ほしいって いうのよ | E8: 你能分我一个吗？
A9: My daughter is | C9: ひとつくらい わけて くれるでしょ？
A10: after one.
A12: You can part with
A13: one, can't you?
A16: |---英文---------+ | C16: |---日文-------------------------+ | E16: |---翻译--------------+----------+ | H16: |---提词---------+ | I16: |---注释---------+ | J16: msg_middlew01_02_t25r1201
A17: Give away an EON | C17: ブイブイメールを あげますか？ | E17: 要给出伊布信件吗？ | H17: =_xlfn.TEXTJOIN(":",TRUE,道!C186,道!D186) -> ブイブイメール:伊布信件
A18: MAIL?
A21: |---英文---------+ | C21: |---日文-------------------------+ | E21: |---翻译--------------+----------+ | H21: |---提词---------+ | I21: |---注释---------+ | J21: msg_middlew01_03_t25r1201
A22: Oh, that's great! | C22: ああ たすかった！ | E22: 啊啊，帮大忙了！
A23: Thank you, honey! | C23: あなた ありがとうね | E23: 谢谢你啊。
A25: Here, this is for | C25: もらう ばかりじゃ わるいから | E25: 白拿你的东西也不太好，
A26: you in return! | C26: おれいに これ あげるわよ | E26: 这个就当是回礼了。
A29: |---英文---------+ | C29: |---日文-------------------------+ | E29: |---翻译--------------+----------+ | H29: |---提词---------+ | I29: |---注释---------+ | J29: msg_middlew01_04_t25r1201
A30: My daughter will | C30: むすめも よろこぶわ！ | E30: 我女儿一定会很高兴的！
A31: be delighted!
A34: |---英文---------+ | C34: |---日文-------------------------+ | E34: |---翻译--------------+----------+ | H34: |---提词---------+ | I34: |---注释---------+ | J34: msg_middlew01_05_t25r1201
A35: Oh? You don't have | C35: あら ないの？ ざんねんねえ… | E35: 哎呀，没有吗？真可惜……
A36: one? Too bad.
A39: |---英文---------+ | C39: |---日文-------------------------+ | E39: |---翻译--------------+----------+ | H39: |---提词---------+ | I39: |---注释---------+ | J39: msg_middlew01_06_t25r1201
A40: Oh… Well, another | C40: あら… | E40: 哎呀……
A41: time, then. | C41: じゃあ また こんど ちょうだいね | E41: 那还是下次再说吧。
A44: |---英文---------+ | C44: |---日文-------------------------+ | E44: |---翻译--------------+----------+ | H44: |---提词---------+ | I44: |---注释---------+ | J44: msg_middlew01_07_t25r1201
A45: <PLAYER> gave away | C45: <PLAYER>は | E45: <PLAYER>交出了
A46: the EON MAIL. | C46: ブイブイメールを わたした！ | E46: 伊布信件！ | H46: =_xlfn.TEXTJOIN(":",TRUE,道!C186,道!D186) -> ブイブイメール:伊布信件
A49: |---英文---------+ | C49: |---日文-------------------------+ | E49: |---翻译--------------+----------+ | H49: |---提词---------+ | I49: |---注释---------+ | J49: msg_manb01_01_r40r0201_nm
A50: Are you going to | C50: きみも バトルタワーに いくの？ | E50: 你也要去对战塔吗？ | H50: =_xlfn.TEXTJOIN(":",TRUE,城!C102,城!D102) -> バトルタワー:对战塔
A51: the BATTLE TOWER?
C52: じつは ここだけの はなしだけど | E52: 如果有人赢了很多次，
A53: This is a secret, | C53: たくさん かちぬいた ひとには | E53: 好像会获得礼物呢。
A54: but if you win a | C54: なにか プレゼントが あるらしいよ！ | E54: 我只告诉你一个人哦！ | H54: =_xlfn.TEXTJOIN(":",TRUE,招!C218,招!D218) -> プレゼント:礼物
A56: whole lot, you can
A57: win special gifts.
A60: |---英文---------+ | C60: |---日文-------------------------+ | E60: |---翻译--------------+----------+ | H60: |---提词---------+ | I60: |---注释---------+ | J60: msg_girl_00_t07_nm
A61: Looking at the | C61: …… どうろの もようを | E61: ……我一边走，
A62: ground while I was | C62: じっと みながら あるいてたら | E62: 一边看路上的花纹，
C63: めが チカチカ しちゃった！ | E63: 眼睛都看花了！ | H63: =_xlfn.TEXTJOIN(":",TRUE,训!C101,训!D101) -> チカ:千佳
A64: walking made me
A65: dizzy.
A68: |---英文---------+ | C68: |---日文-------------------------+ | E68: |---翻译--------------+----------+ | H68: |---提词---------+ | I68: |---注释---------+ | J68: msg_tanpan05_03_r34_nm
A69: I'm going to train | C69: れんしゅうで ダメなら とっくんだ！ | E69: 如果一般的练习还不够，
A70: even harder. | C70: なんたって おれの もくひょうは | E70: 那就要进行特训！
C71: ジムリーダー だからな！ | E71: 毕竟我的梦想是道馆馆主！ | H71: =_xlfn.TEXTJOIN(":",TRUE,类!C2,类!D2) -> ジムリーダー:道馆馆主
A72: After all, I'm
A73: trying to become
A74: a GYM LEADER.
A77: |---英文---------+ | C77: |---日文-------------------------+ | E77: |---翻译--------------+----------+ | H77: |---提词---------+ | I77: |---注释---------+ | J77: msg_girl_01_r36_nm
A78: An odd tree is | C78: おかしな きが はえちゃって | E78: 路上长了棵奇怪的树，
A79: blocking the way | C79: コガネに おかいものに いけないの | E79: 不能去满金市买东西了！
A80: to GOLDENROD CITY. | C80: だれか なんとか してほしいわ | E80: 希望能有人解决这个问题。
A82: It's preventing
A83: me from shopping.
A85: Something should
A86: be done about it.
A89: |---英文---------+ | C89: |---日文-------------------------+ | E89: |---翻译--------------+----------+ | H89: |---提词---------+ | I89: |---注释---------+ | J89: msg_fishing_00_t23r0101_nm
A90: BILL's PC can | C90: マサキのパソコン つかうと | E90: 使用正辉的电脑， | H90: =_xlfn.TEXTJOIN(":",TRUE,其!C30,其!D30) -> マサキ:正辉
A91: store up to 20 | C91: １つの ボックスに ３０ぴきまで | E91: 1个盒子最多可以
A92: #MON per BOX. | C92: ポケモン あずけられぞ！ | E92: 寄放20只宝可梦哦。
A95: |---英文---------+ | C95: |---日文-------------------------+ | E95: |---翻译--------------+----------+ | H95: |---提词---------+ | I95: |---注释---------+ | J95: msg_mobile_battleroom_09_nm
A96: BATTLE TOWER is a | C96: バトルタワーは ポケモンたいせんを | E96: 对战塔是用来进行 | H96: =_xlfn.TEXTJOIN(":",TRUE,城!C102,城!D102) -> バトルタワー:对战塔
A97: facility made for | C97: おこなうための しせつです | E97: 宝可梦对战的设施。
A98: #MON battles.
C99: ぜんこくから たくさんの ポケモン | E99: 来自全国的许多宝可梦
A100: Countless #MON | C100: トレーナーたちが あつまり | E100: 训练家都聚集于此。
A101: trainers gather
C102: バトルルーム という たいせんように | E102: 他们将会在专门用于
A103: from all over to | C103: ようい された へやで たたかいます | E103: 对战的对战房间展开战斗。
A104: hold battles in
C105: バトルルームは バトルタワーないに | E105: 对战塔内准备了很多 | H105: =_xlfn.TEXTJOIN(":",TRUE,城!C102,城!D102) -> バトルタワー:对战塔
A106: specially designed | C106: たくさん ようい されています | E106: 这样的对战房间。
A107: BATTLE ROOMS.
C108: それぞれ バトルルームには | E108: 每个对战房间里
A109: There are many | C109: ７にんの トレーナーが いて | E109: 都有7位训练家，
A110: BATTLE ROOMS in
A111: the BATTLE TOWER. | C111: その７にんを すべて たおすと | E111: 完全战胜7位训练家之后，
C112: すてきな しょうひんを さしあげます | E112: 我们将会送上精美奖品。
A113: Each ROOM holds
A114: seven trainers. | C114: また とちゅうで やめたいときは | E114: 另外，请注意：
C115: ちゃんと レポートを かかないと | E115: 如果挑战中途想要退出，
A116: Beat them all, and | C116: つづけて ちょうせんが できないので | E116: 必须先写入记录，
A117: win a prize. | C117: きをつけて くださいね | E117: 否则将会无法继续挑战。
A119: To interrupt a | C119: | | E119: |
A120: session, you must
A122: SAVE. If not, you
A123: won't be able to
A125: resume your ROOM
A126: challenge.
A128: |
A131: |---英文---------+ | C131: |---日文-------------------------+ | E131: |---翻译--------------+----------+ | H131: |---提词---------+ | I131: |---注释---------+ | J131: msg_mobile_battleroom_15_nm
A132: Thanks for | C132: おつかれさまでした！ | E132: 辛苦您了！
A133: visiting!
A136: |---英文---------+ | C136: |---日文-------------------------+ | E136: |---翻译--------------+----------+ | H136: |---提词---------+ | I136: |---注释---------+ | J136: msg_mobile_battleroom_16_nm
A137: Congratulations! | C137: おめでとう ございます！ | E137: 恭喜你！
C138: リーダーに かたれましたね！ | E138: 顺利战胜了关主！
...

Sheet 文10
A1: |---英文---------+ | C1: |---日文-------------------------+ | E1: |---翻译--------------+----------+ | H1: |---提词---------+ | I1: |---注释---------+ | J1: msg1_003_Play2 | K1: GS
A2: Trade 【0】 | C2: 【0】 と 【1】 を | E2: 将用【0】 | J2: text_ram wBufferTrademonNickname
A3: for 【1】? | C3: こうかんします | E3: 交换【1】？ | J3: text_ram wStringBuffer1
A5: |---英文---------+ | C5: |---日文-------------------------+ | E5: |---翻译--------------+----------+ | H5: |---提词---------+ | I5: |---注释---------+ | J5: honou_m01 | K5: GS
A6: <TARGET> | C6: <TARGET>は うずの なかに | E6: <TARGET> | I6: 水火漩涡都使用这个文本
A7: was trapped! | C7: とじこめられた！ | E7: 被困在了旋涡之中！
A9: |---英文---------+ | C9: |---日文-------------------------+ | E9: |---翻译--------------+----------+ | H9: |---提词---------+ | I9: |---注释---------+ | J9: msg_telboy_01_common | K9: GS
A10: Wow! You're pretty | C10: ところで つよいね きみ！ | E10: 说起来，你可真强啊！ | I10: 그건 그렇고 강하구나 너!
A11: tough. | C11: よかったら でんわばんごう | E11: 那么你愿不愿意 | I11: 괜찮다면 전화번호
C12: おしえて くれない？ | E12: 把电话号码告诉我呢？ | I12: 가르쳐주지 않을래?
A13: Could I get your
A14: phone number? | C14: また しょうぶ したくなったら | E14: 我下次想和你对战的时候， | I14: 또 승부하고 싶어진다면
C15: でんわ するから | E15: 会给你打电话的。 | I15: 전화할 테니까
A16: I'll call you for
A17: a rematch.
A19: |---英文---------+ | C19: |---日文-------------------------+ | E19: |---翻译--------------+----------+ | H19: |---提词---------+ | I19: |---注释---------+ | J19: msg_telboy_02_common | K19: GS
A20: Register the phone | C20: でんわばんごう | E20: 要添加 | I20: 전화번호
A21: number? | C21: とうろく するかい？ | E21: 电话号码吗？ | I21: 등록하겠니？
A23: |---英文---------+ | C23: |---日文-------------------------+ | E23: |---翻译--------------+----------+ | H23: |---提词---------+ | I23: |---注释---------+ | J23: msg_telboy_04_common | K23: GS
A24: I'll call you if | C24: なにか あったら | E24: 有事情的时候， | I24: 무슨 일 있다면
A25: anything comes up. | C25: でんわ するからね | E25: 我会打电话给你的。 | I25: 전화할 테니까
A27: |---英文---------+ | C27: |---日文-------------------------+ | E27: |---翻译--------------+----------+ | H27: |---提词---------+ | I27: |---注释---------+ | J27: msg_telboy_05_common | K27: GS
A28: Oh, OK… | C28: ま いいか… | E28: 啊，那算了…… | I28: 뭐 좋을대로…
A29: Just talk to me if | C29: とうろく したく なったら | E29: 等你想添加号码的时候， | I29: 등록하고싶어지면
C30: また はなしかけてよ！ | E30: 就来找我搭话吧！ | I30: 다시 말 해줘！
A31: you want to get my
A32: phone number.
A34: |---英文---------+ | C34: |---日文-------------------------+ | E34: |---翻译--------------+----------+ | H34: |---提词---------+ | I34: |---注释---------+ | J34: msg_telboy_06_common | K34: GS
A35: Your phone doesn't | C35: って きみの でんわ | E35: 喂，你的电话存满了， | I35: 어라 네 전화 메모리가
A36: have enough memory | C36: いっぱいで とうろく できないな！ | E36: 无法再添加号码了！ | I36: 가득차서 등록되지 않네！
A37: for more numbers.
A39: |---英文---------+ | C39: |---日文-------------------------+ | E39: |---翻译--------------+----------+ | H39: |---提词---------+ | I39: |---注释---------+ | J39: msg_telboy_07_common | K39: GS
A40: I was waiting for | C40: まってたよ！ | E40: 等着你呢！ | I40: 기다렸다구
A41: you. Let's battle! | C41: それじゃあ しょうぶ しようか！ | E41: 那么，来和我对战吧！ | I41: 그러면 승부하자！
A43: |---英文---------+ | C43: |---日文-------------------------+ | E43: |---翻译--------------+----------+ | H43: |---提词---------+ | I43: |---注释---------+ | J43: msg_telgirl_01_common | K43: GS
A44: Wow, you're good | C44: ところで ポケモン つよいわね！ | E44: 说起来，你的宝可梦真强！ | I44: 그건그렇고 포켓몬이 아주 강하네！
A45: at battling. | C45: よかったら | E45: 那么你愿意 | I45: 괜찮다면
C46: でんわばんごう おしえて？ | E46: 把电话号码告诉我吗？ | I46: 전화번호 가르쳐줄래？
A47: Want to give me
A48: your phone number? | C48: また しょうぶ したくなったら | E48: 我下次想和你对战的时候， | I48: 또 승부하고싶어지면
C49: でんわ するから | E49: 会给你打电话的。 | I49: 전화할께
A50: I'll phone you for
A51: another battle.
A53: |---英文---------+ | C53: |---日文-------------------------+ | E53: |---翻译--------------+----------+ | H53: |---提词---------+ | I53: |---注释---------+ | J53: msg_telgirl_02_common | K53: GS
A54: Register the phone | C54: でんわばんごう | E54: 要添加 | I54: 전화번호
A55: number? | C55: とうろく するの？ | E55: 电话号码吗？ | I55: 등록 하겠니？
A57: |---英文---------+ | C57: |---日文-------------------------+ | E57: |---翻译--------------+----------+ | H57: |---提词---------+ | I57: |---注释---------+ | J57: msg_telgirl_04_common | K57: GS
A58: I'll call you if | C58: なにか あったら | E58: 有事情的时候， | I58: 무슨 일 생긴다면
A59: something's up. | C59: でんわ するね！ | E59: 我会给你打电话！ | I59: 전화할께！
A61: |---英文---------+ | C61: |---日文-------------------------+ | E61: |---翻译--------------+----------+ | H61: |---提词---------+ | I61: |---注释---------+ | J61: msg_telgirl_05_common | K61: GS
A62: Oh, fine then… | C62: そう？ とうろく したくなったら | E62: 这样吗？等你想添加的时候 | I62: 그러니？ 등록하고싶어지면
A63: If you want to get | C63: また はなしかけてね | E63: 就来找我搭话哦！ | I63: 다시 말해 줘
A65: my phone number,
A66: just tell me.
A68: |---英文---------+ | C68: |---日文-------------------------+ | E68: |---翻译--------------+----------+ | H68: |---提词---------+ | I68: |---注释---------+ | J68: msg_telgirl_06_common | K68: GS
A69: Your phone doesn't | C69: って きみの でんわ | E69: 喂，你的电话存满了， | I69: 어라 네 전화 메모리가
A70: have enough memory | C70: いっぱいで とうろく できないわ！ | E70: 无法再添加号码啦！ | I70: 가득차서 등록되지 않네！
A71: for more numbers.
A73: |---英文---------+ | C73: |---日文-------------------------+ | E73: |---翻译--------------+----------+ | H73: |---提词---------+ | I73: |---注释---------+ | J73: msg_telgirl_07_common | K73: GS
A74: I waited for you. | C74: まってたわ | E74: 我在等你哦！ | I74: 기다렸다구
A75: Let's battle! | C75: それじゃあ しょうぶ しましょう！ | E75: 那么，请和我对战吧！ | I75: 그러면 승부하자！
A77: |---英文---------+ | C77: |---日文-------------------------+ | E77: |---翻译--------------+----------+ | H77: |---提词---------+ | I77: |---注释---------+ | J77: msg_bouzu_00_d17r0101 | K77: GS
A78: I'm trying to un- | C78: わたしは ここに まいおりるという | E78: 据说传说的宝可梦 | I78: 나는 이곳에 내려온다고 하는
A79: cover the secret | C79: でんせつの ポケモンの | E79: 会在这里降临， | I79: 전설의 포켓몬의
C80: ひみつを さぐっているのです | E80: 而我一直在追寻它的秘密。 | I80: 비밀을 밝혀내려 하고 있소
A81: of the legendary
A82: #MON that is | C82: にしがわの とうが やけてから | E82: 西侧的塔烧毁之后， | I82: 서쪽의 탑이 불에 타버린 이후
A83: said to land here. | C83: ここにいた ポケモンは | E83: 曾经待在这里的宝可梦 | I83: 여기에 있던 포켓몬은
C84: ずっと そらを とんでいるそうです | E84: 一直在天空中盘旋。 | I84: 계속 하늘을 날고 있다하오
A85: They say that the
A86: #MON has flown | C86: そこで かんがえました | E86: 按我的推测， | I86: 거기서 생각해보았소이다
C87: とんでいる ポケモンと | E87: 只要带着来自空中那只 | I87: 날고있는 포켓몬과
A88: continuously ever | C88: おなじ モノを もっていれば | E88: 宝可梦的某种物品 | I88: 같은 것을 가지고 있는 다면
A89: since the TOWER in | C89: さそわれて やってくる はず！ | E89: 应该就能把它被吸引过来！ | I89: 유인되어져 올 것이라는 것을！
A90: the West burned.
C91: その おなじ モノとは おそらく…… | E91: 如果没猜错，那个物品…… | I91: 그 같은 것 이란것은 아마도……
A92: So, I thought that
A93: if I had what the | C93: にじいろのはね！ | E93: 就是虹色之羽！ | I93: 무지개빛 날개！
A95: #MON has, it | C95: だが そんなもの | E95: 但是要去哪里 | I95: 그렇지만 그런 것이
A96: would be attracted | C96: どこに あるんでしょう？ | E96: 才能找到这种东西呢？ | I96: 어디에 있겠소이까？
A97: by that item.
A99: I think that item
A100: is probably…
A102: A RAINBOW WING!
A104: But, where would
A105: I find one?
A107: |---英文---------+ | C107: |---日文-------------------------+ | E107: |---翻译--------------+----------+ | H107: |---提词---------+ | I107: |---注释---------+ | J107: msg_fire02_01_d18r0101 | K107: GS
A108: Hey, I'm training | C108: こっそり れんしゅう してるのを | E108: 被你看到我在这里偷偷练习 | I108: 몰래 연습하고 있는 것을
A109: secretly here! | C109: みられたら はずかしいじゃねーか！ | E109: 太难为情啦——！ | I109: 보이게된다면 창피하잖아！
A111: Don't embarrass me
A112: by looking!
A114: |---英文---------+ | C114: |---日文-------------------------+ | E114: |---翻译--------------+----------+ | H114: |---提词---------+ | I114: |---注释---------+ | J114: msg_fire02_02_d18r0101 | K114: GS
A115: I burned down to | C115: もえつきた…… | E115: 燃烧殆尽了…… | I115: 불이 붙었다……
A116: white ashes… | C116: まっしろに なっちまったよ…… | E116: 只剩一片灰白…… | I116: 새하얗게 되어 버렸어……
A118: |---英文---------+ | C118: |---日文-------------------------+ | E118: |---翻译--------------+----------+ | H118: |---提词---------+ | I118: |---注释---------+ | J118: msg_fire02_03_d18r0101 | K118: GS
A119: I was so into my | C119: れんしゅうに むちゅうで | E119: 太专注于练习， | I119: 연습에 열중해서
A120: training that I | C120: あなから おっこちまったよ わはは | E120: 不小心掉进洞里了，哇哈哈 | I120: 구덩이로부터 떨어져버렸어. 와하하
A122: fell down this
A123: hole.
A125: |---英文---------+ | C125: |---日文-------------------------+ | E125: |---翻译--------------+----------+ | H125: |---提词---------+ | I125: |---注释---------+ | J125: msg_fire03_01_d18r0101 | K125: GS
...

Sheet 标
A1: |---dmap----------- | B1: |---omap----------- | C1: |---dlabel--------- | D1: |---olabel--------- | E1: |---ofname--------- | F1: |---oeom_jp-------- | G1: |---oeom_en--------
A2: data/text/std_text.asm | B2: COMMON | C2: NurseMornText | D2: msg_heal_11_common | E2: script\English\common.mg | F2: EOMeom | G2: EOMeom
A3: data/text/std_text.asm | B3: COMMON | C3: NurseDayText | D3: msg_heal_12_common | E3: script\English\common.mg | F3: EOMeom | G3: EOMeom
A4: data/text/std_text.asm | B4: COMMON | C4: NurseNiteText | D4: msg_heal_13_common | E4: script\English\common.mg | F4: EOMeom | G4: EOMeom
A5: data/text/std_text.asm | B5: COMMON | C5: PokeComNurseMornText | D5: msg_heal_11_01_common | E5: script\English\common.mg | F5: EOMeom | G5: EOMeom | I5: CR
A6: data/text/std_text.asm | B6: COMMON | C6: PokeComNurseDayText | D6: msg_heal_12_01_common | E6: script\English\common.mg | F6: EOMeom | G6: EOMeom | I6: CR
A7: data/text/std_text.asm | B7: COMMON | C7: PokeComNurseNiteText | D7: msg_heal_13_01_common | E7: script\English\common.mg | F7: EOMeom | G7: EOMeom | I7: CR
A8: data/text/std_text.asm | B8: COMMON | C8: NurseAskHealText | D8: msg_heal_01_common | E8: script\English\common.mg | F8: EOMeom | G8: EOMeom
A9: data/text/std_text.asm | B9: COMMON | C9: NurseTakePokemonText | D9: msg_heal_02_common | E9: script\English\common.mg | F9: EOMeom | G9: EOMeom
A10: data/text/std_text.asm | B10: COMMON | C10: NurseReturnPokemonText | D10: msg_heal_03_common | E10: script\English\common.mg | F10: EOMeom | G10: EOMeom
A11: data/text/std_text.asm | B11: COMMON | C11: NurseGoodbyeText | D11: msg_heal_04_common | E11: script\English\common.mg | F11: EOMeom | G11: EOMeom
A12: data/text/std_text.asm | B12: COMMON | C12: NurseSeeYouAgainTextUnused | D12: msg_heal_05_common | E12: script\English\common.mg | F12: EOMeom | G12: EOMeom
A13: data/text/std_text.asm | B13: COMMON | C13: NursePokerusText | D13: msg_heal_10_common | E13: script\English\common.mg | F13: EOMeom | G13: EOMeom
A14: data/text/std_text.asm | B14: COMMON | C14: PokeComNursePokerusText | D14: msg_heal_10_01_common | E14: script\English\common.mg | F14: EOMeom | G14: EOMeom | I14: CR
A15: data/text/std_text.asm | B15: COMMON | C15: DifficultBookshelfText | D15: msg_shelves01_common | E15: script\English\common.mg | F15: EOMeom | G15: EOMeom
A16: data/text/std_text.asm | B16: COMMON | C16: PictureBookshelfText | D16: msg_shelves02_common | E16: script\English\common.mg | F16: EOMeom | G16: EOMeom
A17: data/text/std_text.asm | B17: COMMON | C17: MagazineBookshelfText | D17: msg_shelves03_common | E17: script\English\common.mg | F17: EOMeom | G17: EOMeom
A18: data/text/std_text.asm | B18: COMMON | C18: TeamRocketOathText | D18: msg_shelves04_common | E18: script\English\common.mg | F18: EOMeom | G18: EOMeom
A19: data/text/std_text.asm | B19: COMMON | C19: IncenseBurnerText | D19: msg_butu_common | E19: script\English\common.mg | F19: EOMeom | G19: EOMeom
A20: data/text/std_text.asm | B20: COMMON | C20: MerchandiseShelfText | D20: msg_rack_common | E20: script\English\common.mg | F20: EOMeom | G20: EOMeom
A21: data/text/std_text.asm | B21: COMMON | C21: LookTownMapText | D21: msg_map_common | E21: script\English\common.mg | F21: EOMeom | G21: EOMeom
A22: data/text/std_text.asm | B22: COMMON | C22: WindowText | D22: msg_window_common | E22: script\English\common.mg | F22: EOMeom | G22: EOMeom
A23: data/text/std_text.asm | B23: COMMON | C23: TVText | D23: msg_tv_common | E23: script\English\common.mg | F23: EOMeom | G23: EOMeom
A24: data/text/std_text.asm | B24: COMMON | C24: HomepageText | D24: msg_com_common | E24: script\English\common.mg | F24: EOMeom | G24: EOMeom
A25: data/text/std_text.asm | B25: COMMON | C25: PokemonRadioTextUnused | D25: msg_radio_common | E25: script\English\common.mg | F25: EOMeom | G25: EOMeom
A26: data/text/std_text.asm | B26: COMMON | C26: TrashCanText | D26: msg_trash_common | E26: script\English\common.mg | F26: EOMeom | G26: EOMeom
... A52: data/text/std_text.asm | B52: COMMON | C52: HappinessText1 | D52: msg_friendm_03_common | E52: script\English\common.mg | F52: EOMeom | G52: EOMeom
A53: data/text/std_text.asm | B53: COMMON | C53: RegisteredNumber1Text | D53: msg_telboy_03_common | E53: script\English\common.mg | F53: EOMeom | G53: EOMeom | I53: CR
A54: data/text/std_text.asm | B54: COMMON | C54: RegisteredNumber2Text | D54: msg_telgirl_03_common | E54: script\English\common.mg | F54: EOMeom | G54: EOMeom | I54: CR
A55: data/phone/text/jack_overworld.asm | B55: COMMON | C55: JackAskNumber1Text | D55: msg_telboy01_01_d22r0101 | E55: script\English\common.mg | F55: EOMeom | G55: EOMeom | I55: CR
A56: data/phone/text/jack_overworld.asm | B56: COMMON | C56: JackAskNumber2Text | D56: msg_telboy01_02_d22r0101 | E56: script\English\common.mg | F56: EOMeom | G56: EOMeom | I56: CR
A57: data/phone/text/jack_overworld.asm | B57: COMMON | C57: JackNumberAcceptedText | D57: msg_telboy01_04_d22r0101 | E57: script\English\common.mg | F57: EOMeom | G57: EOMeom | I57: CR
A58: data/phone/text/jack_overworld.asm | B58: COMMON | C58: JackNumberDeclinedText | D58: msg_telboy01_05_d22r0101 | E58: script\English\common.mg | F58: EOMeom | G58: EOMeom | I58: CR
A59: data/phone/text/jack_overworld.asm | B59: COMMON | C59: JackPhoneFullText | D59: msg_telboy01_06_d22r0101 | E59: script\English\common.mg | F59: EOMeom | G59: EOMeom | I59: CR
A60: data/phone/text/jack_overworld.asm | B60: COMMON | C60: JackRematchText | D60: msg_telboy01_07_d22r0101 | E60: script\English\common.mg | F60: EOMeom | G60: EOMeom | I60: CR
A61: data/phone/text/beverly_overworld.asm | B61: COMMON | C61: BeverlyAskNumber1Text | D61: msg_telgirl01_01_d22r0101 | E61: script\English\common.mg | F61: EOMeom | G61: EOMeom | I61: CR
A62: data/phone/text/beverly_overworld.asm | B62: COMMON | C62: BeverlyAskNumber2Text | D62: msg_telgirl01_02_d22r0101 | E62: script\English\common.mg | F62: EOMeom | G62: EOMeom | I62: CR
A63: data/phone/text/beverly_overworld.asm | B63: COMMON | C63: BeverlyNumberAcceptedText | D63: msg_telgirl01_04_d22r0101 | E63: script\English\common.mg | F63: EOMeom | G63: EOMeom | I63: CR
A64: data/phone/text/beverly_overworld.asm | B64: COMMON | C64: BeverlyNumberDeclinedText | D64: msg_telgirl01_05_d22r0101 | E64: script\English\common.mg | F64: EOMeom | G64: EOMeom | I64: CR
... A141: data/phone/text/todd_overworld.asm | B141: COMMON2 | C141: ToddRematchText | D141: msg_telboy01_07_r34 | E141: script\English\common2.mg | F141: EOMeom | G141: EOMeom | I141: CR
A142: data/phone/text/todd_overworld.asm | B142: COMMON2 | C142: ToddSaleText | D142: msg_telboy01_11_r34_UN | E142: script\English\common2.mg | F142: EOMeom | G142: EOMeom | H142: =D2592 -> msg_telboy01_11_r34 | I142: CR
A143: data/phone/text/gina_overworld.asm | B143: COMMON2 | C143: GinaAskNumber1Text | D143: msg_telgirl01_01_r34 | E143: script\English\common2.mg | F143: EOMeom | G143: EOMeom | I143: CR
A144: data/phone/text/gina_overworld.asm | B144: COMMON2 | C144: GinaAskNumber2Text | D144: msg_telgirl01_02_r34 | E144: script\English\common2.mg | F144: EOMeom | G144: EOMeom | I144: CR
A145: data/phone/text/gina_overworld.asm | B145: COMMON2 | C145: GinaNumberAcceptedText | D145: msg_telgirl01_04_r34 | E145: script\English\common2.mg | F145: EOMeom | G145: EOMeom | I145: CR
A146: data/phone/text/gina_overworld.asm | B146: COMMON2 | C146: GinaNumberDeclinedText | D146: msg_telgirl01_05_r34 | E146: script\English\common2.mg | F146: EOMeom | G146: EOMeom | I146: CR
A147: data/phone/text/gina_overworld.asm | B147: COMMON2 | C147: GinaPhoneFullText | D147: msg_telgirl01_06_r34 | E147: script\English\common2.mg | F147: EOMeom | G147: EOMeom | I147: CR
A148: data/phone/text/gina_overworld.asm | B148: COMMON2 | C148: GinaRematchText | D148: msg_telgirl01_07_r34 | E148: script\English\common2.mg | F148: EOMeom | G148: EOMeom | I148: CR
A149: data/phone/text/gina_overworld.asm | B149: COMMON2 | C149: GinaGiftText | D149: msg_telgirl01_08_r34 | E149: script\English\common2.mg | F149: EOMeom | G149: EOMeom | I149: CR
A150: data/phone/text/gina_overworld.asm | B150: COMMON2 | C150: GinaPackFullText | D150: msg_telgirl01_09_r34 | E150: script\English\common2.mg | F150: EOMeom | G150: EOMeom | I150: CR
A151: data/phone/text/irwin_overworld.asm | B151: COMMON2 | C151: IrwinAskNumber1Text | D151: msg_telboy01_01_r35 | E151: script\English\common2.mg | F151: EOMeom | G151: EOMeom | I151: CR
A152: data/phone/text/irwin_overworld.asm | B152: COMMON2 | C152: IrwinAskNumber2Text | D152: msg_telboy01_02_r35 | E152: script\English\common2.mg | F152: EOMeom | G152: EOMeom | I152: CR
A153: data/phone/text/irwin_overworld.asm | B153: COMMON2 | C153: IrwinNumberAcceptedText | D153: msg_telboy01_04_r35 | E153: script\English\common2.mg | F153: EOMeom | G153: EOMeom | I153: CR
A154: data/phone/text/irwin_overworld.asm | B154: COMMON2 | C154: IrwinNumberDeclinedText | D154: msg_telboy01_05_r35 | E154: script\English\common2.mg | F154: EOMeom | G154: EOMeom | I154: CR
... A251: data/phone/text/erin_overworld.asm | B251: COMMON2 | C251: ErinRematchGiftText | D251: msg_telgirl01_10_r46 | E251: script\English\common2.mg | F251: EOMeom | G251: EOMeom | I251: CR
A252: maps/DiglettsCave.asm | B252: D01R0101 | C252: DiglettsCavePokefanMText | D252: msg_middlem_00_d01r0101 | E252: script\English\d01r0101.mg | F252: EOMeom | G252: EOMeom
A253: maps/MountMoon.asm | B253: D02R0101 | C253: MountMoonRivalTextBefore | D253: msg_rival_01_d02r0101 | E253: script\English\d02r0101.mg | F253: EOMeom | G253: EOMeom
A254: maps/MountMoon.asm | B254: D02R0101 | C254: MountMoonRivalTextWin | D254: msg_rival_02_d02r0101 | E254: script\English\d02r0101.mg | F254: EOMeom | G254: EOMeom
A255: maps/MountMoon.asm | B255: D02R0101 | C255: MountMoonRivalTextAfter | D255: msg_rival_03_d02r0101 | E255: script\English\d02r0101.mg | F255: EOMeom | G255: EOMeom
A256: maps/MountMoon.asm | B256: D02R0101 | C256: MountMoonRivalTextLoss | D256: msg_rival_04_d02r0101 | E256: script\English\d02r0101.mg | F256: EOMeom | G256: EOMeom
A257: maps/SproutTower1F.asm | B257: D15R0101 | C257: SageChowSeenText | D257: msg_bouzu01_01_d15r0101 | E257: script\English\d15r0101.mg | F257: EOMeom | G257: EOMeom
A258: maps/SproutTower1F.asm | B258: D15R0101 | C258: SageChowBeatenText | D258: msg_bouzu01_02_d15r0101 | E258: script\English\d15r0101.mg | F258: EOMeom | G258: EOMeom
A259: maps/SproutTower1F.asm | B259: D15R0101 | C259: SageChowAfterBattleText | D259: msg_bouzu01_03_d15r0101 | E259: script\English\d15r0101.mg | F259: EOMeom | G259: EOMeom
A260: maps/SproutTower1F.asm | B260: D15R0101 | C260: SproutTower1FSage1Text | D260: msg_bouzu01_00_d15r0101 | E260: script\English\d15r0101.mg | F260: EOMeom | G260: EOMeom
A261: maps/SproutTower1F.asm | B261: D15R0101 | C261: SproutTower1FSage2Text | D261: msg_bouzu02_00_d15r0101 | E261: script\English\d15r0101.mg | F261: EOMeom | G261: EOMeom
A262: maps/SproutTower1F.asm | B262: D15R0101 | C262: SproutTower1FGrannyText | D262: msg_oldwoman_00_d15r0101 | E262: script\English\d15r0101.mg | F262: EOMeom | G262: EOMeom
A263: maps/SproutTower1F.asm | B263: D15R0101 | C263: SproutTower1FTeacherText | D263: msg_womana_00_d15r0101 | E263: script\English\d15r0101.mg | F263: EOMeom | G263: EOMeom
... A280: maps/SproutTower3F.asm | B280: D15R0103 | C280: SageJinSeenText | D280: msg_bouzu03_01_d15r0103 | E280: script\English\d15r0103.mg | F280: EOMeom | G280: EOMeom
A281: maps/SproutTower3F.asm | B281: D15R0103 | C281: SageJinBeatenText | D281: msg_bouzu03_02_d15r0103 | E281: script\English\d15r0103.mg | F281: EOMeom | G281: EOMeom | I281: CR
A282: maps/SproutTower3F.asm | B282: D15R0103 | C282: SageJinAfterBattleText | D282: msg_bouzu03_03_d15r0103 | E282: script\English\d15r0103.mg | F282: EOMeom | G282: EOMeom
A283: maps/SproutTower3F.asm | B283: D15R0103 | C283: SageTroySeenText | D283: msg_bouzu04_01_d15r0103 | E283: script\English\d15r0103.mg | F283: EOMeom | G283: EOMeom
A284: maps/SproutTower3F.asm | B284: D15R0103 | C284: SageTroyBeatenText | D284: msg_bouzu04_02_d15r0103 | E284: script\English\d15r0103.mg | F284: EOMeom | G284: EOMeom
A285: maps/SproutTower3F.asm | B285: D15R0103 | C285: SageTroyAfterBattleText | D285: msg_bouzu04_03_d15r0103 | E285: script\English\d15r0103.mg | F285: EOMeom | G285: EOMeom
A286: maps/SproutTower3F.asm | B286: D15R0103 | C286: SageNealSeenText | D286: msg_bouzu08_01_d15r0103 | E286: script\English\d15r0103.mg | F286: EOMeom | G286: EOMeom
A287: maps/SproutTower3F.asm | B287: D15R0103 | C287: SageNealBeatenText | D287: msg_bouzu08_02_d15r0103 | E287: script\English\d15r0103.mg | F287: EOMeom | G287: EOMeom
A288: maps/SproutTower3F.asm | B288: D15R0103 | C288: SageNealAfterBattleText | D288: msg_bouzu08_03_d15r0103 | E288: script\English\d15r0103.mg | F288: EOMeom | G288: EOMeom
A289: maps/SproutTower3F.asm | B289: D15R0103 | C289: SproutTower3FPaintingText | D289: msg_fresco_00_d15r0103 | E289: script\English\d15r0103.mg | F289: EOMeom | G289: EOMeom
A290: maps/SproutTower3F.asm | B290: D15R0103 | C290: SproutTower3FStatueText | D290: msg_statue_00_d15r0103 | E290: script\English\d15r0103.mg | F290: EOMeom | G290: EOMeom
A291: maps/TinTower1F.asm | B291: D17R0101 | C291: TinTower1FEusineSuicuneText | D291: msg_minaki_01_d17r0101 | E291: script\English\d17r0101.mg | F291: EOMeom | G291: EOMeom | I291: CR
A292: maps/TinTower1F.asm | B292: D17R0101 | C292: TinTower1FSage1Text | D292: msg_bouzu01_01_d17r0101 | E292: script\English\d17r0101.mg | F292: EOMeom | G292: EOMeom | I292: CR
A293: maps/TinTower1F.asm | B293: D17R0101 | C293: TinTower1FSage2Text | D293: msg_bouzu02_01_d17r0101 | E293: script\English\d17r0101.mg | F293: EOMeom | G293: EOMeom | I293: CR
A294: maps/TinTower1F.asm | B294: D17R0101 | C294: TinTower1FSage3Text | D294: msg_bouzu03_01_d17r0101 | E294: script\English\d17r0101.mg | F294: EOMeom | G294: EOMeom | I294: CR
A295: maps/TinTower1F.asm | B295: D17R0101 | C295: TinTower1FSage4Text1 | D295: msg_bouzu01_02_d17r0101 | E295: script\English\d17r0101.mg | F295: EOMeom | G295: EOMeom | I295: CR
A296: maps/TinTower1F.asm | B296: D17R0101 | C296: TinTower1FSage5Text1 | D296: msg_bouzu02_02_d17r0101 | E296: script\English\d17r0101.mg | F296: EOMeom | G296: EOMeom | I296: CR
A297: maps/TinTower1F.asm | B297: D17R0101 | C297: TinTower1FSage5Text2 | D297: msg_bouzu02_02_d17r0101_1 | E297: script\English\d17r0101.mg | F297: EOMeom | G297: EOMeom | I297: CR
A298: maps/TinTower1F.asm | B298: D17R0101 | C298: TinTower1FSage6Text1 | D298: msg_bouzu03_02_d17r0101 | E298: script\English\d17r0101.mg | F298: EOMeom | G298: EOMeom | I298: CR
A299: maps/TinTower1F.asm | B299: D17R0101 | C299: TinTower1FEusineHoOhText | D299: msg_minaki_03_d17r0101 | E299: script\English\d17r0101.mg | F299: EOMeom | G299: EOMeom | I299: CR
A300: maps/TinTower1F.asm | B300: D17R0101 | C300: TinTower1FSage4Text2 | D300: msg_bouzu01_03_d17r0101 | E300: script\English\d17r0101.mg | F300: EOMeom | G300: EOMeom | I300: CR
A301: maps/TinTower1F.asm | B301: D17R0101 | C301: TinTower1FSage5Text3 | D301: msg_bouzu02_03_d17r0101 | E301: script\English\d17r0101.mg | F301: EOMeom | G301: EOMeom | I301: CR
A302: maps/TinTower1F.asm | B302: D17R0101 | C302: TinTower1FSage6Text2 | D302: msg_bouzu03_03_d17r0101 | E302: script\English\d17r0101.mg | F302: EOMeom | G302: EOMeom | I302: CR
A303: maps/TinTower9F.asm | B303: D17R0109 | C303: TinTower9FUnusedHoOhText | D303: msg_legend01_00_d17r0109 | E303: script\English\d17r0109.mg | F303: EOMeom | G303: EOMeom
A304: maps/TinTower9F.asm | B304: D17R0109 | C304: TinTower9FUnusedLugiaText | D304: msg_legend02_00_d17r0109 | E304: script\English\d17r0109.mg | F304: EOMeom | G304: EOMeom
A305: maps/BurnedTower1F.asm | B305: D18R0101 | C305: BurnedTowerRival_BeforeText | D305: msg_rival_01_d18r0101 | E305: script\English\d18r0101.mg | F305: EOMeom | G305: EOMeom | I305: CR
A306: maps/BurnedTower1F.asm | B306: D18R0101 | C306: BurnedTowerRival_WinText | D306: msg_rival_02_d18r0101 | E306: script\English\d18r0101.mg | F306: EOMeom | G306: EOMeom
A307: maps/BurnedTower1F.asm | B307: D18R0101 | C307: BurnedTowerRival_AfterText1 | D307: msg_rival_03_d18r0101 | E307: script\English\d18r0101.mg | F307: EOMeom | G307: EOMeom
A308: maps/BurnedTower1F.asm | B308: D18R0101 | C308: BurnedTowerRival_LossText | D308: msg_rival_04_d18r0101 | E308: script\English\d18r0101.mg | F308: EOMeom | G308: EOMeom
A309: maps/BurnedTower1F.asm | B309: D18R0101 | C309: BurnedTowerRival_AfterText2 | D309: msg_rival_05_d18r0101 | E309: script\English\d18r0101.mg | F309: EOMeom | G309: EOMeom | I309: CR
A310: maps/BurnedTower1F.asm | B310: D18R0101 | C310: BurnedTower1FEusineIntroText | D310: msg_minaki_01_d18r0101 | E310: script\English\d18r0101.mg | F310: EOMeom | G310: EOMeom | I310: CR
A311: maps/BurnedTower1F.asm | B311: D18R0101 | C311: BurnedTower1FEusineText | D311: msg_minaki_02_d18r0101 | E311: script\English\d18r0101.mg | F311: EOMeom | G311: EOMeom | I311: CR
A312: maps/BurnedTower1F.asm | B312: D18R0101 | C312: BurnedTower1FMortyText | D312: msg_matuba_01_d18r0101 | E312: script\English\d18r0101.mg | F312: EOMeom | G312: EOMeom | I312: CR
A313: maps/BurnedTowerB1F.asm | B313: D18R0102 | C313: BurnedTowerB1FEusineText | D313: msg_minaki_01_d18r0102 | E313: script\English\d18r0102.mg | F313: EOMeom | G313: EOMeom | I313: CR
...

Sheet Sheet
